Workbook

Sheet LEEME_CIERRE
A1: IA + TEA | Cierre analitico
A2: Version congelada: 8 septiembre 2026 | Una referencia = un informe; no una cohorte independiente.
A4: Control | B4: Valor | C4: Interpretacion
A5: Registros conservados | B5: =COUNTA('BASE_CIERRE'!$A$5:$A$458) -> 454 | C5: Todos los registros originales permanecen auditables; no se borraron filas.
A6: Incluidos en sintesis principal | B6: =COUNTIFS('BASE_CIERRE'!$G$5:$G$458,1) -> 428 | C6: Corpus ampliado tras 26 exclusiones documentadas. No equivale a 428 estudios verificados en texto completo en esta pasada.
A7: Exclusiones de esta auditoria | B7: =COUNTIFS('BASE_CIERRE'!$F$5:$F$458,"Exclude") -> 26 | C7: Tipos no elegibles, ausencia de IA pertinente, tema/poblacion fuera de alcance y dos retractados.
A8: Etapa clinica resuelta | B8: =COUNTIFS('BASE_CIERRE'!$AF$5:$AF$458,1) -> 397 | C8: Base de los porcentajes por las cinco etapas; 31 informes sin etapa unica permanecen en el corpus.
A9: Uso de IA evaluado | B9: =COUNTIFS('BASE_CIERRE'!$G$5:$G$458,1,'BASE_CIERRE'!$M$5:$M$458,"Evaluated at point of use")+COUNTIFS('BASE_CIERRE'!$G$5:$G$458,1,'BASE_CIERRE'!$M$5:$M$458,"Evaluated AI-supported intervention")+COUNTIFS('BASE_CIERRE'!$G$5:$G$458,1,'BASE_CIERRE'!$M$5:$M$458,"Evaluated care-delivery platform") -> 19 | C9: 8 evaluaciones en punto de uso, 10 intervenciones y 1 plataforma de atencion; no implica eficacia clinica demostrada.
A10: Sin alertas editoriales | B10: =COUNTIFS('BASE_CIERRE'!$AD$5:$AD$458,1) -> 426 | C10: Excluye dos expresiones de preocupacion, ademas de los retractados ya excluidos.
A11: Sensibilidad conservadora | B11: =COUNTIFS('BASE_CIERRE'!$AE$5:$AE$458,1) -> 410 | C11: Excluye alertas editoriales y 16 cautelas adicionales de alcance/fuente.
A12: Sensibilidad de etapa directa | B12: =COUNTIFS('BASE_CIERRE'!$AG$5:$AG$458,1) -> 385 | C12: Subconjunto conservador con una de las cinco etapas clinicas resuelta.
A13: Verificacion humana de esta recodificacion | B13: No documentada | C13: No atribuir esta auditoria a los dos revisores ni afirmar concordancia independiente.
A14: PRISMA inicial | B14: No reconstruible | C14: El manuscrito informa 282; la base historica contiene 276. Falta trazabilidad de seis referencias y del flujo inicial.
A15: Entrada de los scripts | B15: BASE_CIERRE | C15: Las hojas originales estan ocultas como archivo. No mezclar con los antiguos XLSX ni con las cifras 282/273/260.
A16: Inicio para redactar | B16: RESULTADOS_EN | C16: Texto en ingles, tablas con denominadores, limitaciones y reemplazos numericos. No se reescribio el manuscrito original.
A18: RESUMEN_CIERRE | B18: Abrir | C18: Distribuciones y denominadores recalculables.
A19: RQ1_PERFILES | B19: Abrir | C19: Tecnica x fuente x etapa; incluye todos los perfiles.
A20: RQ2_INTEGRACION | B20: Abrir | C20: Etapa, madurez de uso, rol y momento de decision.
A21: RQ3_PRACTICAS | B21: Abrir | C21: Cuatro practicas principales y analisis estricto adicional.
A22: RQ3_PERFILES | B22: Abrir | C22: Numeradores, no reportados e indeterminados en cada perfil.
A23: SENSIBILIDAD | B23: Abrir | C23: Robustez de los conteos a alertas y criterios conservadores.
A24: EVIDENCIA_CIERRE | B24: Abrir | C24: Fuentes, texto original, notas y procedencia de las correcciones.
A25: CAMBIOS_CIERRE | B25: Abrir | C25: Antes/despues por campo; 2,449 cambios trazables.
... A27: VALIDACION | B27: Abrir | C27: Controles computacionales; no auditoria humana ficticia.

Sheet BASE_CIERRE
A1: Base unica de analisis
A2: Modificar solamente codigos basados en evidencia; todos los resumenes se derivan de esta hoja. Las columnas de inclusion son formulas.
A4: study_id | B4: cohort | C4: title | D4: doi | E4: year | F4: eligibility | G4: include_main | H4: stage_primary | I4: ai_type | J4: data_source_primary | K4: algorithm_main | L4: algorithm_family | M4: rq2_status | N4: rq2_role | O4: decision_timing_coded | P4: observed_decision_timing | Q4: external_validation | R4: multisource_integration | S4: xai_broad | T4: xai_strict | U4: cross_site_robustness | V4: multisite_dataset | W4: multisource_data | X4: prospective_evaluation | Y4: prospective_data_collection | Z4: xai_partial | AA4: integrity_status | AB4: integrity_caution | AC4: source_scope_caution | AD4: include_no_editorial_alert | AE4: include_conservative | AF4: stage_resolved | AG4: include_direct_stage_sensitivity | AH4: source_level | AI4: source_url | AJ4: source_locator | AK4: rationale | AL4: exclusion_reason | AM4: endpoint_level | AN4: source_scope_caution_detail | AO4: publication_status_update | AP4: independent_human_verification | AQ4: assessor | AR4: original_reviewer | AS4: original_access_status
A5: 1 | B5: Historical | C5: A Clinically Interpretable Approach for Early Detection of Autism Using Machine Learning With Explainable AI | D5: 10.1109/access.2025.3586314 | E5: 2025 | F5: Include | G5: =IF(F5="Include",1,0) -> 1 | H5: Screening | I5: Machine Learning | J5: Structured clinical/questionnaire data | K5: Random Forest | L5: Random forest | M5: Proposed only | N5: Triage/questionnaire assessment | O5: Pre-decision | P5: Not observed in assessed sources | Q5: Not reported in assessed sources | R5: Not reported in assessed sources | S5: Reported | T5: Reported | U5: Not reported in assessed sources | V5: Not reported in assessed sources | W5: Not reported in assessed sources | X5: Not reported in assessed sources | Y5: Not ascertainable | Z5: Not reported in assessed sources | AA5: Not recorded | AB5: 0 | AC5: 0 | AD5: =IF(AND(G5=1,AB5=0),1,0) -> 1 | AE5: =IF(AND(AD5=1,AC5=0),1,0) -> 1 | AF5: =IF(AND(G5=1,H5<>"Not specified"),1,0) -> 1 | AG5: =IF(AND(AE5=1,AF5=1),1,0) -> 1 | AH5: Supplied abstract/coding notes; no new full-text verification | AI5: https://doi.org/10.1109/access.2025.3586314 | AJ5: EVIDENCIA; original abstract/coding notes and lot source trace; Historical signals: title/abstract/notes; full-text completion not independently established | AK5: Public age-specific screening datasets; five-fold CV and SHAP. Physician interpretation is proposed, not evaluated in a clinical workflow. Background mentions do not establish five clinical stages. | AL5: Not applicable | AM5: Not separately specified | AO5: No additional status determination | AP5: Not documented for this recharting | AQ5: ChatGPT-assisted evidence recharting, 2026-09-08 | AS5: Not recorded; historical inclusion retained
A6: 2 | B6: Historical | C6: Searching for a minimal set of behaviors for autism detection through feature selection-based machine learning | D6: 10.1038/tp.2015.7 | E6: 2015 | F6: Include | G6: =IF(F6="Include",1,0) -> 1 | H6: Screening | I6: Machine Learning | J6: Structured clinical/questionnaire data | K6: Multiple algorithms compared (8; primary not specified) | L6: Multiple/not uniquely specified | M6: Proposed only | N6: Triage/questionnaire assessment | O6: Pre-decision | P6: Not observed in assessed sources | Q6: Not reported in assessed sources | R6: Not reported in assessed sources | S6: Reported | T6: Not reported in assessed sources | U6: Not reported in assessed sources | V6: Not reported in assessed sources | W6: Not reported in assessed sources | X6: Not reported in assessed sources | Y6: Not ascertainable | Z6: Reported | AA6: Not recorded | AB6: 0 | AC6: 0 | AD6: =IF(AND(G6=1,AB6=0),1,0) -> 1 | AE6: =IF(AND(AD6=1,AC6=0),1,0) -> 1 | AF6: =IF(AND(G6=1,H6<>"Not specified"),1,0) -> 1 | AG6: =IF(AND(AE6=1,AF6=1),1,0) -> 1 | AH6: Supplied abstract/coding notes; no new full-text verification | AI6: https://doi.org/10.1038/tp.2015.7 | AJ6: EVIDENCIA; original abstract/coding notes and lot source trace; Historical signals: title/abstract/notes; full-text completion not independently established | AK6: ADOS score sheets are structured behavioral records, not unspecified data. The reduced behavioral set is proposed for preliminary triage; no prospective use of the resulting model is described. | AL6: Not applicable | AM6: Not separately specified | AO6: No additional status determination | AP6: Not documented for this recharting | AQ6: ChatGPT-assisted evidence recharting, 2026-09-08 | AR6: RA | AS6: Not recorded; historical inclusion retained
A7: 3 | B7: Historical | C7: The use of data independent acquisition based proteomic analysis and machine learning to reveal potential biomarkers for autism spectrum disorder | D7: 10.1016/j.jprot.2023.104872 | E7: 2023 | F7: Include | G7: =IF(F7="Include",1,0) -> 1 | H7: Diagnosis | I7: Machine Learning | J7: Biological/omics | K7: Not specified | L7: Multiple/not uniquely specified | M7: Research only | N7: Automated measurement/classification | O7: Not observed in assessed sources | P7: Not observed in assessed sources | Q7: Reported | R7: Not reported in assessed sources | S7: Not reported in assessed sources | T7: Not reported in assessed sources | U7: Not reported in assessed sources | V7: Not reported in assessed sources | W7: Not reported in assessed sources | X7: Not reported in assessed sources | Y7: Not ascertainable | Z7: Not reported in assessed sources | AA7: Not recorded | AB7: 0 | AC7: 0 | AD7: =IF(AND(G7=1,AB7=0),1,0) -> 1 | AE7: =IF(AND(AD7=1,AC7=0),1,0) -> 1 | AF7: =IF(AND(G7=1,H7<>"Not specified"),1,0) -> 1 | AG7: =IF(AND(AE7=1,AF7=1),1,0) -> 1 | AH7: Supplied abstract/coding notes; no new full-text verification | AI7: https://doi.org/10.1016/j.jprot.2023.104872 | AJ7: EVIDENCIA; original abstract/coding notes and lot source trace; Historical signals: title/abstract/notes; full-text completion not independently established | AK7: Plasma proteomics with DIA/MRM and machine-learning biomarker selection. Molecular assay verification alone does not establish external validation of the predictive model. | AL7: Not applicable | AM7: Not separately specified | AO7: No additional status determination | AP7: Not documented for this recharting | AQ7: ChatGPT-assisted evidence recharting, 2026-09-08 | AR7: RA | AS7: Not recorded; historical inclusion retained
A8: 4 | B8: Historical | C8: Cognitive Disorder Detection Used for Early Autism Screening Using Deep Learning | D8: 10.1007/978-981-96-3942-7_18 | E8: 2025 | F8: Exclude | G8: =IF(F8="Include",1,0) -> 0 | H8: Excluded | I8: Excluded | J8: Excluded | K8: MLP | L8: MLP/ANN | M8: Excluded | N8: Excluded | O8: Not applicable - excluded | P8: Not applicable - excluded | Q8: Not reported in assessed sources | R8: Not reported in assessed sources | S8: Not reported in assessed sources | T8: Not reported in assessed sources | U8: Not reported in assessed sources | V8: Not reported in assessed sources | W8: Not reported in assessed sources | X8: Not reported in assessed sources | Y8: Not ascertainable | Z8: Not reported in assessed sources | AA8: Not recorded | AB8: 0 | AC8: 0 | AD8: =IF(AND(G8=1,AB8=0),1,0) -> 0 | AE8: =IF(AND(AD8=1,AC8=0),1,0) -> 0 | AF8: =IF(AND(G8=1,H8<>"Not specified"),1,0) -> 0 | AG8: =IF(AND(AE8=1,AF8=1),1,0) -> 0 | AH8: Publisher abstract and bibliographic metadata | AI8: https://link.springer.com/chapter/10.1007/978-981-96-3942-7_18 | AJ8: Publisher abstract and references | AK8: The abstract describes CATest validation for mild cognitive disorder, Alzheimer disease and other neurological conditions rather than empirical ASD-specific modeling. Title wording alone does not establish eligibility. | AL8: EC2 - Wrong condition / population | AM8: Not separately specified | AO8: No additional status determination | AP8: Not documented for this recharting | AQ8: ChatGPT-assisted evidence recharting, 2026-09-08 | AS8: Not recorded; historical inclusion retained
A9: 5 | B9: Historical | C9: Metabolomics as a tool for discovery of biomarkers of autism spectrum disorder in the blood plasma of children | D9: 10.1371/journal.pone.0112445 | E9: 2014 | F9: Include | G9: =IF(F9="Include",1,0) -> 1 | H9: Diagnosis | I9: Machine Learning | J9: Biological/omics | K9: SVM / PLS-DA | L9: SVM | M9: Research only | N9: Automated measurement/classification | O9: Not observed in assessed sources | P9: Not observed in assessed sources | Q9: Not reported in assessed sources | R9: Reported | S9: Reported | T9: Not reported in assessed sources | U9: Not reported in assessed sources | V9: Not reported in assessed sources | W9: Reported | X9: Not reported in assessed sources | Y9: Not ascertainable | Z9: Reported | AA9: Not recorded | AB9: 0 | AC9: 0 | AD9: =IF(AND(G9=1,AB9=0),1,0) -> 1 | AE9: =IF(AND(AD9=1,AC9=0),1,0) -> 1 | AF9: =IF(AND(G9=1,H9<>"Not specified"),1,0) -> 1 | AG9: =IF(AND(AE9=1,AF9=1),1,0) -> 1 | AH9: Primary-source full text (targeted sections) | AI9: https://journals.plos.org/plosone/article?id=10.1371/journal.pone.0112445 | AJ9: Methods: Training and Independent Validation Sets; Classification Modeling; Results: Validation Set Model Performance | AK9: Metabolomic classification and feature-ranking study. The held-out 21 participants were randomly partitioned from the same 82-participant cohort; this is internal holdout validation, despite the authors' external-sample terminology. | AL9: Not applicable | AM9: Not separately specified | AO9: No additional status determination | AP9: Not documented for this recharting | AQ9: ChatGPT-assisted evidence recharting, 2026-09-08 | AR9: RA | AS9: Not recorded; historical inclusion retained
A10: 6 | B10: Historical | C10: Sparsifying machine learning models identify stable subsets of predictive features for behavioral detection of autism | D10: 10.1186/s13229-017-0180-6 | E10: 2017 | F10: Include | G10: =IF(F10="Include",1,0) -> 1 | H10: Screening | I10: Machine Learning | J10: Structured clinical/questionnaire data | K10: Multiple sparse models (logistic regression / linear SVM) | L10: Composite/ensemble pipeline | M10: Proposed only | N10: Triage/questionnaire assessment | O10: Pre-decision | P10: Not observed in assessed sources | Q10: Not reported in assessed sources | R10: Not reported in assessed sources | S10: Reported | T10: Not reported in assessed sources | U10: Not reported in assessed sources | V10: Not reported in assessed sources | W10: Not reported in assessed sources | X10: Not reported in assessed sources | Y10: Not ascertainable | Z10: Reported | AA10: Not recorded | AB10: 0 | AC10: 0 | AD10: =IF(AND(G10=1,AB10=0),1,0) -> 1 | AE10: =IF(AND(AD10=1,AC10=0),1,0) -> 1 | AF10: =IF(AND(G10=1,H10<>"Not specified"),1,0) -> 1 | AG10: =IF(AND(AE10=1,AF10=1),1,0) -> 1 | AH10: Supplied abstract/coding notes; no new full-text verification | AI10: https://doi.org/10.1186/s13229-017-0180-6 | AJ10: EVIDENCIA; original abstract/coding notes and lot source trace; Historical signals: title/abstract/notes; full-text completion not independently established | AK10: ADOS score sheets and demographic covariates; sparse models intended to shorten assessment. No clinical use of predictions is evaluated. Comparing ML models is not hybrid ML/DL integration. | AL10: Not applicable | AM10: Not separately specified | AO10: No additional status determination | AP10: Not documented for this recharting | AQ10: ChatGPT-assisted evidence recharting, 2026-09-08 | AS10: Not recorded; historical inclusion retained
A11: 7 | B11: Historical | C11: Transformer-based deep learning ensemble framework predicts autism spectrum disorder using health administrative and birth registry data | D11: 10.1038/s41598-025-90216-8 | E11: 2025 | F11: Include | G11: =IF(F11="Include",1,0) -> 1 | H11: Prognosis | I11: Deep Learning | J11: Structured clinical/questionnaire data | K11: Transformer ensemble | L11: Transformer | M11: Proposed only | N11: Risk/trajectory estimation | O11: Pre-decision | P11: Not observed in assessed sources | Q11: Not reported in assessed sources | R11: Reported | S11: Reported | T11: Not ascertainable | U11: Not reported in assessed sources | V11: Not reported in assessed sources | W11: Reported | X11: Not reported in assessed sources | Y11: Not ascertainable | Z11: Reported | AA11: Not recorded | AB11: 0 | AC11: 0 | AD11: =IF(AND(G11=1,AB11=0),1,0) -> 1 | AE11: =IF(AND(AD11=1,AC11=0),1,0) -> 1 | AF11: =IF(AND(G11=1,H11<>"Not specified"),1,0) -> 1 | AG11: =IF(AND(AE11=1,AF11=1),1,0) -> 1 | AH11: Supplied abstract/coding notes; no new full-text verification | AI11: https://doi.org/10.1038/s41598-025-90216-8 | AJ11: EVIDENCIA; original abstract/coding notes and lot source trace; Historical signals: title/abstract/notes; full-text completion not independently established | AK11: Linked maternal-newborn administrative and registry records predict a future ASD diagnosis at 18-60 months. Population prescreening is a proposed use; the implemented endpoint is prognostic. | AL11: Not applicable | AM11: Not separately specified | AO11: No additional status determination | AP11: Not documented for this recharting | AQ11: ChatGPT-assisted evidence recharting, 2026-09-08 | AR11: RA | AS11: Not recorded; historical inclusion retained
A12: 8 | B12: Historical | C12: A Closed-Loop Ear-Worn Wearable EEG System with Real-Time Passive Electrode Skin Impedance Measurement for Early Autism Detection † | D12: 10.3390/s24237489 | E12: 2024 | F12: Include | G12: =IF(F12="Include",1,0) -> 1 | H12: Screening | I12: Machine Learning | J12: Physiological signals | K12: Not specified | L12: Multiple/not uniquely specified | M12: Proposed only | N12: Mobile assessment | O12: Pre-decision | P12: Not observed in assessed sources | Q12: Not reported in assessed sources | R12: Not reported in assessed sources | S12: Not reported in assessed sources | T12: Not reported in assessed sources | U12: Not reported in assessed sources | V12: Not reported in assessed sources | W12: Not reported in assessed sources | X12: Not reported in assessed sources | Y12: Not ascertainable | Z12: Not reported in assessed sources | AA12: Not recorded | AB12: 0 | AC12: 0 | AD12: =IF(AND(G12=1,AB12=0),1,0) -> 1 | AE12: =IF(AND(AD12=1,AC12=0),1,0) -> 1 | AF12: =IF(AND(G12=1,H12<>"Not specified"),1,0) -> 1 | AG12: =IF(AND(AE12=1,AF12=1),1,0) -> 1 | AH12: Supplied abstract/coding notes; no new full-text verification | AI12: https://doi.org/10.3390/s24237489 | AJ12: EVIDENCIA; original abstract/coding notes and lot source trace; Historical signals: title/abstract/notes; full-text completion not independently established | AK12: Ear-worn EEG hardware with on-chip classification is bench-tested using the Old Dominion University ASD dataset. A deployed wearable screening workflow is proposed, not demonstrated by a real-time hardware benchmark. | AL12: Not applicable | AM12: Not separately specified | AO12: No additional status determination | AP12: Not documented for this recharting | AQ12: ChatGPT-assisted evidence recharting, 2026-09-08 | AS12: Not recorded; historical inclusion retained
A13: 9 | B13: Historical | C13: An automated assessment framework for atypical prosody and stereotyped idiosyncratic phrases related to autism spectrum disorder | D13: 10.1016/j.csl.2018.11.002 | E13: 2019 | F13: Include | G13: =IF(F13="Include",1,0) -> 1 | H13: Diagnosis | I13: Hybrid | J13: Audio/voice | K13: CNN/RNN and SVM | L13: Composite/ensemble pipeline | M13: Research only | N13: Automated measurement/classification | O13: Not observed in assessed sources | P13: Not observed in assessed sources | Q13: Not reported in assessed sources | R13: Not ascertainable | S13: Not reported in assessed sources | T13: Not reported in assessed sources | U13: Not reported in assessed sources | V13: Not reported in assessed sources | W13: Reported | X13: Not reported in assessed sources | Y13: Not ascertainable | Z13: Not reported in assessed sources | AA13: Not recorded | AB13: 0 | AC13: 0 | AD13: =IF(AND(G13=1,AB13=0),1,0) -> 1 | AE13: =IF(AND(AD13=1,AC13=0),1,0) -> 1 | AF13: =IF(AND(G13=1,H13<>"Not specified"),1,0) -> 1 | AG13: =IF(AND(AE13=1,AF13=1),1,0) -> 1 | AH13: Supplied abstract/coding notes; no new full-text verification | AI13: https://doi.org/10.1016/j.csl.2018.11.002 | AJ13: EVIDENCIA; original abstract/coding notes and lot source trace; Historical signals: title/abstract/notes; full-text completion not independently established | AK13: Acoustic and transcript-based ADOS-code prediction is evaluated offline. Audio and transcript tasks are described separately; classifier score fusion is not itself evidence of independent-source fusion. | AL13: Not applicable | AM13: Not separately specified | AO13: No additional status determination | AP13: Not documented for this recharting | AQ13: ChatGPT-assisted evidence recharting, 2026-09-08 | AS13: Not recorded; historical inclusion retained
A14: 10 | B14: Historical | C14: Artificial Intelligence Driven Predictive Analysis of Acoustic and Linguistic Behaviors for ASD Identification | D14: 10.1109/tai.2024.3439288 | E14: 2024 | F14: Include | G14: =IF(F14="Include",1,0) -> 1 | H14: Diagnosis | I14: Not specified | J14: Audio/voice | K14: Not specified | L14: Multiple/not uniquely specified | M14: Research only | N14: Automated measurement/classification | O14: Not observed in assessed sources | P14: Not observed in assessed sources | Q14: Not reported in assessed sources | R14: Not reported in assessed sources | S14: Not reported in assessed sources | T14: Not reported in assessed sources | U14: Not reported in assessed sources | V14: Not reported in assessed sources | W14: Not reported in assessed sources | X14: Not reported in assessed sources | Y14: Not ascertainable | Z14: Not reported in assessed sources | AA14: Not recorded | AB14: 0 | AC14: 0 | AD14: =IF(AND(G14=1,AB14=0),1,0) -> 1 | AE14: =IF(AND(AD14=1,AC14=0),1,0) -> 1 | AF14: =IF(AND(G14=1,H14<>"Not specified"),1,0) -> 1 | AG14: =IF(AND(AE14=1,AF14=1),1,0) -> 1 | AH14: Supplied abstract/coding notes; no new full-text verification | AI14: https://doi.org/10.1109/tai.2024.3439288 | AJ14: EVIDENCIA; original abstract/coding notes and lot source trace; Historical signals: title/abstract/notes; full-text completion not independently established | AK14: Speech-derived acoustic and linguistic biomarkers are evaluated in Hindi and English; no active clinician-facing workflow is documented in the assessed abstract. Acoustic and linguistic representations from speech; language variation is not independent input modality. | AL14: Not applicable | AM14: Not separately specified | AO14: No additional status determination | AP14: Not documented for this recharting | AQ14: ChatGPT-assisted evidence recharting, 2026-09-08 | AS14: Not recorded; historical inclusion retained
A15: 11 | B15: Historical | C15: Data Mining-Based Model for Computer-Aided Diagnosis of Autism and Gelotophobia: Mixed Methods Deep Learning Approach. | D15: 10.2196/72115 | E15: 2025 | F15: Include | G15: =IF(F15="Include",1,0) -> 1 | H15: Diagnosis | I15: Deep Learning | J15: Multiple source categories | K15: DeepFace with MLP classifier | L15: MLP/ANN | M15: Proposed only | N15: Diagnostic decision support | O15: In-decision | P15: Not observed in assessed sources | Q15: Not reported in assessed sources | R15: Reported | S15: Not reported in assessed sources | T15: Not reported in assessed sources | U15: Not reported in assessed sources | V15: Not reported in assessed sources | W15: Reported | X15: Not reported in assessed sources | Y15: Not ascertainable | Z15: Not reported in assessed sources | AA15: Expression of Concern | AB15: 1 | AC15: 0 | AD15: =IF(AND(G15=1,AB15=0),1,0) -> 0 | AE15: =IF(AND(AD15=1,AC15=0),1,0) -> 0 | AF15: =IF(AND(G15=1,H15<>"Not specified"),1,0) -> 1 | AG15: =IF(AND(AE15=1,AF15=1),1,0) -> 0 | AH15: Primary-source full text (targeted sections) | AI15: https://formative.jmir.org/2026/1/e91833/ | AJ15: Editorial notice, 23 January 2026 | AK15: Facial-image classification and questionnaire-assisted gelotophobia assessment are proposed for clinical use. Retain the expression-of-concern flag; diagnostic performance is not evidence of deployment. | AL15: Not applicable | AM15: Not separately specified | AO15: No additional status determination | AP15: Not documented for this recharting | AQ15: ChatGPT-assisted evidence recharting, 2026-09-08 | AS15: Not recorded; historical inclusion retained
A16: 12 | B16: Historical | C16: Effect of Wearable Digital Intervention for Improving Socialization in Children with Autism Spectrum Disorder: A Randomized Clinical Trial | D16: 10.1001/jamapediatrics.2019.0285 | E16: 2019 | F16: Include | G16: =IF(F16="Include",1,0) -> 1 | H16: Monitoring/intervention | I16: Not specified | J16: Behavioral images/video/gaze/movement | K16: Computer vision classifier (family not specified) | L16: Multiple/not uniquely specified | M16: Evaluated AI-supported intervention | N16: Adaptive intervention | O16: Post-decision | P16: Post-decision | Q16: Not reported in assessed sources | R16: Not reported in assessed sources | S16: Not reported in assessed sources | T16: Not reported in assessed sources | U16: Not reported in assessed sources | V16: Not reported in assessed sources | W16: Not reported in assessed sources | X16: Reported | Y16: Not ascertainable | Z16: Not reported in assessed sources | AA16: Not recorded | AB16: 0 | AC16: 0 | AD16: =IF(AND(G16=1,AB16=0),1,0) -> 1 | AE16: =IF(AND(AD16=1,AC16=0),1,0) -> 1 | AF16: =IF(AND(G16=1,H16<>"Not specified"),1,0) -> 1 | AG16: =IF(AND(AE16=1,AF16=1),1,0) -> 1 | AH16: Supplied abstract/coding notes; no new full-text verification | AI16: https://doi.org/10.1001/jamapediatrics.2019.0285 | AJ16: EVIDENCIA; original abstract/coding notes and lot source trace; Historical signals: title/abstract/notes; full-text completion not independently established | AK16: Superpower Glass provides AI-generated facial-expression feedback in a randomized home intervention. Standard ABA therapy and outcome scales are not additional AI input modalities. | AL16: Not applicable | AM16: Not separately specified | AO16: No additional status determination | AP16: Not documented for this recharting | AQ16: ChatGPT-assisted evidence recharting, 2026-09-08 | AS16: Not recorded; historical inclusion retained
A17: 13 | B17: Historical | C17: Feature Signature Discovery for Autism Detection: An Automated Machine Learning Based Feature Ranking Framework | D17: 10.1155/2023/6330002 | E17: 2023 | F17: Include | G17: =IF(F17="Include",1,0) -> 1 | H17: Screening | I17: Machine Learning | J17: Structured clinical/questionnaire data | K17: AutoML / feature-ranking framework | L17: Other specified method | M17: Research only | N17: Automated measurement/classification | O17: Not observed in assessed sources | P17: Not observed in assessed sources | Q17: Not reported in assessed sources | R17: Not reported in assessed sources | S17: Reported | T17: Not reported in assessed sources | U17: Not reported in assessed sources | V17: Not reported in assessed sources | W17: Not reported in assessed sources | X17: Not reported in assessed sources | Y17: Not ascertainable | Z17: Reported | AA17: Not recorded | AB17: 0 | AC17: 0 | AD17: =IF(AND(G17=1,AB17=0),1,0) -> 1 | AE17: =IF(AND(AD17=1,AC17=0),1,0) -> 1 | AF17: =IF(AND(G17=1,H17<>"Not specified"),1,0) -> 1 | AG17: =IF(AND(AE17=1,AF17=1),1,0) -> 1 | AH17: Supplied abstract/coding notes; no new full-text verification | AI17: https://doi.org/10.1155/2023/6330002 | AJ17: EVIDENCIA; original abstract/coding notes and lot source trace; Historical signals: title/abstract/notes; full-text completion not independently established | AK17: Q-CHAT-based tabular screening datasets and automated ML model ranking. Discussion of deep-learning comparators does not make the proposed AutoML framework deep learning. | AL17: Not applicable | AM17: Not separately specified | AO17: No additional status determination | AP17: Not documented for this recharting | AQ17: ChatGPT-assisted evidence recharting, 2026-09-08 | AR17: RA | AS17: Not recorded; historical inclusion retained
A18: 14 | B18: Historical | C18: Functional neuroimaging of high-risk 6-month-old infants predicts a diagnosis of autism at 24 months of age | D18: 10.1126/scitranslmed.aag2882 | E18: 2017 | F18: Include | G18: =IF(F18="Include",1,0) -> 1 | H18: Prognosis | I18: Machine Learning | J18: Neuroimaging | K18: Not specified | L18: Multiple/not uniquely specified | M18: Research only | N18: Risk/trajectory estimation | O18: Not observed in assessed sources | P18: Not observed in assessed sources | Q18: Not reported in assessed sources | R18: Not reported in assessed sources | S18: Not reported in assessed sources | T18: Not reported in assessed sources | U18: Not reported in assessed sources | V18: Not reported in assessed sources | W18: Not reported in assessed sources | X18: Not reported in assessed sources | Y18: Reported | Z18: Not reported in assessed sources | AA18: Not recorded | AB18: 0 | AC18: 0 | AD18: =IF(AND(G18=1,AB18=0),1,0) -> 1 | AE18: =IF(AND(AD18=1,AC18=0),1,0) -> 1 | AF18: =IF(AND(G18=1,H18<>"Not specified"),1,0) -> 1 | AG18: =IF(AND(AE18=1,AF18=1),1,0) -> 1 | AH18: Supplied abstract/coding notes; no new full-text verification | AI18: https://doi.org/10.1126/scitranslmed.aag2882 | AJ18: EVIDENCIA; original abstract/coding notes and lot source trace; Historical signals: title/abstract/notes; full-text completion not independently established | AK18: Prospective infant fcMRI cohort predicts research diagnosis at 24 months using internal cross-validation. Prospective data collection is not prospective clinical use of model outputs. | AL18: Not applicable | AM18: Not separately specified | AO18: No additional status determination | AP18: Not documented for this recharting | AQ18: ChatGPT-assisted evidence recharting, 2026-09-08 | AR18: RA | AS18: Not recorded; historical inclusion retained
A19: 15 | B19: Historical | C19: Hybrid CNN and random forest model with late fusion for detection of autism spectrum disorder in Toddlers | D19: 10.1016/j.mex.2025.103278 | E19: 2025 | F19: Include | G19: =IF(F19="Include",1,0) -> 1 | H19: Screening | I19: Hybrid | J19: Multiple source categories | K19: VGG16 CNN + Random Forest (late fusion) | L19: Composite/ensemble pipeline | M19: Proposed only | N19: Triage/questionnaire assessment | O19: Pre-decision | P19: Not observed in assessed sources | Q19: Not reported in assessed sources | R19: Reported | S19: Not reported in assessed sources | T19: Not reported in assessed sources | U19: Not reported in assessed sources | V19: Not reported in assessed sources | W19: Reported | X19: Not reported in assessed sources | Y19: Not ascertainable | Z19: Not reported in assessed sources | AA19: Not recorded | AB19: 0 | AC19: 0 | AD19: =IF(AND(G19=1,AB19=0),1,0) -> 1 | AE19: =IF(AND(AD19=1,AC19=0),1,0) -> 1 | AF19: =IF(AND(G19=1,H19<>"Not specified"),1,0) -> 1 | AG19: =IF(AND(AE19=1,AF19=1),1,0) -> 1 | AH19: Supplied abstract/coding notes; no new full-text verification | AI19: https://doi.org/10.1016/j.mex.2025.103278 | AJ19: EVIDENCIA; original abstract/coding notes and lot source trace; Historical signals: title/abstract/notes; full-text completion not independently established | AK19: The source describes facial-image and questionnaire models with late fusion. Participant-level pairing and independence of the two datasets are not established by the abstract; no evaluated clinical workflow is claimed. | AL19: Not applicable | AM19: Not separately specified | AO19: No additional status determination | AP19: Not documented for this recharting | AQ19: ChatGPT-assisted evidence recharting, 2026-09-08 | AS19: Not recorded; historical inclusion retained
A20: 16 | B20: Historical | C20: Machine Learning Approaches for the Early Diagnosis of Autism Spectrum Disorder: A Systematic Framework | D20: 10.1007/978-3-031-81083-1_7 | E20: 2025 | F20: Include | G20: =IF(F20="Include",1,0) -> 1 | H20: Screening | I20: Machine Learning | J20: Structured clinical/questionnaire data | K20: Neural network (depth not specified) | L20: Multiple/not uniquely specified | M20: Proposed only | N20: Triage/questionnaire assessment | O20: Pre-decision | P20: Not observed in assessed sources | Q20: Not reported in assessed sources | R20: Not reported in assessed sources | S20: Not reported in assessed sources | T20: Not reported in assessed sources | U20: Not reported in assessed sources | V20: Not reported in assessed sources | W20: Not reported in assessed sources | X20: Not reported in assessed sources | Y20: Not ascertainable | Z20: Not reported in assessed sources | AA20: Not recorded | AB20: 0 | AC20: 0 | AD20: =IF(AND(G20=1,AB20=0),1,0) -> 1 | AE20: =IF(AND(AD20=1,AC20=0),1,0) -> 1 | AF20: =IF(AND(G20=1,H20<>"Not specified"),1,0) -> 1 | AG20: =IF(AND(AE20=1,AF20=1),1,0) -> 1 | AH20: Supplied abstract/coding notes; no new full-text verification | AI20: https://doi.org/10.1007/978-3-031-81083-1_7 | AJ20: EVIDENCIA; original abstract/coding notes and lot source trace; Historical signals: title/abstract/notes; full-text completion not independently established | AK20: The abstract describes screening-assessment datasets and neural-network training, with an intended early-screening system. Detailed architecture and deployment are not established. | AL20: Not applicable | AM20: Not separately specified | AO20: No additional status determination | AP20: Not documented for this recharting | AQ20: ChatGPT-assisted evidence recharting, 2026-09-08 | AS20: Not recorded; historical inclusion retained
A21: 17 | B21: Historical | C21: Machine learning classification of autism spectrum disorder based on reciprocity in naturalistic social interactions | D21: 10.1038/s41398-024-02802-5 | E21: 2024 | F21: Include | G21: =IF(F21="Include",1,0) -> 1 | H21: Diagnosis | I21: Machine Learning | J21: Behavioral images/video/gaze/movement | K21: SVM | L21: SVM | M21: Research only | N21: Automated measurement/classification | O21: Not observed in assessed sources | P21: Not observed in assessed sources | Q21: Not reported in assessed sources | R21: Not reported in assessed sources | S21: Not reported in assessed sources | T21: Not reported in assessed sources | U21: Not reported in assessed sources | V21: Not reported in assessed sources | W21: Not reported in assessed sources | X21: Not reported in assessed sources | Y21: Not ascertainable | Z21: Not reported in assessed sources | AA21: Not recorded | AB21: 0 | AC21: 0 | AD21: =IF(AND(G21=1,AB21=0),1,0) -> 1 | AE21: =IF(AND(AD21=1,AC21=0),1,0) -> 1 | AF21: =IF(AND(G21=1,H21<>"Not specified"),1,0) -> 1 | AG21: =IF(AND(AE21=1,AF21=1),1,0) -> 1 | AH21: Supplied abstract/coding notes; no new full-text verification | AI21: https://doi.org/10.1038/s41398-024-02802-5 | AJ21: EVIDENCIA; original abstract/coding notes and lot source trace; Historical signals: title/abstract/notes; full-text completion not independently established | AK21: Naturalistic interaction videos are computationally annotated and classified offline; the source explicitly places routine-care generalization in future work. | AL21: Not applicable | AM21: Not separately specified | AO21: No additional status determination | AP21: Not documented for this recharting | AQ21: ChatGPT-assisted evidence recharting, 2026-09-08 | AS21: Not recorded; historical inclusion retained
A22: 18 | B22: Historical | C22: Multiparametric MRI characterization and prediction in autism spectrum disorder using graph theory and machine learning | D22: 10.1371/journal.pone.0090405 | E22: 2014 | F22: Include | G22: =IF(F22="Include",1,0) -> 1 | H22: Diagnosis | I22: Machine Learning | J22: Neuroimaging | K22: Not specified | L22: Multiple/not uniquely specified | M22: Research only | N22: Automated measurement/classification | O22: Not observed in assessed sources | P22: Not observed in assessed sources | Q22: Not reported in assessed sources | R22: Reported | S22: Not reported in assessed sources | T22: Not reported in assessed sources | U22: Not reported in assessed sources | V22: Reported | W22: Reported | X22: Not reported in assessed sources | Y22: Not ascertainable | Z22: Not reported in assessed sources | AA22: Not recorded | AB22: 0 | AC22: 0 | AD22: =IF(AND(G22=1,AB22=0),1,0) -> 1 | AE22: =IF(AND(AD22=1,AC22=0),1,0) -> 1 | AF22: =IF(AND(G22=1,H22<>"Not specified"),1,0) -> 1 | AG22: =IF(AND(AE22=1,AF22=1),1,0) -> 1 | AH22: Supplied abstract/coding notes; no new full-text verification | AI22: https://doi.org/10.1371/journal.pone.0090405 | AJ22: EVIDENCIA; original abstract/coding notes and lot source trace; Historical signals: title/abstract/notes; full-text completion not independently established | AK22: Multiparametric MRI and graph-theoretic features are analyzed with machine learning, not necessarily a graph neural network. Multi-center data and multiple MRI-derived feature types are reported. | AL22: Not applicable | AM22: Not separately specified | AO22: No additional status determination | AP22: Not documented for this recharting | AQ22: ChatGPT-assisted evidence recharting, 2026-09-08 | AR22: RA | AS22: Not recorded; historical inclusion retained
A23: 19 | B23: Historical | C23: Multivariate Neural Connectivity Patterns in Early Infancy Predict Later Autism Symptoms | D23: 10.1016/j.bpsc.2020.06.003 | E23: 2021 | F23: Include | G23: =IF(F23="Include",1,0) -> 1 | H23: Prognosis | I23: Machine Learning | J23: Physiological signals | K23: Support vector regression | L23: SVM | M23: Research only | N23: Risk/trajectory estimation | O23: Not observed in assessed sources | P23: Not observed in assessed sources | Q23: Not reported in assessed sources | R23: Not reported in assessed sources | S23: Not reported in assessed sources | T23: Not reported in assessed sources | U23: Not reported in assessed sources | V23: Not reported in assessed sources | W23: Not reported in assessed sources | X23: Not reported in assessed sources | Y23: Reported | Z23: Not reported in assessed sources | AA23: Not recorded | AB23: 0 | AC23: 0 | AD23: =IF(AND(G23=1,AB23=0),1,0) -> 1 | AE23: =IF(AND(AD23=1,AC23=0),1,0) -> 1 | AF23: =IF(AND(G23=1,H23<>"Not specified"),1,0) -> 1 | AG23: =IF(AND(AE23=1,AF23=1),1,0) -> 1 | AH23: Supplied abstract/coding notes; no new full-text verification | AI23: https://doi.org/10.1016/j.bpsc.2020.06.003 | AJ23: EVIDENCIA; original abstract/coding notes and lot source trace; Historical signals: title/abstract/notes; full-text completion not independently established | AK23: Three-month EEG predicts ADOS scores at 18 months in a longitudinal research cohort. A future clinical endpoint distinguishes prognosis from cross-sectional diagnosis. | AL23: Not applicable | AM23: Not separately specified | AO23: No additional status determination | AP23: Not documented for this recharting | AQ23: ChatGPT-assisted evidence recharting, 2026-09-08 | AR23: RA | AS23: Not recorded; historical inclusion retained
A24: 20 | B24: Historical | C24: Testing the accuracy of an observation-based classifier for rapid detection of autism risk. | D24: 10.1038/tp.2014.65 | E24: 2014 | F24: Include | G24: =IF(F24="Include",1,0) -> 1 | H24: Screening | I24: Machine Learning | J24: Structured clinical/questionnaire data | K24: Alternating Decision Tree | L24: Decision tree/rules | M24: Proposed only | N24: Triage/questionnaire assessment | O24: Pre-decision | P24: Not observed in assessed sources | Q24: Reported | R24: Not reported in assessed sources | S24: Not reported in assessed sources | T24: Not reported in assessed sources | U24: Not reported in assessed sources | V24: Not reported in assessed sources | W24: Not reported in assessed sources | X24: Not reported in assessed sources | Y24: Not ascertainable | Z24: Not reported in assessed sources | AA24: Not recorded | AB24: 0 | AC24: 0 | AD24: =IF(AND(G24=1,AB24=0),1,0) -> 1 | AE24: =IF(AND(AD24=1,AC24=0),1,0) -> 1 | AF24: =IF(AND(G24=1,H24<>"Not specified"),1,0) -> 1 | AG24: =IF(AND(AE24=1,AF24=1),1,0) -> 1 | AH24: Supplied abstract/coding notes; no new full-text verification | AI24: https://doi.org/10.1038/tp.2014.65 | AJ24: EVIDENCIA; original abstract/coding notes and lot source trace; Historical signals: title/abstract/notes; full-text completion not independently established | AK24: A previously developed shortened ADOS classifier is tested on an independent 2616-child sample. This is external model evaluation but not an observed clinical triage deployment. | AL24: Not applicable | AM24: Not separately specified | AO24: No additional status determination | AP24: Not documented for this recharting | AQ24: ChatGPT-assisted evidence recharting, 2026-09-08 | AS24: Not recorded; historical inclusion retained
A25: 21 | B25: Historical | C25: Using deep learning to classify developmental differences in reaching and placing movements in children with and without autism spectrum disorder | D25: 10.1038/s41598-024-81652-z | E25: 2024 | F25: Include | G25: =IF(F25="Include",1,0) -> 1 | H25: Diagnosis | I25: Deep Learning | J25: Behavioral images/video/gaze/movement | K25: MLP | L25: MLP/ANN | M25: Research only | N25: Automated measurement/classification | O25: Not observed in assessed sources | P25: Not observed in assessed sources | Q25: Not reported in assessed sources | R25: Not reported in assessed sources | S25: Not reported in assessed sources | T25: Not reported in assessed sources | U25: Not reported in assessed sources | V25: Not reported in assessed sources | W25: Not reported in assessed sources | X25: Not reported in assessed sources | Y25: Not ascertainable | Z25: Not reported in assessed sources | AA25: Not recorded | AB25: 0 | AC25: 0 | AD25: =IF(AND(G25=1,AB25=0),1,0) -> 1 | AE25: =IF(AND(AD25=1,AC25=0),1,0) -> 1 | AF25: =IF(AND(G25=1,H25<>"Not specified"),1,0) -> 1 | AG25: =IF(AND(AE25=1,AF25=1),1,0) -> 1 | AH25: Supplied abstract/coding notes; no new full-text verification | AI25: https://doi.org/10.1038/s41598-024-81652-z | AJ25: EVIDENCIA; original abstract/coding notes and lot source trace; Historical signals: title/abstract/notes; full-text completion not independently established | AK25: Deep classification uses reaching/placing movement kinematics; age groups and diagnostic labels are not separate data modalities. Clinical deployment is not evaluated. | AL25: Not applicable | AM25: Not separately specified | AO25: No additional status determination | AP25: Not documented for this recharting | AQ25: ChatGPT-assisted evidence recharting, 2026-09-08 | AS25: Not recorded; historical inclusion retained
A26: 22 | B26: Historical | C26: A CNN deep local and global ASD classification approach with continuous wavelet transform using task-based FMRI | D26: 10.3390/s21175822 | E26: 2021 | F26: Include | G26: =IF(F26="Include",1,0) -> 1 | H26: Diagnosis | I26: Deep Learning | J26: Neuroimaging | K26: CNN | L26: CNN | M26: Proposed only | N26: Diagnostic decision support | O26: In-decision | P26: Not observed in assessed sources | Q26: Not reported in assessed sources | R26: Not reported in assessed sources | S26: Reported | T26: Not reported in assessed sources | U26: Not reported in assessed sources | V26: Not reported in assessed sources | W26: Not reported in assessed sources | X26: Not reported in assessed sources | Y26: Not ascertainable | Z26: Reported | AA26: Not recorded | AB26: 0 | AC26: 0 | AD26: =IF(AND(G26=1,AB26=0),1,0) -> 1 | AE26: =IF(AND(AD26=1,AC26=0),1,0) -> 1 | AF26: =IF(AND(G26=1,H26<>"Not specified"),1,0) -> 1 | AG26: =IF(AND(AE26=1,AF26=1),1,0) -> 1 | AH26: Supplied abstract/coding notes; no new full-text verification | AI26: https://doi.org/10.3390/s21175822 | AJ26: EVIDENCIA; original abstract/coding notes and lot source trace; Historical signals: title/abstract/notes; full-text completion not independently established | AK26: Task-fMRI CAD with local/global CNN classifiers and a proposed severity map. Speech is the eliciting stimulus, not the model's audio input. Clinical interpretation remains proposed. | AL26: Not applicable | AM26: Not separately specified | AO26: No additional status determination | AP26: Not documented for this recharting | AQ26: ChatGPT-assisted evidence recharting, 2026-09-08 | AS26: Not recorded; historical inclusion retained
A27: 23 | B27: Historical | C27: A new machine learning model based on induction of rules for autism detection | D27: 10.1177/1460458218824711 | E27: 2020 | F27: Include | G27: =IF(F27="Include",1,0) -> 1 | H27: Screening | I27: Machine Learning | J27: Structured clinical/questionnaire data | K27: Rule induction (Rules-Machine Learning) | L27: Decision tree/rules | M27: Proposed only | N27: Triage/questionnaire assessment | O27: Pre-decision | P27: Not observed in assessed sources | Q27: Not reported in assessed sources | R27: Not reported in assessed sources | S27: Reported | T27: Not reported in assessed sources | U27: Not reported in assessed sources | V27: Not reported in assessed sources | W27: Not reported in assessed sources | X27: Not reported in assessed sources | Y27: Not ascertainable | Z27: Reported | AA27: Not recorded | AB27: 0 | AC27: 0 | AD27: =IF(AND(G27=1,AB27=0),1,0) -> 1 | AE27: =IF(AND(AD27=1,AC27=0),1,0) -> 1 | AF27: =IF(AND(G27=1,H27<>"Not specified"),1,0) -> 1 | AG27: =IF(AND(AE27=1,AF27=1),1,0) -> 1 | AH27: Supplied abstract/coding notes; no new full-text verification | AI27: https://doi.org/10.1177/1460458218824711 | AJ27: EVIDENCIA; original abstract/coding notes and lot source trace; Historical signals: title/abstract/notes; full-text completion not independently established | AK27: Questionnaire-derived datasets support a rule-learning classifier whose rules are intended for domain-expert interpretation. Retain the specified rule family rather than forcing a decision-tree label. | AL27: Not applicable | AM27: Not separately specified | AO27: No additional status determination | AP27: Not documented for this recharting | AQ27: ChatGPT-assisted evidence recharting, 2026-09-08 | AR27: RA | AS27: Not recorded; historical inclusion retained
A28: 24 | B28: Historical | C28: A Novel Grading System for Autism Severity Level Using Task-Based Functional MRI: A Response to Speech Study | D28: 10.1109/access.2021.3097606 | E28: 2021 | F28: Include | G28: =IF(F28="Include",1,0) -> 1 | H28: Diagnosis | I28: Machine Learning | J28: Neuroimaging | K28: Multiple classifiers (primary not specified) | L28: Multiple/not uniquely specified | M28: Proposed only | N28: Diagnostic decision support | O28: In-decision | P28: Not observed in assessed sources | Q28: Not reported in assessed sources | R28: Not reported in assessed sources | S28: Not reported in assessed sources | T28: Not reported in assessed sources | U28: Not reported in assessed sources | V28: Not reported in assessed sources | W28: Not reported in assessed sources | X28: Not reported in assessed sources | Y28: Not ascertainable | Z28: Not reported in assessed sources | AA28: Not recorded | AB28: 0 | AC28: 0 | AD28: =IF(AND(G28=1,AB28=0),1,0) -> 1 | AE28: =IF(AND(AD28=1,AC28=0),1,0) -> 1 | AF28: =IF(AND(G28=1,H28<>"Not specified"),1,0) -> 1 | AG28: =IF(AND(AE28=1,AF28=1),1,0) -> 1 | AH28: Supplied abstract/coding notes; no new full-text verification | AI28: https://doi.org/10.1109/access.2021.3097606 | AJ28: EVIDENCIA; original abstract/coding notes and lot source trace; Historical signals: title/abstract/notes; full-text completion not independently established | AK28: A task-fMRI framework grades contemporaneous ASD severity. Speech stimulation is not voice-data modeling; oversampling and repeated random splits are internal validation only. | AL28: Not applicable | AM28: Not separately specified | AO28: No additional status determination | AP28: Not documented for this recharting | AQ28: ChatGPT-assisted evidence recharting, 2026-09-08 | AR28: RA | AS28: Not recorded; historical inclusion retained
A29: 26 | B29: Historical | C29: An Analysis of the Use of Machine Learning in the Diagnosis of Autism Spectrum Disorder | D29: 10.1007/978-3-031-23683-9_12 | E29: 2023 | F29: Exclude | G29: =IF(F29="Include",1,0) -> 0 | H29: Excluded | I29: Excluded | J29: Excluded | K29: Not specified | L29: Multiple/not uniquely specified | M29: Excluded | N29: Excluded | O29: Not applicable - excluded | P29: Not applicable - excluded | Q29: Not reported in assessed sources | R29: Not ascertainable | S29: Not reported in assessed sources | T29: Not reported in assessed sources | U29: Not reported in assessed sources | V29: Not reported in assessed sources | W29: Reported | X29: Not reported in assessed sources | Y29: Not ascertainable | Z29: Not reported in assessed sources | AA29: Not recorded | AB29: 0 | AC29: 0 | AD29: =IF(AND(G29=1,AB29=0),1,0) -> 0 | AE29: =IF(AND(AD29=1,AC29=0),1,0) -> 0 | AF29: =IF(AND(G29=1,H29<>"Not specified"),1,0) -> 0 | AG29: =IF(AND(AE29=1,AF29=1),1,0) -> 0 | AH29: Supplied abstract/coding notes; no new full-text verification | AI29: https://link.springer.com/chapter/10.1007/978-3-031-23683-9_12 | AJ29: EVIDENCIA; original abstract/coding notes and lot source trace; Historical signals: title/abstract/notes; full-text completion not independently established | AK29: The publication identifies itself as a survey of machine-learning techniques and prior reported performance rather than an original empirical ASD model evaluation. | AL29: EC1 - Secondary / non-empirical publication | AM29: Not separately specified | AO29: No additional status determination | AP29: Not documented for this recharting | AQ29: ChatGPT-assisted evidence recharting, 2026-09-08 | AS29: Not recorded; historical inclusion retained
A30: 27 | B30: Historical | C30: An analytics-driven model for identifying autism spectrum disorder using eye tracking | D30: 10.1016/j.health.2025.100409 | E30: 2025 | F30: Include | G30: =IF(F30="Include",1,0) -> 1 | H30: Screening | I30: Not specified | J30: Behavioral images/video/gaze/movement | K30: Multiple ML/DL models (primary not specified) | L30: Multiple/not uniquely specified | M30: Research only | N30: Triage/questionnaire assessment | O30: Not observed in assessed sources | P30: Not observed in assessed sources | Q30: Not reported in assessed sources | R30: Not reported in assessed sources | S30: Not reported in assessed sources | T30: Not reported in assessed sources | U30: Not reported in assessed sources | V30: Not reported in assessed sources | W30: Not reported in assessed sources | X30: Not reported in assessed sources | Y30: Not ascertainable | Z30: Not reported in assessed sources | AA30: Not recorded | AB30: 0 | AC30: 0 | AD30: =IF(AND(G30=1,AB30=0),1,0) -> 1 | AE30: =IF(AND(AD30=1,AC30=0),1,0) -> 1 | AF30: =IF(AND(G30=1,H30<>"Not specified"),1,0) -> 1 | AG30: =IF(AND(AE30=1,AF30=1),1,0) -> 1 | AH30: Supplied abstract/coding notes; no new full-text verification | AI30: https://doi.org/10.1016/j.health.2025.100409 | AJ30: EVIDENCIA; original abstract/coding notes and lot source trace; Historical signals: title/abstract/notes; full-text completion not independently established | AK30: Saliency4ASD eye-movement features are evaluated with several ML/DL models. The assessed material does not identify one primary model; comparison alone does not establish a hybrid architecture. | AL30: Not applicable | AM30: Not separately specified | AO30: No additional status determination | AP30: Not documented for this recharting | AQ30: ChatGPT-assisted evidence recharting, 2026-09-08 | AR30: RA | AS30: Not recorded; historical inclusion retained
A31: 28 | B31: Historical | C31: An evaluation of machine learning approaches for early diagnosis of autism spectrum disorder | D31: 10.1016/j.health.2023.100293 | E31: 2024 | F31: Include | G31: =IF(F31="Include",1,0) -> 1 | H31: Screening | I31: Machine Learning | J31: Structured clinical/questionnaire data | K31: Neural network (combined dataset); SVM/LR comparators | L31: SVM | M31: Research only | N31: Triage/questionnaire assessment | O31: Not observed in assessed sources | P31: Not observed in assessed sources | Q31: Not reported in assessed sources | R31: Not reported in assessed sources | S31: Not reported in assessed sources | T31: Not reported in assessed sources | U31: Not reported in assessed sources | V31: Not reported in assessed sources | W31: Not reported in assessed sources | X31: Not reported in assessed sources | Y31: Not ascertainable | Z31: Not reported in assessed sources | AA31: Not recorded | AB31: 0 | AC31: 0 | AD31: =IF(AND(G31=1,AB31=0),1,0) -> 1 | AE31: =IF(AND(AD31=1,AC31=0),1,0) -> 1 | AF31: =IF(AND(G31=1,H31<>"Not specified"),1,0) -> 1 | AG31: =IF(AND(AE31=1,AF31=1),1,0) -> 1 | AH31: Supplied abstract/coding notes; no new full-text verification | AI31: https://doi.org/10.1016/j.health.2023.100293 | AJ31: EVIDENCIA; original abstract/coding notes and lot source trace; Historical signals: title/abstract/notes; full-text completion not independently established | AK31: Public age-specific screening datasets are analyzed with classification and clustering. The proposed ANN is emphasized for the pooled dataset; no prospective diagnostic use is shown. | AL31: Not applicable | AM31: Not separately specified | AO31: No additional status determination | AP31: Not documented for this recharting | AQ31: ChatGPT-assisted evidence recharting, 2026-09-08 | AR31: RA | AS31: Not recorded; historical inclusion retained
A32: 29 | B32: Historical | C32: An intellectual autism spectrum disorder classification framework in healthcare industry using ViT-based adaptive deep learning model | D32: 10.1016/j.bspc.2025.107737 | E32: 2025 | F32: Include | G32: =IF(F32="Include",1,0) -> 1 | H32: Diagnosis | I32: Deep Learning | J32: Neuroimaging | K32: ViT-ARDNet-LSTM | L32: Composite/ensemble pipeline | M32: Proposed only | N32: Diagnostic decision support | O32: In-decision | P32: Not observed in assessed sources | Q32: Not reported in assessed sources | R32: Not reported in assessed sources | S32: Not reported in assessed sources | T32: Not reported in assessed sources | U32: Not reported in assessed sources | V32: Not reported in assessed sources | W32: Not reported in assessed sources | X32: Not reported in assessed sources | Y32: Not ascertainable | Z32: Not reported in assessed sources | AA32: Not recorded | AB32: 0 | AC32: 0 | AD32: =IF(AND(G32=1,AB32=0),1,0) -> 1 | AE32: =IF(AND(AD32=1,AC32=0),1,0) -> 1 | AF32: =IF(AND(G32=1,H32<>"Not specified"),1,0) -> 1 | AG32: =IF(AND(AE32=1,AF32=1),1,0) -> 1 | AH32: Supplied abstract/coding notes; no new full-text verification | AI32: https://doi.org/10.1016/j.bspc.2025.107737 | AJ32: EVIDENCIA; original abstract/coding notes and lot source trace; Historical signals: title/abstract/notes; full-text completion not independently established | AK32: MRI classification uses a vision transformer, residual DenseNet and LSTM in a deep-learning architecture. Combining deep components is not ML/DL hybrid integration. | AL32: Not applicable | AM32: Not separately specified | AO32: No additional status determination | AP32: Not documented for this recharting | AQ32: ChatGPT-assisted evidence recharting, 2026-09-08 | AS32: Not recorded; historical inclusion retained
A33: 30 | B33: Historical | C33: Analysis and Detection of Autism Spectrum Disorder Using Machine Learning Techniques | D33: 10.1016/j.procs.2020.03.399 | E33: 2020 | F33: Include | G33: =IF(F33="Include",1,0) -> 1 | H33: Screening | I33: Deep Learning | J33: Structured clinical/questionnaire data | K33: CNN | L33: CNN | M33: Research only | N33: Triage/questionnaire assessment | O33: Not observed in assessed sources | P33: Not observed in assessed sources | Q33: Not reported in assessed sources | R33: Not reported in assessed sources | S33: Not reported in assessed sources | T33: Not reported in assessed sources | U33: Not reported in assessed sources | V33: Not reported in assessed sources | W33: Not reported in assessed sources | X33: Not reported in assessed sources | Y33: Not ascertainable | Z33: Not reported in assessed sources | AA33: Not recorded | AB33: 0 | AC33: 0 | AD33: =IF(AND(G33=1,AB33=0),1,0) -> 1 | AE33: =IF(AND(AD33=1,AC33=0),1,0) -> 1 | AF33: =IF(AND(G33=1,H33<>"Not specified"),1,0) -> 1 | AG33: =IF(AND(AE33=1,AF33=1),1,0) -> 1 | AH33: Supplied abstract/coding notes; no new full-text verification | AI33: https://doi.org/10.1016/j.procs.2020.03.399 | AJ33: EVIDENCIA; original abstract/coding notes and lot source trace; Historical signals: title/abstract/notes; full-text completion not independently established | AK33: Three public tabular screening datasets are evaluated. CNN is the reported best-performing model; evaluating conventional ML baselines does not make this a hybrid model. | AL33: Not applicable | AM33: Not separately specified | AO33: No additional status determination | AP33: Not documented for this recharting | AQ33: ChatGPT-assisted evidence recharting, 2026-09-08 | AS33: Not recorded; historical inclusion retained
A34: 31 | B34: Historical | C34: ASD classification for children using deep neural network | D34: 10.1016/j.gltp.2021.08.042 | E34: 2021 | F34: Include | G34: =IF(F34="Include",1,0) -> 1 | H34: Screening | I34: Deep Learning | J34: Structured clinical/questionnaire data | K34: DNN with diffusion mapping | L34: Other specified method | M34: Research only | N34: Triage/questionnaire assessment | O34: Not observed in assessed sources | P34: Not observed in assessed sources | Q34: Not reported in assessed sources | R34: Not reported in assessed sources | S34: Not reported in assessed sources | T34: Not reported in assessed sources | U34: Not reported in assessed sources | V34: Not reported in assessed sources | W34: Not reported in assessed sources | X34: Not reported in assessed sources | Y34: Not ascertainable | Z34: Not reported in assessed sources | AA34: Not recorded | AB34: 0 | AC34: 0 | AD34: =IF(AND(G34=1,AB34=0),1,0) -> 1 | AE34: =IF(AND(AD34=1,AC34=0),1,0) -> 1 | AF34: =IF(AND(G34=1,H34<>"Not specified"),1,0) -> 1 | AG34: =IF(AND(AE34=1,AF34=1),1,0) -> 1 | AH34: Supplied abstract/coding notes; no new full-text verification | AI34: https://doi.org/10.1016/j.gltp.2021.08.042 | AJ34: EVIDENCIA; original abstract/coding notes and lot source trace; Historical signals: title/abstract/notes; full-text completion not independently established | AK34: A UCI child screening dataset is classified using a DNN. The word diagnosis does not demonstrate specialist diagnostic workflow use. | AL34: Not applicable | AM34: Not separately specified | AO34: No additional status determination | AP34: Not documented for this recharting | AQ34: ChatGPT-assisted evidence recharting, 2026-09-08 | AS34: Not recorded; historical inclusion retained
A35: 32 | B35: Historical | C35: ASD-GraphNet: A novel graph learning approach for Autism Spectrum Disorder diagnosis using fMRI data | D35: 10.1016/j.compbiomed.2025.110723 | E35: 2025 | F35: Include | G35: =IF(F35="Include",1,0) -> 1 | H35: Diagnosis | I35: Machine Learning | J35: Neuroimaging | K35: Multiple classifiers with graph-derived features | L35: Multiple/not uniquely specified | M35: Research only | N35: Automated measurement/classification | O35: Not observed in assessed sources | P35: Not observed in assessed sources | Q35: Not reported in assessed sources | R35: Not reported in assessed sources | S35: Reported | T35: Not reported in assessed sources | U35: Not reported in assessed sources | V35: Reported | W35: Not reported in assessed sources | X35: Not reported in assessed sources | Y35: Not ascertainable | Z35: Reported | AA35: Not recorded | AB35: 0 | AC35: 0 | AD35: =IF(AND(G35=1,AB35=0),1,0) -> 1 | AE35: =IF(AND(AD35=1,AC35=0),1,0) -> 1 | AF35: =IF(AND(G35=1,H35<>"Not specified"),1,0) -> 1 | AG35: =IF(AND(AE35=1,AF35=1),1,0) -> 1 | AH35: Supplied abstract/coding notes; no new full-text verification | AI35: https://doi.org/10.1016/j.compbiomed.2025.110723 | AJ35: EVIDENCIA; original abstract/coding notes and lot source trace; Historical signals: title/abstract/notes; full-text completion not independently established | AK35: ASD-GraphNet describes engineered brain-graph features and conventional classifiers. Graph analysis is not assumed to be a graph neural network; no clinician-facing implementation is evaluated. | AL35: Not applicable | AM35: Not separately specified | AO35: No additional status determination | AP35: Not documented for this recharting | AQ35: ChatGPT-assisted evidence recharting, 2026-09-08 | AS35: Not recorded; historical inclusion retained
A36: 33 | B36: Historical | C36: Automated identification of postural control for children with autism spectrum disorder using a machine learning approach | D36: 10.1016/j.jbiomech.2020.110073 | E36: 2020 | F36: Include | G36: =IF(F36="Include",1,0) -> 1 | H36: Diagnosis | I36: Machine Learning | J36: Behavioral images/video/gaze/movement | K36: Naive Bayes | L36: Other specified method | M36: Research only | N36: Automated measurement/classification | O36: Not observed in assessed sources | P36: Not observed in assessed sources | Q36: Not reported in assessed sources | R36: Not reported in assessed sources | S36: Not reported in assessed sources | T36: Not reported in assessed sources | U36: Not reported in assessed sources | V36: Not reported in assessed sources | W36: Not reported in assessed sources | X36: Not reported in assessed sources | Y36: Not ascertainable | Z36: Not reported in assessed sources | AA36: Not recorded | AB36: 0 | AC36: 0 | AD36: =IF(AND(G36=1,AB36=0),1,0) -> 1 | AE36: =IF(AND(AD36=1,AC36=0),1,0) -> 1 | AF36: =IF(AND(G36=1,H36<>"Not specified"),1,0) -> 1 | AG36: =IF(AND(AE36=1,AF36=1),1,0) -> 1 | AH36: Supplied abstract/coding notes; no new full-text verification | AI36: https://doi.org/10.1016/j.jbiomech.2020.110073 | AJ36: EVIDENCIA; original abstract/coding notes and lot source trace; Historical signals: title/abstract/notes; full-text completion not independently established | AK36: Force-plate postural-control features are classified in 50 children; naive Bayes is the reported optimal classifier. This is experimental motor-phenotype classification, not deep learning. | AL36: Not applicable | AM36: Not separately specified | AO36: No additional status determination | AP36: Not documented for this recharting | AQ36: ChatGPT-assisted evidence recharting, 2026-09-08 | AR36: RA | AS36: Not recorded; historical inclusion retained
A37: 34 | B37: Historical | C37: Distributed Intrinsic Functional Connectivity Patterns Predict Diagnostic Status in Large Autism Cohort | D37: 10.1089/brain.2017.0496 | E37: 2017 | F37: Include | G37: =IF(F37="Include",1,0) -> 1 | H37: Diagnosis | I37: Machine Learning | J37: Neuroimaging | K37: Conditional Random Forest | L37: Random forest | M37: Research only | N37: Automated measurement/classification | O37: Not observed in assessed sources | P37: Not observed in assessed sources | Q37: Reported | R37: Not reported in assessed sources | S37: Reported | T37: Not reported in assessed sources | U37: Reported | V37: Reported | W37: Not reported in assessed sources | X37: Not reported in assessed sources | Y37: Not ascertainable | Z37: Reported | AA37: Not recorded | AB37: 0 | AC37: 0 | AD37: =IF(AND(G37=1,AB37=0),1,0) -> 1 | AE37: =IF(AND(AD37=1,AC37=0),1,0) -> 1 | AF37: =IF(AND(G37=1,H37<>"Not specified"),1,0) -> 1 | AG37: =IF(AND(AE37=1,AF37=1),1,0) -> 1 | AH37: Supplied abstract/coding notes; no new full-text verification | AI37: https://doi.org/10.1089/brain.2017.0496 | AJ37: EVIDENCIA; original abstract/coding notes and lot source trace; Historical signals: title/abstract/notes; full-text completion not independently established | AK37: ABIDE resting-state connectivity classification is externally tested in an in-house dataset with substantially lower accuracy. This supports external/cross-dataset evaluation, not stable transportability or clinical deployment. | AL37: Not applicable | AM37: Not separately specified | AO37: No additional status determination | AP37: Not documented for this recharting | AQ37: ChatGPT-assisted evidence recharting, 2026-09-08 | AR37: RA | AS37: Not recorded; historical inclusion retained
A38: 35 | B38: Historical | C38: Enhancing diagnosis of autism with optimized machine learning models and personal characteristic data | D38: 10.3389/fncom.2019.00009 | E38: 2019 | F38: Include | G38: =IF(F38="Include",1,0) -> 1 | H38: Diagnosis | I38: Machine Learning | J38: Structured clinical/questionnaire data | K38: Neural network (personal characteristics) | L38: Other specified method | M38: Research only | N38: Automated measurement/classification | O38: Not observed in assessed sources | P38: Not observed in assessed sources | Q38: Not reported in assessed sources | R38: Not reported in assessed sources | S38: Not reported in assessed sources | T38: Not reported in assessed sources | U38: Not reported in assessed sources | V38: Reported | W38: Not reported in assessed sources | X38: Not reported in assessed sources | Y38: Not ascertainable | Z38: Not reported in assessed sources | AA38: Not recorded | AB38: 0 | AC38: 0 | AD38: =IF(AND(G38=1,AB38=0),1,0) -> 1 | AE38: =IF(AND(AD38=1,AC38=0),1,0) -> 1 | AF38: =IF(AND(G38=1,H38<>"Not specified"),1,0) -> 1 | AG38: =IF(AND(AE38=1,AF38=1),1,0) -> 1 | AH38: Supplied abstract/coding notes; no new full-text verification | AI38: https://doi.org/10.3389/fncom.2019.00009/full | AJ38: EVIDENCIA; original abstract/coding notes and lot source trace; Historical signals: title/abstract/notes; full-text completion not independently established | AK38: Only six demographic/IQ characteristics from ABIDE are modeled. The fact that the parent resource is a neuroimaging database does not make these MRI inputs. | AL38: Not applicable | AM38: Not separately specified | AO38: No additional status determination | AP38: Not documented for this recharting | AQ38: ChatGPT-assisted evidence recharting, 2026-09-08 | AR38: RA | AS38: Not recorded; historical inclusion retained
A39: 36 | B39: Historical | C39: Investigating multiclass autism spectrum disorder classification using machine learning techniques | D39: 10.1016/j.prime.2024.100602 | E39: 2024 | F39: Include | G39: =IF(F39="Include",1,0) -> 1 | H39: Screening | I39: Machine Learning | J39: Structured clinical/questionnaire data | K39: Logistic regression / SVM (task-specific winners) | L39: Composite/ensemble pipeline | M39: Research only | N39: Triage/questionnaire assessment | O39: Not observed in assessed sources | P39: Not observed in assessed sources | Q39: Not reported in assessed sources | R39: Not reported in assessed sources | S39: Not reported in assessed sources | T39: Not reported in assessed sources | U39: Not reported in assessed sources | V39: Not reported in assessed sources | W39: Not reported in assessed sources | X39: Not reported in assessed sources | Y39: Not ascertainable | Z39: Not reported in assessed sources | AA39: Not recorded | AB39: 0 | AC39: 0 | AD39: =IF(AND(G39=1,AB39=0),1,0) -> 1 | AE39: =IF(AND(AD39=1,AC39=0),1,0) -> 1 | AF39: =IF(AND(G39=1,H39<>"Not specified"),1,0) -> 1 | AG39: =IF(AND(AE39=1,AF39=1),1,0) -> 1 | AH39: Supplied abstract/coding notes; no new full-text verification | AI39: https://doi.org/10.1016/j.prime.2024.100602 | AJ39: EVIDENCIA; original abstract/coding notes and lot source trace; Historical signals: title/abstract/notes; full-text completion not independently established | AK39: Different models perform best across age-specific and pooled screening endpoints. A single universally best classifier is not identifiable from the reported comparisons. | AL39: Not applicable | AM39: Not separately specified | AO39: No additional status determination | AP39: Not documented for this recharting | AQ39: ChatGPT-assisted evidence recharting, 2026-09-08 | AR39: RA | AS39: Not recorded; historical inclusion retained
A40: 37 | B40: Historical | C40: Jellyfish Search Optimization with Deep Learning Driven Autism Spectrum Disorder Classification | D40: 10.32604/cmc.2023.032586 | E40: 2023 | F40: Include | G40: =IF(F40="Include",1,0) -> 1 | H40: Screening | I40: Deep Learning | J40: Not specified | K40: GRU optimized with jellyfish search and bacterial foraging | L40: Recurrent network | M40: Research only | N40: Triage/questionnaire assessment | O40: Not observed in assessed sources | P40: Not observed in assessed sources | Q40: Not reported in assessed sources | R40: Not reported in assessed sources | S40: Not reported in assessed sources | T40: Not reported in assessed sources | U40: Not reported in assessed sources | V40: Not reported in assessed sources | W40: Not reported in assessed sources | X40: Not reported in assessed sources | Y40: Not ascertainable | Z40: Not reported in assessed sources | AA40: Not recorded | AB40: 0 | AC40: 0 | AD40: =IF(AND(G40=1,AB40=0),1,0) -> 1 | AE40: =IF(AND(AD40=1,AC40=0),1,0) -> 1 | AF40: =IF(AND(G40=1,H40<>"Not specified"),1,0) -> 1 | AG40: =IF(AND(AE40=1,AF40=1),1,0) -> 1 | AH40: Supplied abstract/coding notes; no new full-text verification | AI40: https://doi.org/10.32604/cmc.2023.032586 | AJ40: EVIDENCIA; original abstract/coding notes and lot source trace; Historical signals: title/abstract/notes; full-text completion not independently established | AK40: Cross-sectional ASD classification, not temporal prognosis. Abstract identifies GRU but not the biomedical input source; distinct benchmark datasets do not establish fusion. | AL40: Not applicable | AM40: Not separately specified | AO40: No additional status determination | AP40: Not documented for this recharting | AQ40: ChatGPT-assisted evidence recharting, 2026-09-08 | AS40: Not recorded; historical inclusion retained
A41: 38 | B41: Historical | C41: Machine learning analysis of pregnancy data enables early identification of a subpopulation of newborns with ASD | D41: 10.1038/s41598-021-86320-0 | E41: 2021 | F41: Include | G41: =IF(F41="Include",1,0) -> 1 | H41: Prognosis | I41: Machine Learning | J41: Structured clinical/questionnaire data | K41: XGBoost | L41: Gradient boosting | M41: Proposed only | N41: Risk/trajectory estimation | O41: Pre-decision | P41: Not observed in assessed sources | Q41: Not reported in assessed sources | R41: Not reported in assessed sources | S41: Reported | T41: Reported | U41: Not reported in assessed sources | V41: Not reported in assessed sources | W41: Not reported in assessed sources | X41: Not reported in assessed sources | Y41: Not ascertainable | Z41: Not reported in assessed sources | AA41: Not recorded | AB41: 0 | AC41: 0 | AD41: =IF(AND(G41=1,AB41=0),1,0) -> 1 | AE41: =IF(AND(AD41=1,AC41=0),1,0) -> 1 | AF41: =IF(AND(G41=1,H41<>"Not specified"),1,0) -> 1 | AG41: =IF(AND(AE41=1,AF41=1),1,0) -> 1 | AH41: Supplied abstract/coding notes; no new full-text verification | AI41: https://doi.org/10.1038/s41598-021-86320-0 | AJ41: EVIDENCIA; original abstract/coding notes and lot source trace; Historical signals: title/abstract/notes; full-text completion not independently established | AK41: Retrospective pregnancy and birth measurements predict later ASD. Numeric ultrasound measurements are structured records, not raw imaging inputs. SHAP is explicitly documented in source coding notes. | AL41: Not applicable | AM41: Not separately specified | AO41: No additional status determination | AP41: Not documented for this recharting | AQ41: ChatGPT-assisted evidence recharting, 2026-09-08 | AS41: Not recorded; historical inclusion retained
A42: 39 | B42: Historical | C42: Machine Learning-Based Blood RNA Signature for Diagnosis of Autism Spectrum Disorder | D42: 10.3390/ijms24032082 | E42: 2023 | F42: Include | G42: =IF(F42="Include",1,0) -> 1 | H42: Diagnosis | I42: Machine Learning | J42: Biological/omics | K42: Random forest | L42: Random forest | M42: Research only | N42: Automated measurement/classification | O42: Not observed in assessed sources | P42: Not observed in assessed sources | Q42: Not reported in assessed sources | R42: Not reported in assessed sources | S42: Not reported in assessed sources | T42: Not reported in assessed sources | U42: Not reported in assessed sources | V42: Not reported in assessed sources | W42: Not reported in assessed sources | X42: Not reported in assessed sources | Y42: Not ascertainable | Z42: Not reported in assessed sources | AA42: Not recorded | AB42: 0 | AC42: 0 | AD42: =IF(AND(G42=1,AB42=0),1,0) -> 1 | AE42: =IF(AND(AD42=1,AC42=0),1,0) -> 1 | AF42: =IF(AND(G42=1,H42<>"Not specified"),1,0) -> 1 | AG42: =IF(AND(AE42=1,AF42=1),1,0) -> 1 | AH42: Supplied abstract/coding notes; no new full-text verification | AI42: https://doi.org/10.3390/ijms24032082 | AJ42: EVIDENCIA; original abstract/coding notes and lot source trace; Historical signals: title/abstract/notes; full-text completion not independently established | AK42: Blood RNA sequencing classifier; abstract calls for further independent validation, not a deployed diagnostic workflow. | AL42: Not applicable | AM42: Not separately specified | AO42: No additional status determination | AP42: Not documented for this recharting | AQ42: ChatGPT-assisted evidence recharting, 2026-09-08 | AS42: Not recorded; historical inclusion retained
A43: 40 | B43: Historical | C43: Metabolomic analysis of maternal mid-gestation plasma and cord blood in autism spectrum disorders | D43: 10.1038/s41380-023-02051-w | E43: 2023 | F43: Include | G43: =IF(F43="Include",1,0) -> 1 | H43: Prognosis | I43: Machine Learning | J43: Biological/omics | K43: Multiple machine-learning classifiers; principal family unresolved | L43: Multiple/not uniquely specified | M43: Research only | N43: Risk/trajectory estimation | O43: Not observed in assessed sources | P43: Not observed in assessed sources | Q43: Not reported in assessed sources | R43: Not reported in assessed sources | S43: Not reported in assessed sources | T43: Not reported in assessed sources | U43: Not reported in assessed sources | V43: Not reported in assessed sources | W43: Reported | X43: Not reported in assessed sources | Y43: Not ascertainable | Z43: Not reported in assessed sources | AA43: Not recorded | AB43: 0 | AC43: 0 | AD43: =IF(AND(G43=1,AB43=0),1,0) -> 1 | AE43: =IF(AND(AD43=1,AC43=0),1,0) -> 1 | AF43: =IF(AND(G43=1,H43<>"Not specified"),1,0) -> 1 | AG43: =IF(AND(AE43=1,AF43=1),1,0) -> 1 | AH43: Supplied abstract/coding notes; no new full-text verification | AI43: https://doi.org/10.1038/s41380-023-02051-w | AJ43: EVIDENCIA; original abstract/coding notes and lot source trace; Historical signals: title/abstract/notes; full-text completion not independently established | AK43: Maternal mid-gestation and cord-blood metabolomic profiles predict subsequent ASD. Source describes separate analyses, not demonstrated combined-input prediction. | AL43: Not applicable | AM43: Not separately specified | AO43: No additional status determination | AP43: Not documented for this recharting | AQ43: ChatGPT-assisted evidence recharting, 2026-09-08 | AS43: Not recorded; historical inclusion retained
A44: 41 | B44: Historical | C44: Predictors of age at diagnosis in autism spectrum disorders: the use of multiple regression analyses and a classification tree on a clinical sample | D44: 10.1007/s00787-023-02189-6 | E44: 2023 | F44: Include | G44: =IF(F44="Include",1,0) -> 1 | H44: Not specified | I44: Machine Learning | J44: Structured clinical/questionnaire data | K44: Regression and classification tree | L44: Other specified method | M44: Research only | N44: Research characterization | O44: Not observed in assessed sources | P44: Not observed in assessed sources | Q44: Not reported in assessed sources | R44: Not reported in assessed sources | S44: Not reported in assessed sources | T44: Not reported in assessed sources | U44: Not reported in assessed sources | V44: Not reported in assessed sources | W44: Not reported in assessed sources | X44: Not reported in assessed sources | Y44: Not ascertainable | Z44: Not reported in assessed sources | AA44: Not recorded | AB44: 0 | AC44: 0 | AD44: =IF(AND(G44=1,AB44=0),1,0) -> 1 | AE44: =IF(AND(AD44=1,AC44=0),1,0) -> 1 | AF44: =IF(AND(G44=1,H44<>"Not specified"),1,0) -> 0 | AG44: =IF(AND(AE44=1,AF44=1),1,0) -> 0 | AH44: Supplied abstract/coding notes; no new full-text verification | AI44: https://doi.org/10.1007/s00787-023-02189-6 | AJ44: EVIDENCIA; original abstract/coding notes and lot source trace; Historical signals: title/abstract/notes; full-text completion not independently established | AK44: Retrospective predictors of age at diagnosis; relevant care-pathway characterization but no uniquely supported prospective clinical stage. | AL44: Not applicable | AM44: Not separately specified | AO44: No additional status determination | AP44: Not documented for this recharting | AQ44: ChatGPT-assisted evidence recharting, 2026-09-08 | AR44: RA | AS44: Not recorded; historical inclusion retained
A45: 42 | B45: Historical | C45: Promoting emotional and behavioral interventions in ASD treatment: Evidence from EPIGRAM, A naturalistic, prospective and longitudinal study | D45: 10.1016/j.ridd.2024.104688 | E45: 2024 | F45: Include | G45: =IF(F45="Include",1,0) -> 1 | H45: Prognosis | I45: Machine Learning | J45: Structured clinical/questionnaire data | K45: CART and multivariable regression | L45: Other specified method | M45: Research only | N45: Risk/trajectory estimation | O45: Not observed in assessed sources | P45: Not observed in assessed sources | Q45: Not reported in assessed sources | R45: Not reported in assessed sources | S45: Not reported in assessed sources | T45: Not reported in assessed sources | U45: Not reported in assessed sources | V45: Not reported in assessed sources | W45: Not reported in assessed sources | X45: Not reported in assessed sources | Y45: Reported | Z45: Not reported in assessed sources | AA45: Not recorded | AB45: 0 | AC45: 0 | AD45: =IF(AND(G45=1,AB45=0),1,0) -> 1 | AE45: =IF(AND(AD45=1,AC45=0),1,0) -> 1 | AF45: =IF(AND(G45=1,H45<>"Not specified"),1,0) -> 1 | AG45: =IF(AND(AE45=1,AF45=1),1,0) -> 1 | AH45: Supplied abstract/coding notes; no new full-text verification | AI45: https://doi.org/10.1016/j.ridd.2024.104688 | AJ45: EVIDENCIA; original abstract/coding notes and lot source trace; Historical signals: title/abstract/notes; full-text completion not independently established | AK45: Prognostic analysis of 12-month intervention outcomes. Prospective patient follow-up is not evidence that AI selected or adapted the treatment. | AL45: Not applicable | AM45: Not separately specified | AO45: No additional status determination | AP45: Not documented for this recharting | AQ45: ChatGPT-assisted evidence recharting, 2026-09-08 | AR45: RA | AS45: Not recorded; historical inclusion retained
A46: 43 | B46: Historical | C46: The role of the dopamine system in autism spectrum disorder revealed using machine learning: an ABIDE database–based study | D46: 10.1093/cercor/bhaf022 | E46: 2025 | F46: Include | G46: =IF(F46="Include",1,0) -> 1 | H46: Diagnosis | I46: Machine Learning | J46: Neuroimaging | K46: Classification and clustering; principal family unresolved | L46: Clustering | M46: Research only | N46: Automated measurement/classification | O46: Not observed in assessed sources | P46: Not observed in assessed sources | Q46: Not reported in assessed sources | R46: Not reported in assessed sources | S46: Not reported in assessed sources | T46: Not reported in assessed sources | U46: Not reported in assessed sources | V46: Reported | W46: Not reported in assessed sources | X46: Not reported in assessed sources | Y46: Not ascertainable | Z46: Not reported in assessed sources | AA46: Not recorded | AB46: 0 | AC46: 0 | AD46: =IF(AND(G46=1,AB46=0),1,0) -> 1 | AE46: =IF(AND(AD46=1,AC46=0),1,0) -> 1 | AF46: =IF(AND(G46=1,H46<>"Not specified"),1,0) -> 1 | AG46: =IF(AND(AE46=1,AF46=1),1,0) -> 1 | AH46: Supplied abstract/coding notes; no new full-text verification | AI46: https://doi.org/10.1093/cercor/bhaf022 | AJ46: EVIDENCIA; original abstract/coding notes and lot source trace; Historical signals: title/abstract/notes; full-text completion not independently established | AK46: fMRI analysis of dopaminergic regions. Multiple brain regions and computational representations do not establish separate data modalities or deep learning. | AL46: Not applicable | AM46: Not separately specified | AO46: No additional status determination | AP46: Not documented for this recharting | AQ46: ChatGPT-assisted evidence recharting, 2026-09-08 | AS46: Not recorded; historical inclusion retained
A47: 44 | B47: Historical | C47: Using Artificial Intelligence to Identify Factors Associated with Autism Spectrum Disorder in Adolescents with Cerebral Palsy | D47: 10.1055/s-0039-1685525 | E47: 2019 | F47: Include | G47: =IF(F47="Include",1,0) -> 1 | H47: Diagnosis | I47: Machine Learning | J47: Structured clinical/questionnaire data | K47: Logistic regression | L47: Logistic regression | M47: Research only | N47: Risk/trajectory estimation | O47: Not observed in assessed sources | P47: Not observed in assessed sources | Q47: Not reported in assessed sources | R47: Not reported in assessed sources | S47: Not reported in assessed sources | T47: Not reported in assessed sources | U47: Not reported in assessed sources | V47: Reported | W47: Not reported in assessed sources | X47: Not reported in assessed sources | Y47: Not ascertainable | Z47: Not reported in assessed sources | AA47: Not recorded | AB47: 0 | AC47: 0 | AD47: =IF(AND(G47=1,AB47=0),1,0) -> 1 | AE47: =IF(AND(AD47=1,AC47=0),1,0) -> 1 | AF47: =IF(AND(G47=1,H47<>"Not specified"),1,0) -> 1 | AG47: =IF(AND(AE47=1,AF47=1),1,0) -> 1 | AH47: Supplied abstract/coding notes; no new full-text verification | AI47: https://doi.org/10.1055/s-0039-1685525 | AJ47: EVIDENCIA; original abstract/coding notes and lot source trace; Historical signals: title/abstract/notes; full-text completion not independently established | AK47: ASD co-occurrence is the model endpoint in adolescents with cerebral palsy; multicentre clinical variables, not a prospective risk forecast. | AL47: Not applicable | AM47: Not separately specified | AO47: No additional status determination | AP47: Not documented for this recharting | AQ47: ChatGPT-assisted evidence recharting, 2026-09-08 | AR47: RA | AS47: Not recorded; historical inclusion retained
A48: 45 | B48: Historical | C48: Using resting state functional MRI to build a personalized autism diagnosis system | D48: 10.1371/journal.pone.0206351 | E48: 2018 | F48: Include | G48: =IF(F48="Include",1,0) -> 1 | H48: Diagnosis | I48: Hybrid | J48: Neuroimaging | K48: Stacked autoencoder with probabilistic SVM | L48: Composite/ensemble pipeline | M48: Proposed only | N48: Diagnostic decision support | O48: In-decision | P48: Not observed in assessed sources | Q48: Not reported in assessed sources | R48: Not reported in assessed sources | S48: Not reported in assessed sources | T48: Not reported in assessed sources | U48: Not reported in assessed sources | V48: Not reported in assessed sources | W48: Not reported in assessed sources | X48: Not reported in assessed sources | Y48: Not ascertainable | Z48: Not reported in assessed sources | AA48: Not recorded | AB48: 0 | AC48: 0 | AD48: =IF(AND(G48=1,AB48=0),1,0) -> 1 | AE48: =IF(AND(AD48=1,AC48=0),1,0) -> 1 | AF48: =IF(AND(G48=1,H48<>"Not specified"),1,0) -> 1 | AG48: =IF(AND(AE48=1,AF48=1),1,0) -> 1 | AH48: Supplied abstract/coding notes; no new full-text verification | AI48: https://doi.org/10.1371/journal.pone.0206351 | AJ48: EVIDENCIA; original abstract/coding notes and lot source trace; Historical signals: title/abstract/notes; full-text completion not independently established | AK48: Actual ML-DL pipeline is stated; PSD features and autoencoder representations originate from the same resting-state fMRI. Personalized reports were proposed, not evaluated in clinician decisions. | AL48: Not applicable | AM48: Not separately specified | AO48: No additional status determination | AP48: Not documented for this recharting | AQ48: ChatGPT-assisted evidence recharting, 2026-09-08 | AR48: RA | AS48: Not recorded; historical inclusion retained
A49: 46 | B49: Historical | C49: A Model to Support the Prediction of Indicators in the Diagnosis and Intervention of Autism Spectrum Disorder | D49: 10.1007/978-3-031-48642-5_7 | E49: 2023 | F49: Include | G49: =IF(F49="Include",1,0) -> 1 | H49: Monitoring/intervention | I49: Not specified | J49: Text/language | K49: Transformer or ChatGPT proposed; implemented architecture unresolved | L49: Transformer | M49: Proposed only | N49: Adaptive intervention | O49: Post-decision | P49: Not observed in assessed sources | Q49: Not reported in assessed sources | R49: Not ascertainable | S49: Not reported in assessed sources | T49: Not reported in assessed sources | U49: Not reported in assessed sources | V49: Not reported in assessed sources | W49: Reported | X49: Not reported in assessed sources | Y49: Not ascertainable | Z49: Not reported in assessed sources | AA49: Not recorded | AB49: 0 | AC49: 0 | AD49: =IF(AND(G49=1,AB49=0),1,0) -> 1 | AE49: =IF(AND(AD49=1,AC49=0),1,0) -> 1 | AF49: =IF(AND(G49=1,H49<>"Not specified"),1,0) -> 1 | AG49: =IF(AND(AE49=1,AF49=1),1,0) -> 1 | AH49: Supplied abstract/coding notes; no new full-text verification | AI49: https://doi.org/10.1007/978-3-031-48642-5_7 | AJ49: EVIDENCIA; original abstract/coding notes and lot source trace; Historical signals: title/abstract/notes; full-text completion not independently established | AK49: Ongoing NLP project uses conversations or writing to inform intervention indicators. Proposed architecture is not sufficient to assert an implemented deep-learning family or a clinical intervention deployment. | AL49: Not applicable | AM49: Not separately specified | AO49: No additional status determination | AP49: Not documented for this recharting | AQ49: ChatGPT-assisted evidence recharting, 2026-09-08 | AR49: RA | AS49: Not recorded; historical inclusion retained
A50: 47 | B50: Historical | C50: A novel multi-modal model to assist the diagnosis of autism spectrum disorder using eye-tracking data | D50: 10.1007/s13755-024-00299-2 | E50: 2024 | F50: Include | G50: =IF(F50="Include",1,0) -> 1 | H50: Diagnosis | I50: Deep Learning | J50: Behavioral images/video/gaze/movement | K50: CNN-GRU-ANN | L50: Composite/ensemble pipeline | M50: Research only | N50: Automated measurement/classification | O50: Not observed in assessed sources | P50: Not observed in assessed sources | Q50: Not reported in assessed sources | R50: Not reported in assessed sources | S50: Not reported in assessed sources | T50: Not reported in assessed sources | U50: Not reported in assessed sources | V50: Not reported in assessed sources | W50: Not reported in assessed sources | X50: Not reported in assessed sources | Y50: Not ascertainable | Z50: Not reported in assessed sources | AA50: Not recorded | AB50: 0 | AC50: 0 | AD50: =IF(AND(G50=1,AB50=0),1,0) -> 1 | AE50: =IF(AND(AD50=1,AC50=0),1,0) -> 1 | AF50: =IF(AND(G50=1,H50<>"Not specified"),1,0) -> 1 | AG50: =IF(AND(AE50=1,AF50=1),1,0) -> 1 | AH50: Supplied abstract/coding notes; no new full-text verification | AI50: https://doi.org/10.1007/s13755-024-00299-2 | AJ50: EVIDENCIA; original abstract/coding notes and lot source trace; Historical signals: title/abstract/notes; full-text completion not independently established | AK50: Scanpaths, distances and fixation durations derive from eye tracking; multiple representations do not by themselves establish multisource integration. All named components are neural, not an ML-DL hybrid. | AL50: Not applicable | AM50: Not separately specified | AO50: No additional status determination | AP50: Not documented for this recharting | AQ50: ChatGPT-assisted evidence recharting, 2026-09-08 | AS50: Not recorded; historical inclusion retained
A51: 48 | B51: Historical | C51: A randomized controlled trial of 25 sessions comparing music therapy and music listening for children with autism spectrum disorder | D51: 10.1016/j.psychres.2020.113377 | E51: 2020 | F51: Exclude | G51: =IF(F51="Include",1,0) -> 0 | H51: Excluded | I51: Excluded | J51: Excluded | K51: Other / Not clear | L51: Other specified method | M51: Excluded | N51: Excluded | O51: Not applicable - excluded | P51: Not applicable - excluded | Q51: Not reported in assessed sources | R51: Not reported in assessed sources | S51: Not reported in assessed sources | T51: Not reported in assessed sources | U51: Not reported in assessed sources | V51: Not reported in assessed sources | W51: Not reported in assessed sources | X51: Not reported in assessed sources | Y51: Not ascertainable | Z51: Not reported in assessed sources | AA51: Not recorded | AB51: 0 | AC51: 0 | AD51: =IF(AND(G51=1,AB51=0),1,0) -> 0 | AE51: =IF(AND(AD51=1,AC51=0),1,0) -> 0 | AF51: =IF(AND(G51=1,H51<>"Not specified"),1,0) -> 0 | AG51: =IF(AND(AE51=1,AF51=1),1,0) -> 0 | AH51: Primary-source full text (targeted sections) | AI51: https://extradoc.univ-nantes.fr/pluginfile.php/412199/mod_folder/content/0/article%20Bonnot-Vrait-Carasco-Rabeyron....pdf | AJ51: Abstract and Methods, pp. 1-3 | AK51: Verified original music-therapy RCT uses ML as music listening, not machine learning. The stored eye-tracking abstract belongs to a different report and is quarantined. | AL51: EC3 No qualifying AI evaluation | AM51: Not separately specified | AO51: No additional status determination | AP51: Not documented for this recharting | AQ51: ChatGPT-assisted evidence recharting, 2026-09-08 | AR51: RA | AS51: Not recorded; historical inclusion retained
A52: 49 | B52: Historical | C52: A Triple-Pooling Graph Neural Network for\&#xa0;Multi-scale Topological Learning of\&#xa0;Brain Functional Connectivity: Application to\&#xa0;ASD Diagnosis | D52: 10.1007/978-3-030-93049-3_30 | E52: 2021 | F52: Include | G52: =IF(F52="Include",1,0) -> 1 | H52: Diagnosis | I52: Deep Learning | J52: Neuroimaging | K52: Triple-pooling graph neural network | L52: GNN | M52: Research only | N52: Automated measurement/classification | O52: Not observed in assessed sources | P52: Not observed in assessed sources | Q52: Not reported in assessed sources | R52: Not reported in assessed sources | S52: Not reported in assessed sources | T52: Not reported in assessed sources | U52: Not reported in assessed sources | V52: Not reported in assessed sources | W52: Not reported in assessed sources | X52: Not reported in assessed sources | Y52: Not ascertainable | Z52: Not reported in assessed sources | AA52: Not recorded | AB52: 0 | AC52: 0 | AD52: =IF(AND(G52=1,AB52=0),1,0) -> 1 | AE52: =IF(AND(AD52=1,AC52=0),1,0) -> 1 | AF52: =IF(AND(G52=1,H52<>"Not specified"),1,0) -> 1 | AG52: =IF(AND(AE52=1,AF52=1),1,0) -> 1 | AH52: Supplied abstract/coding notes; no new full-text verification | AI52: https://doi.org/10.1007/978-3-030-93049-3_30 | AJ52: EVIDENCIA; original abstract/coding notes and lot source trace; Historical signals: title/abstract/notes; full-text completion not independently established | AK52: Functional brain-connectivity graphs are derived from resting-state fMRI; graph neural network is retained as its own family rather than Other or conventional CNN. | AL52: Not applicable | AM52: Not separately specified | AO52: No additional status determination | AP52: Not documented for this recharting | AQ52: ChatGPT-assisted evidence recharting, 2026-09-08 | AS52: Not recorded; historical inclusion retained
A53: 51 | B53: Historical | C53: Bilinear Perceptual Fusion Algorithm Based on Brain Functional and Structural Data for ASD Diagnosis and Regions of Interest Identification | D53: 10.1007/s12539-024-00651-w | E53: 2024 | F53: Include | G53: =IF(F53="Include",1,0) -> 1 | H53: Diagnosis | I53: Deep Learning | J53: Neuroimaging | K53: Bilinear perceptual fusion GCN | L53: GNN | M53: Proposed only | N53: Diagnostic decision support | O53: In-decision | P53: Not observed in assessed sources | Q53: Not reported in assessed sources | R53: Reported | S53: Not reported in assessed sources | T53: Not reported in assessed sources | U53: Not reported in assessed sources | V53: Not reported in assessed sources | W53: Reported | X53: Not reported in assessed sources | Y53: Not ascertainable | Z53: Not reported in assessed sources | AA53: Not recorded | AB53: 0 | AC53: 0 | AD53: =IF(AND(G53=1,AB53=0),1,0) -> 1 | AE53: =IF(AND(AD53=1,AC53=0),1,0) -> 1 | AF53: =IF(AND(G53=1,H53<>"Not specified"),1,0) -> 1 | AG53: =IF(AND(AE53=1,AF53=1),1,0) -> 1 | AH53: Supplied abstract/coding notes; no new full-text verification | AI53: https://doi.org/10.1007/s12539-024-00651-w | AJ53: EVIDENCIA; original abstract/coding notes and lot source trace; Historical signals: title/abstract/notes; full-text completion not independently established | AK53: Explicit deep graph architecture fuses structural and functional brain data; within-neuroimaging multimodal integration is retained. | AL53: Not applicable | AM53: Not separately specified | AO53: No additional status determination | AP53: Not documented for this recharting | AQ53: ChatGPT-assisted evidence recharting, 2026-09-08 | AR53: RA | AS53: Not recorded; historical inclusion retained
A54: 52 | B54: Historical | C54: Computer-aided diagnosis of autism spectrum disorder from EEG signals using deep learning with FAWT and multiscale permutation entropy features | D54: 10.1177/09544119221141751 | E54: 2023 | F54: Include | G54: =IF(F54="Include",1,0) -> 1 | H54: Diagnosis | I54: Deep Learning | J54: Physiological signals | K54: CNN | L54: CNN | M54: Proposed only | N54: Diagnostic decision support | O54: In-decision | P54: Not observed in assessed sources | Q54: Not reported in assessed sources | R54: Not reported in assessed sources | S54: Not reported in assessed sources | T54: Not reported in assessed sources | U54: Not reported in assessed sources | V54: Not reported in assessed sources | W54: Not reported in assessed sources | X54: Not reported in assessed sources | Y54: Not ascertainable | Z54: Not reported in assessed sources | AA54: Not recorded | AB54: 0 | AC54: 0 | AD54: =IF(AND(G54=1,AB54=0),1,0) -> 1 | AE54: =IF(AND(AD54=1,AC54=0),1,0) -> 1 | AF54: =IF(AND(G54=1,H54<>"Not specified"),1,0) -> 1 | AG54: =IF(AND(AE54=1,AF54=1),1,0) -> 1 | AH54: Supplied abstract/coding notes; no new full-text verification | AI54: https://doi.org/10.1177/09544119221141751 | AJ54: EVIDENCIA; original abstract/coding notes and lot source trace; Historical signals: title/abstract/notes; full-text completion not independently established | AK54: EEG wavelet and entropy preprocessing followed by CNN; comparison with conventional classifiers is not an integrated ML-DL hybrid or demonstrated clinician use. | AL54: Not applicable | AM54: Not separately specified | AO54: No additional status determination | AP54: Not documented for this recharting | AQ54: ChatGPT-assisted evidence recharting, 2026-09-08 | AR54: RA | AS54: Not recorded; historical inclusion retained
A55: 53 | B55: Historical | C55: Development and validation of a machine learning-based tool to predict autism among children | D55: 10.1002/aur.2912 | E55: 2023 | F55: Include | G55: =IF(F55="Include",1,0) -> 1 | H55: Prognosis | I55: Machine Learning | J55: Structured clinical/questionnaire data | K55: Logistic regression and gradient-boosted trees | L55: Composite/ensemble pipeline | M55: Proposed only | N55: Risk/trajectory estimation | O55: Pre-decision | P55: Not observed in assessed sources | Q55: Not reported in assessed sources | R55: Reported | S55: Not reported in assessed sources | T55: Not reported in assessed sources | U55: Not reported in assessed sources | V55: Not reported in assessed sources | W55: Reported | X55: Not reported in assessed sources | Y55: Not ascertainable | Z55: Not reported in assessed sources | AA55: Not recorded | AB55: 0 | AC55: 0 | AD55: =IF(AND(G55=1,AB55=0),1,0) -> 1 | AE55: =IF(AND(AD55=1,AC55=0),1,0) -> 1 | AF55: =IF(AND(G55=1,H55<>"Not specified"),1,0) -> 1 | AG55: =IF(AND(AE55=1,AF55=1),1,0) -> 1 | AH55: Supplied abstract/coding notes; no new full-text verification | AI55: https://doi.org/10.1002/aur.2912 | AJ55: EVIDENCIA; original abstract/coding notes and lot source trace; Historical signals: title/abstract/notes; full-text completion not independently established | AK55: Linked maternal and infant administrative records predict later ASD; not a contemporaneous diagnostic or deployed clinical tool. | AL55: Not applicable | AM55: Not separately specified | AO55: No additional status determination | AP55: Not documented for this recharting | AQ55: ChatGPT-assisted evidence recharting, 2026-09-08 | AS55: Not recorded; historical inclusion retained
A56: 54 | B56: Historical | C56: Diagnostic classification of intrinsic functional connectivity highlights somatosensory, default mode, and visual regions in autism | D56: 10.1016/j.nicl.2015.04.002 | E56: 2015 | F56: Include | G56: =IF(F56="Include",1,0) -> 1 | H56: Diagnosis | I56: Machine Learning | J56: Neuroimaging | K56: Random forest | L56: Random forest | M56: Research only | N56: Automated measurement/classification | O56: Not observed in assessed sources | P56: Not observed in assessed sources | Q56: Not reported in assessed sources | R56: Not reported in assessed sources | S56: Reported | T56: Not reported in assessed sources | U56: Not reported in assessed sources | V56: Reported | W56: Not reported in assessed sources | X56: Not reported in assessed sources | Y56: Not ascertainable | Z56: Reported | AA56: Not recorded | AB56: 0 | AC56: 0 | AD56: =IF(AND(G56=1,AB56=0),1,0) -> 1 | AE56: =IF(AND(AD56=1,AC56=0),1,0) -> 1 | AF56: =IF(AND(G56=1,H56<>"Not specified"),1,0) -> 1 | AG56: =IF(AND(AE56=1,AF56=1),1,0) -> 1 | AH56: Supplied abstract/coding notes; no new full-text verification | AI56: https://doi.org/10.1016/j.nicl.2015.04.002 | AJ56: EVIDENCIA; original abstract/coding notes and lot source trace; Historical signals: title/abstract/notes; full-text completion not independently established | AK56: ABIDE resting-state fMRI classification. Identification of informative functional connections provides partial interpretability; multisite data alone are not cross-site testing. | AL56: Not applicable | AM56: Not separately specified | AO56: No additional status determination | AP56: Not documented for this recharting | AQ56: ChatGPT-assisted evidence recharting, 2026-09-08 | AS56: Not recorded; historical inclusion retained
A57: 56 | B57: Historical | C57: Epigenomic signatures reveal mechanistic clues and predictive markers for autism spectrum disorder | D57: 10.1038/s41380-022-01917-9 | E57: 2023 | F57: Exclude | G57: =IF(F57="Include",1,0) -> 0 | H57: Excluded | I57: Excluded | J57: Excluded | K57: Not specified | L57: Multiple/not uniquely specified | M57: Excluded | N57: Excluded | O57: Not applicable - excluded | P57: Not applicable - excluded | Q57: Not reported in assessed sources | R57: Not reported in assessed sources | S57: Not reported in assessed sources | T57: Not reported in assessed sources | U57: Not reported in assessed sources | V57: Not reported in assessed sources | W57: Not reported in assessed sources | X57: Not reported in assessed sources | Y57: Not ascertainable | Z57: Not reported in assessed sources | AA57: Not recorded | AB57: 0 | AC57: 0 | AD57: =IF(AND(G57=1,AB57=0),1,0) -> 0 | AE57: =IF(AND(AD57=1,AC57=0),1,0) -> 0 | AF57: =IF(AND(G57=1,H57<>"Not specified"),1,0) -> 0 | AG57: =IF(AND(AE57=1,AF57=1),1,0) -> 0 | AH57: Supplied abstract/coding notes; no new full-text verification | AI57: https://doi.org/10.1038/s41380-022-01917-9 | AJ57: EVIDENCIA; original abstract/coding notes and lot source trace; Historical signals: title/abstract/notes; full-text completion not independently established | AK57: Narrative synthesis of epigenomic signatures and anticipated future ML applications, not an original evaluated AI method. | AL57: EC1 Non-primary review | AM57: Not separately specified | AO57: No additional status determination | AP57: Not documented for this recharting | AQ57: ChatGPT-assisted evidence recharting, 2026-09-08 | AS57: Not recorded; historical inclusion retained
A58: 57 | B58: Historical | C58: Evaluation and benchmarking of hybrid machine learning models for autism spectrum disorder diagnosis using a 2-tuple linguistic neutrosophic fuzzy sets-based decision-making model | D58: 10.1007/s00521-024-09905-6 | E58: 2024 | F58: Include | G58: =IF(F58="Include",1,0) -> 1 | H58: Diagnosis | I58: Machine Learning | J58: Structured clinical/questionnaire data | K58: Feature selection, multiple ML models and fuzzy multicriteria ranking | L58: Multiple/not uniquely specified | M58: Research only | N58: Diagnostic decision support | O58: Not observed in assessed sources | P58: Not observed in assessed sources | Q58: Not reported in assessed sources | R58: Not reported in assessed sources | S58: Not reported in assessed sources | T58: Not reported in assessed sources | U58: Not reported in assessed sources | V58: Not reported in assessed sources | W58: Not reported in assessed sources | X58: Not reported in assessed sources | Y58: Not ascertainable | Z58: Not reported in assessed sources | AA58: Not recorded | AB58: 0 | AC58: 0 | AD58: =IF(AND(G58=1,AB58=0),1,0) -> 1 | AE58: =IF(AND(AD58=1,AC58=0),1,0) -> 1 | AF58: =IF(AND(G58=1,H58<>"Not specified"),1,0) -> 1 | AG58: =IF(AND(AE58=1,AF58=1),1,0) -> 1 | AH58: Supplied abstract/coding notes; no new full-text verification | AI58: https://doi.org/10.1007/s00521-024-09905-6 | AJ58: EVIDENCIA; original abstract/coding notes and lot source trace; Historical signals: title/abstract/notes; full-text completion not independently established | AK58: Linguistic neutrosophic sets are the ranking representation, not patient natural-language inputs. Empirical data comprise medical and sociodemographic variables. | AL58: Not applicable | AM58: Not separately specified | AO58: No additional status determination | AP58: Not documented for this recharting | AQ58: ChatGPT-assisted evidence recharting, 2026-09-08 | AR58: RA | AS58: Not recorded; historical inclusion retained
A59: 58 | B59: Historical | C59: Event Related Potential Analysis Using Machine Learning to Predict Diagnostic Outcome of Autism Spectrum Disorder | D59: 10.1007/978-3-030-88163-4_7 | E59: 2021 | F59: Include | G59: =IF(F59="Include",1,0) -> 1 | H59: Prognosis | I59: Machine Learning | J59: Physiological signals | K59: Decision tree | L59: Decision tree/rules | M59: Research only | N59: Risk/trajectory estimation | O59: Not observed in assessed sources | P59: Not observed in assessed sources | Q59: Not reported in assessed sources | R59: Not reported in assessed sources | S59: Not reported in assessed sources | T59: Not reported in assessed sources | U59: Not reported in assessed sources | V59: Not reported in assessed sources | W59: Not reported in assessed sources | X59: Not reported in assessed sources | Y59: Reported | Z59: Not reported in assessed sources | AA59: Not recorded | AB59: 0 | AC59: 0 | AD59: =IF(AND(G59=1,AB59=0),1,0) -> 1 | AE59: =IF(AND(AD59=1,AC59=0),1,0) -> 1 | AF59: =IF(AND(G59=1,H59<>"Not specified"),1,0) -> 1 | AG59: =IF(AND(AE59=1,AF59=1),1,0) -> 1 | AH59: Supplied abstract/coding notes; no new full-text verification | AI59: https://doi.org/10.1007/978-3-030-88163-4_7 | AJ59: EVIDENCIA; original abstract/coding notes and lot source trace; Historical signals: title/abstract/notes; full-text completion not independently established | AK59: Six-month infant EEG event-related potentials predict subsequent diagnostic outcome; visual stimuli are not image inputs to the model. | AL59: Not applicable | AM59: Not separately specified | AO59: No additional status determination | AP59: Not documented for this recharting | AQ59: ChatGPT-assisted evidence recharting, 2026-09-08 | AS59: Not recorded; historical inclusion retained
A60: 59 | B60: Historical | C60: Functional Connectivities Are More Informative Than Anatomical Variables in Diagnostic Classification of Autism | D60: 10.1089/brain.2019.0689 | E60: 2019 | F60: Include | G60: =IF(F60="Include",1,0) -> 1 | H60: Diagnosis | I60: Machine Learning | J60: Neuroimaging | K60: Conditional random forest | L60: Random forest | M60: Research only | N60: Automated measurement/classification | O60: Not observed in assessed sources | P60: Not observed in assessed sources | Q60: Not reported in assessed sources | R60: Reported | S60: Not reported in assessed sources | T60: Not reported in assessed sources | U60: Not reported in assessed sources | V60: Not reported in assessed sources | W60: Reported | X60: Not reported in assessed sources | Y60: Not ascertainable | Z60: Not reported in assessed sources | AA60: Not recorded | AB60: 0 | AC60: 0 | AD60: =IF(AND(G60=1,AB60=0),1,0) -> 1 | AE60: =IF(AND(AD60=1,AC60=0),1,0) -> 1 | AF60: =IF(AND(G60=1,H60<>"Not specified"),1,0) -> 1 | AG60: =IF(AND(AE60=1,AF60=1),1,0) -> 1 | AH60: Supplied abstract/coding notes; no new full-text verification | AI60: https://doi.org/10.1089/brain.2019.0689 | AJ60: EVIDENCIA; original abstract/coding notes and lot source trace; Historical signals: title/abstract/notes; full-text completion not independently established | AK60: Diagnostic comparison and explicit fusion of anatomical MRI, DWI and functional MRI; not monitoring or intervention. | AL60: Not applicable | AM60: Not separately specified | AO60: No additional status determination | AP60: Not documented for this recharting | AQ60: ChatGPT-assisted evidence recharting, 2026-09-08 | AS60: Not recorded; historical inclusion retained
A61: 60 | B61: Historical | C61: Hyperuricemia and Metabolic Adverse Effect in Children and Adolescents with Autism Spectrum Disorder Treated with Risperidone | D61: 10.1016/j.eurpsy.2017.02.198 | E61: 2017 | F61: Exclude | G61: =IF(F61="Include",1,0) -> 0 | H61: Excluded | I61: Excluded | J61: Excluded | K61: Other / Not clear | L61: Other specified method | M61: Excluded | N61: Excluded | O61: Not applicable - excluded | P61: Not applicable - excluded | Q61: Not reported in assessed sources | R61: Not ascertainable | S61: Not reported in assessed sources | T61: Not reported in assessed sources | U61: Not reported in assessed sources | V61: Not reported in assessed sources | W61: Reported | X61: Not reported in assessed sources | Y61: Not ascertainable | Z61: Not reported in assessed sources | AA61: Not recorded | AB61: 0 | AC61: 0 | AD61: =IF(AND(G61=1,AB61=0),1,0) -> 0 | AE61: =IF(AND(AD61=1,AC61=0),1,0) -> 0 | AF61: =IF(AND(G61=1,H61<>"Not specified"),1,0) -> 0 | AG61: =IF(AND(AE61=1,AF61=1),1,0) -> 0 | AH61: Supplied abstract/coding notes; no new full-text verification | AI61: https://doi.org/10.1016/j.eurpsy.2017.02.198 | AJ61: EVIDENCIA; original abstract/coding notes and lot source trace; Historical signals: title/abstract/notes; full-text completion not independently established | AK61: Cross-sectional biochemical adverse-effect prevalence/correlation study, with no computational predictive model in the supplied report description. | AL61: EC3 No qualifying AI evaluation | AM61: Not separately specified | AO61: No additional status determination | AP61: Not documented for this recharting | AQ61: ChatGPT-assisted evidence recharting, 2026-09-08 | AR61: RA | AS61: Not recorded; historical inclusion retained
A62: 61 | B62: Historical | C62: Identifying Visual Attention Features Accurately Discerning Between Autism and Typically Developing: a Deep Learning Framework | D62: 10.1007/s12539-022-00510-6 | E62: 2022 | F62: Include | G62: =IF(F62="Include",1,0) -> 1 | H62: Diagnosis | I62: Deep Learning | J62: Behavioral images/video/gaze/movement | K62: Two-stream VGG16 framework | L62: CNN | M62: Proposed only | N62: Diagnostic decision support | O62: In-decision | P62: Not observed in assessed sources | Q62: Not reported in assessed sources | R62: Not reported in assessed sources | S62: Not ascertainable | T62: Not ascertainable | U62: Not reported in assessed sources | V62: Not reported in assessed sources | W62: Not reported in assessed sources | X62: Not reported in assessed sources | Y62: Not ascertainable | Z62: Not ascertainable | AA62: Not recorded | AB62: 0 | AC62: 0 | AD62: =IF(AND(G62=1,AB62=0),1,0) -> 1 | AE62: =IF(AND(AD62=1,AC62=0),1,0) -> 1 | AF62: =IF(AND(G62=1,H62<>"Not specified"),1,0) -> 1 | AG62: =IF(AND(AE62=1,AF62=1),1,0) -> 1 | AH62: Supplied abstract/coding notes; no new full-text verification | AI62: https://doi.org/10.1007/s12539-022-00510-6 | AJ62: EVIDENCIA; original abstract/coding notes and lot source trace; Historical signals: title/abstract/notes; full-text completion not independently established | AK62: Visual-attention classification and explicit feature-dissection by segmentation and image ablation. No longitudinal intervention was evaluated. | AL62: Not applicable | AM62: Not separately specified | AO62: No additional status determination | AP62: Not documented for this recharting | AQ62: ChatGPT-assisted evidence recharting, 2026-09-08 | AS62: Not recorded; historical inclusion retained
A63: 62 | B63: Historical | C63: Impact of DRD2 polymorphisms on prolactin level in risperidone-treated Thai children and adolescent with autism spectrum disorders | D63: 10.1016/j.eurpsy.2016.01.060 | E63: 2016 | F63: Exclude | G63: =IF(F63="Include",1,0) -> 0 | H63: Excluded | I63: Excluded | J63: Excluded | K63: Other / Not clear | L63: Other specified method | M63: Excluded | N63: Excluded | O63: Not applicable - excluded | P63: Not applicable - excluded | Q63: Not reported in assessed sources | R63: Not ascertainable | S63: Not reported in assessed sources | T63: Not reported in assessed sources | U63: Not reported in assessed sources | V63: Not reported in assessed sources | W63: Reported | X63: Not reported in assessed sources | Y63: Not ascertainable | Z63: Not reported in assessed sources | AA63: Not recorded | AB63: 0 | AC63: 0 | AD63: =IF(AND(G63=1,AB63=0),1,0) -> 0 | AE63: =IF(AND(AD63=1,AC63=0),1,0) -> 0 | AF63: =IF(AND(G63=1,H63<>"Not specified"),1,0) -> 0 | AG63: =IF(AND(AE63=1,AF63=1),1,0) -> 0 | AH63: Supplied abstract/coding notes; no new full-text verification | AI63: https://doi.org/10.1016/j.eurpsy.2016.01.060 | AJ63: EVIDENCIA; original abstract/coding notes and lot source trace; Historical signals: title/abstract/notes; full-text completion not independently established | AK63: Pharmacogenetic group comparison of prolactin; reported PCR genotyping and inferential tests do not establish ML. | AL63: EC3 No qualifying AI evaluation | AM63: Not separately specified | AO63: No additional status determination | AP63: Not documented for this recharting | AQ63: ChatGPT-assisted evidence recharting, 2026-09-08 | AR63: RA | AS63: Not recorded; historical inclusion retained
A64: 63 | B64: Historical | C64: Improving fMRI-Based Autism Severity Identification via Brain Network Distance and Adaptive Label Distribution Learning | D64: 10.1109/tnsre.2024.3516216 | E64: 2025 | F64: Include | G64: =IF(F64="Include",1,0) -> 1 | H64: Diagnosis | I64: Machine Learning | J64: Neuroimaging | K64: HBFND-AMLD adaptive label-distribution learning | L64: Other specified method | M64: Proposed only | N64: Diagnostic decision support | O64: In-decision | P64: Not observed in assessed sources | Q64: Not reported in assessed sources | R64: Not reported in assessed sources | S64: Not reported in assessed sources | T64: Not reported in assessed sources | U64: Not reported in assessed sources | V64: Reported | W64: Not reported in assessed sources | X64: Not reported in assessed sources | Y64: Not ascertainable | Z64: Not reported in assessed sources | AA64: Not recorded | AB64: 0 | AC64: 0 | AD64: =IF(AND(G64=1,AB64=0),1,0) -> 1 | AE64: =IF(AND(AD64=1,AC64=0),1,0) -> 1 | AF64: =IF(AND(G64=1,H64<>"Not specified"),1,0) -> 1 | AG64: =IF(AND(AE64=1,AF64=1),1,0) -> 1 | AH64: Supplied abstract/coding notes; no new full-text verification | AI64: https://doi.org/10.1109/tnsre.2024.3516216 | AJ64: EVIDENCIA; original abstract/coding notes and lot source trace; Historical signals: title/abstract/notes; full-text completion not independently established | AK64: Current symptom-severity identification from fMRI, not prediction of future course. The named method is retained rather than forcing it into an unsupported MLP family. | AL64: Not applicable | AM64: Not separately specified | AO64: No additional status determination | AP64: Not documented for this recharting | AQ64: ChatGPT-assisted evidence recharting, 2026-09-08 | AR64: RA | AS64: Not recorded; historical inclusion retained
A65: 64 | B65: Historical | C65: Leveraging hybrid model of ConvNextBase and LightGBM for early ASD detection via eye-gaze analysis | D65: 10.1016/j.mex.2025.103166 | E65: 2025 | F65: Include | G65: =IF(F65="Include",1,0) -> 1 | H65: Screening | I65: Hybrid | J65: Behavioral images/video/gaze/movement | K65: ConvNeXtBase with LightGBM | L65: Gradient boosting | M65: Research only | N65: Automated measurement/classification | O65: Not observed in assessed sources | P65: Not observed in assessed sources | Q65: Not reported in assessed sources | R65: Not reported in assessed sources | S65: Not reported in assessed sources | T65: Not reported in assessed sources | U65: Not reported in assessed sources | V65: Not reported in assessed sources | W65: Not reported in assessed sources | X65: Not reported in assessed sources | Y65: Not ascertainable | Z65: Not reported in assessed sources | AA65: Not recorded | AB65: 0 | AC65: 0 | AD65: =IF(AND(G65=1,AB65=0),1,0) -> 1 | AE65: =IF(AND(AD65=1,AC65=0),1,0) -> 1 | AF65: =IF(AND(G65=1,H65<>"Not specified"),1,0) -> 1 | AG65: =IF(AND(AE65=1,AF65=1),1,0) -> 1 | AH65: Supplied abstract/coding notes; no new full-text verification | AI65: https://doi.org/10.1016/j.mex.2025.103166 | AJ65: EVIDENCIA; original abstract/coding notes and lot source trace; Historical signals: title/abstract/notes; full-text completion not independently established | AK65: True neural feature extractor plus conventional boosted-tree classifier; public eye-gaze image benchmark, not clinical screening deployment. | AL65: Not applicable | AM65: Not separately specified | AO65: No additional status determination | AP65: Not documented for this recharting | AQ65: ChatGPT-assisted evidence recharting, 2026-09-08 | AS65: Not recorded; historical inclusion retained
A66: 65 | B66: Historical | C66: Modified Grasshopper Optimization Algorithm for detection of Autism Spectrum Disorder | D66: 10.1016/j.phycom.2020.101115 | E66: 2020 | F66: Include | G66: =IF(F66="Include",1,0) -> 1 | H66: Screening | I66: Machine Learning | J66: Structured clinical/questionnaire data | K66: Random forest with modified grasshopper optimization | L66: Random forest | M66: Research only | N66: Triage/questionnaire assessment | O66: Not observed in assessed sources | P66: Not observed in assessed sources | Q66: Not reported in assessed sources | R66: Not reported in assessed sources | S66: Not reported in assessed sources | T66: Not reported in assessed sources | U66: Not reported in assessed sources | V66: Not reported in assessed sources | W66: Not reported in assessed sources | X66: Not reported in assessed sources | Y66: Not ascertainable | Z66: Not reported in assessed sources | AA66: Not recorded | AB66: 0 | AC66: 0 | AD66: =IF(AND(G66=1,AB66=0),1,0) -> 1 | AE66: =IF(AND(AD66=1,AC66=0),1,0) -> 1 | AF66: =IF(AND(G66=1,H66<>"Not specified"),1,0) -> 1 | AG66: =IF(AND(AE66=1,AF66=1),1,0) -> 1 | AH66: Supplied abstract/coding notes; no new full-text verification | AI66: https://doi.org/10.1016/j.phycom.2020.101115 | AJ66: EVIDENCIA; original abstract/coding notes and lot source trace; Historical signals: title/abstract/notes; full-text completion not independently established | AK66: Three age-specific questionnaire screening datasets; repeated model evaluation on different cohorts does not establish external validation or fused data. | AL66: Not applicable | AM66: Not separately specified | AO66: No additional status determination | AP66: Not documented for this recharting | AQ66: ChatGPT-assisted evidence recharting, 2026-09-08 | AR66: RA | AS66: Not recorded; historical inclusion retained
A67: 66 | B67: Historical | C67: Motor Signature Differences Between Autism Spectrum Disorder and Developmental Coordination Disorder, and Their Neural Mechanisms | D67: 10.1007/s10803-023-06171-8 | E67: 2023 | F67: Include | G67: =IF(F67="Include",1,0) -> 1 | H67: Diagnosis | I67: Machine Learning | J67: Behavioral images/video/gaze/movement | K67: Kinematic machine-learning classifier; family unresolved | L67: Other specified method | M67: Research only | N67: Automated measurement/classification | O67: Not observed in assessed sources | P67: Not observed in assessed sources | Q67: Not reported in assessed sources | R67: Not reported in assessed sources | S67: Not reported in assessed sources | T67: Not reported in assessed sources | U67: Not reported in assessed sources | V67: Not reported in assessed sources | W67: Reported | X67: Not reported in assessed sources | Y67: Not ascertainable | Z67: Not reported in assessed sources | AA67: Not recorded | AB67: 0 | AC67: 0 | AD67: =IF(AND(G67=1,AB67=0),1,0) -> 1 | AE67: =IF(AND(AD67=1,AC67=0),1,0) -> 1 | AF67: =IF(AND(G67=1,H67<>"Not specified"),1,0) -> 1 | AG67: =IF(AND(AE67=1,AF67=1),1,0) -> 1 | AH67: Supplied abstract/coding notes; no new full-text verification | AI67: https://doi.org/10.1007/s10803-023-06171-8 | AJ67: EVIDENCIA; original abstract/coding notes and lot source trace; Historical signals: title/abstract/notes; full-text completion not independently established | AK67: Tablet movement classification with ancillary fMRI correlations; principal prediction uses kinematics, not a demonstrated multimodal fused network. | AL67: Not applicable | AM67: Not separately specified | AO67: No additional status determination | AP67: Not documented for this recharting | AQ67: ChatGPT-assisted evidence recharting, 2026-09-08 | AR67: RA | AS67: Not recorded; historical inclusion retained
A68: 67 | B68: Historical | C68: Novelty detection using deep normative modeling for imu-based abnormal movement monitoring in parkinson’s disease and autism spectrum disorders | D68: 10.3390/s18103533 | E68: 2018 | F68: Include | G68: =IF(F68="Include",1,0) -> 1 | H68: Monitoring/intervention | I68: Deep Learning | J68: Behavioral images/video/gaze/movement | K68: Deep normative generative model | L68: Other specified method | M68: Proposed only | N68: Monitoring/longitudinal analysis | O68: Post-decision | P68: Not observed in assessed sources | Q68: Not reported in assessed sources | R68: Not reported in assessed sources | S68: Not reported in assessed sources | T68: Not reported in assessed sources | U68: Not reported in assessed sources | V68: Not reported in assessed sources | W68: Not reported in assessed sources | X68: Not reported in assessed sources | Y68: Not ascertainable | Z68: Not reported in assessed sources | AA68: Not recorded | AB68: 0 | AC68: 0 | AD68: =IF(AND(G68=1,AB68=0),1,0) -> 1 | AE68: =IF(AND(AD68=1,AC68=0),1,0) -> 1 | AF68: =IF(AND(G68=1,H68<>"Not specified"),1,0) -> 1 | AG68: =IF(AND(AE68=1,AF68=1),1,0) -> 1 | AH68: Supplied abstract/coding notes; no new full-text verification | AI68: https://doi.org/10.3390/s18103533 | AJ68: EVIDENCIA; original abstract/coding notes and lot source trace; Historical signals: title/abstract/notes; full-text completion not independently established | AK68: Wearable IMU movement novelty detection is behavioral kinematics rather than electrophysiology. Evaluation is on benchmark datasets, not prospective patient-facing monitoring. | AL68: Not applicable | AM68: Not separately specified | AO68: No additional status determination | AP68: Not documented for this recharting | AQ68: ChatGPT-assisted evidence recharting, 2026-09-08 | AR68: RA | AS68: Not recorded; historical inclusion retained
A69: 68 | B69: Historical | C69: Perceived social support in adults with autism spectrum disorder and attention-deficit/hyperactivity disorder | D69: 10.1002/aur.1735 | E69: 2017 | F69: Include | G69: =IF(F69="Include",1,0) -> 1 | H69: Not specified | I69: Machine Learning | J69: Structured clinical/questionnaire data | K69: Random forest | L69: Random forest | M69: Research only | N69: Research characterization | O69: Not observed in assessed sources | P69: Not observed in assessed sources | Q69: Not reported in assessed sources | R69: Not reported in assessed sources | S69: Not reported in assessed sources | T69: Not reported in assessed sources | U69: Not reported in assessed sources | V69: Not reported in assessed sources | W69: Not reported in assessed sources | X69: Not reported in assessed sources | Y69: Not ascertainable | Z69: Not reported in assessed sources | AA69: Not recorded | AB69: 0 | AC69: 0 | AD69: =IF(AND(G69=1,AB69=0),1,0) -> 1 | AE69: =IF(AND(AD69=1,AC69=0),1,0) -> 1 | AF69: =IF(AND(G69=1,H69<>"Not specified"),1,0) -> 0 | AG69: =IF(AND(AE69=1,AF69=1),1,0) -> 0 | AH69: Supplied abstract/coding notes; no new full-text verification | AI69: https://doi.org/10.1002/aur.1735 | AJ69: EVIDENCIA; original abstract/coding notes and lot source trace; Historical signals: title/abstract/notes; full-text completion not independently established | AK69: Cross-sectional prediction of perceived social support in ASD/ADHD; relevant care characterization but not ASD diagnostic classification or future prognosis. | AL69: Not applicable | AM69: Not separately specified | AO69: No additional status determination | AP69: Not documented for this recharting | AQ69: ChatGPT-assisted evidence recharting, 2026-09-08 | AS69: Not recorded; historical inclusion retained
A70: 69 | B70: Historical | C70: Regional-Asymmetric Adaptive Graph Convolutional Neural Network for Diagnosis of Autism in Children with Resting-State EEG | D70: 10.1109/tnsre.2023.3347134 | E70: 2024 | F70: Include | G70: =IF(F70="Include",1,0) -> 1 | H70: Diagnosis | I70: Deep Learning | J70: Physiological signals | K70: Regional-asymmetric adaptive GCN | L70: GNN | M70: Research only | N70: Automated measurement/classification | O70: Not observed in assessed sources | P70: Not observed in assessed sources | Q70: Not reported in assessed sources | R70: Not reported in assessed sources | S70: Not reported in assessed sources | T70: Not reported in assessed sources | U70: Not reported in assessed sources | V70: Not reported in assessed sources | W70: Not reported in assessed sources | X70: Not reported in assessed sources | Y70: Not ascertainable | Z70: Not reported in assessed sources | AA70: Not recorded | AB70: 0 | AC70: 0 | AD70: =IF(AND(G70=1,AB70=0),1,0) -> 1 | AE70: =IF(AND(AD70=1,AC70=0),1,0) -> 1 | AF70: =IF(AND(G70=1,H70<>"Not specified"),1,0) -> 1 | AG70: =IF(AND(AE70=1,AF70=1),1,0) -> 1 | AH70: Supplied abstract/coding notes; no new full-text verification | AI70: https://doi.org/10.1109/tnsre.2023.3347134 | AJ70: EVIDENCIA; original abstract/coding notes and lot source trace; Historical signals: title/abstract/notes; full-text completion not independently established | AK70: Subject-independent internal cross-validation on resting EEG. Graph convolutional architecture is explicitly identified; no external cohort is described. | AL70: Not applicable | AM70: Not separately specified | AO70: No additional status determination | AP70: Not documented for this recharting | AQ70: ChatGPT-assisted evidence recharting, 2026-09-08 | AR70: RA | AS70: Not recorded; historical inclusion retained
A71: 70 | B71: Historical | C71: Relationship between abnormal intrinsic functional connectivity of subcortices and autism symptoms in high-functioning adults with autism spectrum disorder | D71: 10.1016/j.pscychresns.2023.111762 | E71: 2024 | F71: Include | G71: =IF(F71="Include",1,0) -> 1 | H71: Diagnosis | I71: Machine Learning | J71: Neuroimaging | K71: Multivariate classifier; family unresolved | L71: Other specified method | M71: Research only | N71: Automated measurement/classification | O71: Not observed in assessed sources | P71: Not observed in assessed sources | Q71: Not reported in assessed sources | R71: Not reported in assessed sources | S71: Not reported in assessed sources | T71: Not reported in assessed sources | U71: Not reported in assessed sources | V71: Not reported in assessed sources | W71: Reported | X71: Not reported in assessed sources | Y71: Not ascertainable | Z71: Not reported in assessed sources | AA71: Not recorded | AB71: 0 | AC71: 0 | AD71: =IF(AND(G71=1,AB71=0),1,0) -> 1 | AE71: =IF(AND(AD71=1,AC71=0),1,0) -> 1 | AF71: =IF(AND(G71=1,H71<>"Not specified"),1,0) -> 1 | AG71: =IF(AND(AE71=1,AF71=1),1,0) -> 1 | AH71: Supplied abstract/coding notes; no new full-text verification | AI71: https://doi.org/10.1016/j.pscychresns.2023.111762 | AJ71: EVIDENCIA; original abstract/coding notes and lot source trace; Historical signals: title/abstract/notes; full-text completion not independently established | AK71: Concurrent ASD classification from fMRI or clinical scores. Separate predictors and correlations do not establish temporal prognosis or deep learning. | AL71: Not applicable | AM71: Not separately specified | AO71: No additional status determination | AP71: Not documented for this recharting | AQ71: ChatGPT-assisted evidence recharting, 2026-09-08 | AS71: Not recorded; historical inclusion retained
A72: 72 | B72: Historical | C72: Transdiagnostic symptom subtypes across autism spectrum disorders and attention deficit hyperactivity disorder: validated by measures of neurocognition and structural connectivity | D72: 10.1186/s12888-022-03734-4 | E72: 2022 | F72: Include | G72: =IF(F72="Include",1,0) -> 1 | H72: Diagnosis | I72: Machine Learning | J72: Structured clinical/questionnaire data | K72: Clustering; principal family unresolved | L72: Clustering | M72: Research only | N72: Automated measurement/classification | O72: Not observed in assessed sources | P72: Not observed in assessed sources | Q72: Not reported in assessed sources | R72: Not reported in assessed sources | S72: Not reported in assessed sources | T72: Not reported in assessed sources | U72: Not reported in assessed sources | V72: Not reported in assessed sources | W72: Reported | X72: Not reported in assessed sources | Y72: Not ascertainable | Z72: Not reported in assessed sources | AA72: Not recorded | AB72: 0 | AC72: 0 | AD72: =IF(AND(G72=1,AB72=0),1,0) -> 1 | AE72: =IF(AND(AD72=1,AC72=0),1,0) -> 1 | AF72: =IF(AND(G72=1,H72<>"Not specified"),1,0) -> 1 | AG72: =IF(AND(AE72=1,AF72=1),1,0) -> 1 | AH72: Supplied abstract/coding notes; no new full-text verification | AI72: https://doi.org/10.1186/s12888-022-03734-4 | AJ72: EVIDENCIA; original abstract/coding notes and lot source trace; Historical signals: title/abstract/notes; full-text completion not independently established | AK72: Symptom-defined transdiagnostic subtyping with ancillary cognitive and structural-connectivity validation. Clustering is not automatically deep learning; validation of cluster correlates is not external predictive validation. | AL72: Not applicable | AM72: Not separately specified | AO72: No additional status determination | AP72: Not documented for this recharting | AQ72: ChatGPT-assisted evidence recharting, 2026-09-08 | AR72: RA | AS72: Not recorded; historical inclusion retained
A73: 73 | B73: Historical | C73: A Convolutional Neural Network Combined With Prototype Learning Framework for Brain Functional Network Classification of Autism Spectrum Disorder | D73: 10.1109/tnsre.2021.3120024 | E73: 2021 | F73: Include | G73: =IF(F73="Include",1,0) -> 1 | H73: Diagnosis | I73: Deep Learning | J73: Neuroimaging | K73: CNN with prototype learning | L73: CNN | M73: Research only | N73: Automated measurement/classification | O73: Not observed in assessed sources | P73: Not observed in assessed sources | Q73: Not reported in assessed sources | R73: Not reported in assessed sources | S73: Reported | T73: Not reported in assessed sources | U73: Not reported in assessed sources | V73: Reported | W73: Not reported in assessed sources | X73: Not reported in assessed sources | Y73: Not ascertainable | Z73: Reported | AA73: Not recorded | AB73: 0 | AC73: 0 | AD73: =IF(AND(G73=1,AB73=0),1,0) -> 1 | AE73: =IF(AND(AD73=1,AC73=0),1,0) -> 1 | AF73: =IF(AND(G73=1,H73<>"Not specified"),1,0) -> 1 | AG73: =IF(AND(AE73=1,AF73=1),1,0) -> 1 | AH73: Supplied abstract/coding notes; no new full-text verification | AI73: https://doi.org/10.1109/tnsre.2021.3120024 | AJ73: EVIDENCIA; original abstract/coding notes and lot source trace; Historical signals: title/abstract/notes; full-text completion not independently established | AK73: Multisite fMRI benchmark is explicitly described. Inter-site biomarker claims alone do not establish a held-out-site experiment. | AL73: Not applicable | AM73: Not separately specified | AO73: No additional status determination | AP73: Not documented for this recharting | AQ73: ChatGPT-assisted evidence recharting, 2026-09-08 | AS73: Not recorded; historical inclusion retained
A74: 74 | B74: Historical | C74: A heterogeneous graph convolutional attention network method for classification of autism spectrum disorder | D74: 10.1186/s12859-023-05495-7 | E74: 2023 | F74: Include | G74: =IF(F74="Include",1,0) -> 1 | H74: Diagnosis | I74: Deep Learning | J74: Multiple source categories | K74: Heterogeneous graph convolutional attention network | L74: GNN | M74: Research only | N74: Automated measurement/classification | O74: Not observed in assessed sources | P74: Not observed in assessed sources | Q74: Not reported in assessed sources | R74: Reported | S74: Reported | T74: Not reported in assessed sources | U74: Not reported in assessed sources | V74: Reported | W74: Reported | X74: Not reported in assessed sources | Y74: Not ascertainable | Z74: Reported | AA74: Not recorded | AB74: 0 | AC74: 0 | AD74: =IF(AND(G74=1,AB74=0),1,0) -> 1 | AE74: =IF(AND(AD74=1,AC74=0),1,0) -> 1 | AF74: =IF(AND(G74=1,H74<>"Not specified"),1,0) -> 1 | AG74: =IF(AND(AE74=1,AF74=1),1,0) -> 1 | AH74: Supplied abstract/coding notes; no new full-text verification | AI74: https://doi.org/10.1186/s12859-023-05495-7 | AJ74: EVIDENCIA; original abstract/coding notes and lot source trace; Historical signals: title/abstract/notes; full-text completion not independently established | AK74: Graph framework combines fMRI connectivity and phenotype information; semantic attention is not itself proof of a validated explanation method. | AL74: Not applicable | AM74: Not separately specified | AO74: No additional status determination | AP74: Not documented for this recharting | AQ74: ChatGPT-assisted evidence recharting, 2026-09-08 | AR74: RA | AS74: Not recorded; historical inclusion retained
A75: 75 | B75: Historical | C75: A monitoring system for patients of autism spectrum disorder using artificial intelligence | D75: 10.1007/978-3-030-59277-6_23 | E75: 2020 | F75: Include | G75: =IF(F75="Include",1,0) -> 1 | H75: Monitoring/intervention | I75: Not specified | J75: Multiple source categories | K75: AI monitoring and adaptive learning system; implementation unspecified | L75: Multiple/not uniquely specified | M75: Proposed only | N75: Monitoring/longitudinal analysis | O75: Post-decision | P75: Not observed in assessed sources | Q75: Not reported in assessed sources | R75: Not ascertainable | S75: Not reported in assessed sources | T75: Not reported in assessed sources | U75: Not reported in assessed sources | V75: Not reported in assessed sources | W75: Not reported in assessed sources | X75: Not reported in assessed sources | Y75: Not ascertainable | Z75: Not reported in assessed sources | AA75: Not recorded | AB75: 0 | AC75: 1 | AD75: =IF(AND(G75=1,AB75=0),1,0) -> 1 | AE75: =IF(AND(AD75=1,AC75=0),1,0) -> 0 | AF75: =IF(AND(G75=1,H75<>"Not specified"),1,0) -> 1 | AG75: =IF(AND(AE75=1,AF75=1),1,0) -> 0 | AH75: Publisher abstract and bibliographic metadata | AI75: https://link.springer.com/chapter/10.1007/978-3-030-59277-6_23 | AJ75: Publisher abstract; conference publication metadata | AK75: Proposed sensor and facial-expression monitoring with caregiver alerts. Accessible description does not document a participant-facing empirical evaluation. Accessible abstract proposes a system but does not establish original empirical AI evaluation; retain inherited inclusion with uncertainty and exclude in stricter-evidence sensitivity. | AL75: Not applicable | AM75: Not separately specified | AN75: Accessible abstract proposes a system but does not establish original empirical AI evaluation; retain inherited inclusion with uncertainty and exclude in stricter-evidence sensitivity. | AO75: No additional status determination | AP75: Not documented for this recharting | AQ75: ChatGPT-assisted evidence recharting, 2026-09-08 | AS75: Not recorded; historical inclusion retained
A76: 77 | B76: Historical | C76: Age-Specific Diagnostic Classification of ASD Using Deep Learning Approaches | D76: 10.3233/shti230794 | E76: 2023 | F76: Include | G76: =IF(F76="Include",1,0) -> 1 | H76: Diagnosis | I76: Deep Learning | J76: Neuroimaging | K76: DenseNet201 | L76: CNN | M76: Research only | N76: Automated measurement/classification | O76: Not observed in assessed sources | P76: Not observed in assessed sources | Q76: Not reported in assessed sources | R76: Not reported in assessed sources | S76: Not reported in assessed sources | T76: Not reported in assessed sources | U76: Not reported in assessed sources | V76: Reported | W76: Not reported in assessed sources | X76: Not reported in assessed sources | Y76: Not ascertainable | Z76: Not reported in assessed sources | AA76: Not recorded | AB76: 0 | AC76: 0 | AD76: =IF(AND(G76=1,AB76=0),1,0) -> 1 | AE76: =IF(AND(AD76=1,AC76=0),1,0) -> 1 | AF76: =IF(AND(G76=1,H76<>"Not specified"),1,0) -> 1 | AG76: =IF(AND(AE76=1,AF76=1),1,0) -> 1 | AH76: Supplied abstract/coding notes; no new full-text verification | AI76: https://doi.org/10.3233/shti230794 | AJ76: EVIDENCIA; original abstract/coding notes and lot source trace; Historical signals: title/abstract/notes; full-text completion not independently established | AK76: Functional-connectivity matrices from fMRI are represented as heatmaps; they remain neuroimaging, not EEG or photographs. ABIDE I and II use does not specify independent train-test separation. | AL76: Not applicable | AM76: Not separately specified | AO76: No additional status determination | AP76: Not documented for this recharting | AQ76: ChatGPT-assisted evidence recharting, 2026-09-08 | AR76: RA | AS76: Not recorded; historical inclusion retained
A77: 78 | B77: Historical | C77: An Automatic Framework for Detecting Autism Spectrum Disorder From EEG Signals Using TFD | D77: 10.1109/jsen.2024.3362341 | E77: 2024 | F77: Include | G77: =IF(F77="Include",1,0) -> 1 | H77: Diagnosis | I77: Deep Learning | J77: Physiological signals | K77: ASD-Net CNN | L77: CNN | M77: Research only | N77: Automated measurement/classification | O77: Not observed in assessed sources | P77: Not observed in assessed sources | Q77: Not reported in assessed sources | R77: Not reported in assessed sources | S77: Not reported in assessed sources | T77: Not reported in assessed sources | U77: Not reported in assessed sources | V77: Not reported in assessed sources | W77: Not reported in assessed sources | X77: Not reported in assessed sources | Y77: Not ascertainable | Z77: Not reported in assessed sources | AA77: Not recorded | AB77: 0 | AC77: 0 | AD77: =IF(AND(G77=1,AB77=0),1,0) -> 1 | AE77: =IF(AND(AD77=1,AC77=0),1,0) -> 1 | AF77: =IF(AND(G77=1,H77<>"Not specified"),1,0) -> 1 | AG77: =IF(AND(AE77=1,AF77=1),1,0) -> 1 | AH77: Supplied abstract/coding notes; no new full-text verification | AI77: https://doi.org/10.1109/jsen.2024.3362341 | AJ77: EVIDENCIA; original abstract/coding notes and lot source trace; Historical signals: title/abstract/notes; full-text completion not independently established | AK77: Time-frequency image representations originate from EEG and remain physiological data; alternative transforms do not establish additional sources. | AL77: Not applicable | AM77: Not separately specified | AO77: No additional status determination | AP77: Not documented for this recharting | AQ77: ChatGPT-assisted evidence recharting, 2026-09-08 | AR77: RA | AS77: Not recorded; historical inclusion retained
A78: 79 | B78: Historical | C78: Applying Machine Learning to Kinematic and Eye Movement Features of a Movement Imitation Task to Predict Autism Diagnosis | D78: 10.1038/s41598-020-65384-4 | E78: 2020 | F78: Include | G78: =IF(F78="Include",1,0) -> 1 | H78: Diagnosis | I78: Machine Learning | J78: Behavioral images/video/gaze/movement | K78: Supervised classifier; family unresolved | L78: Other specified method | M78: Research only | N78: Automated measurement/classification | O78: Not observed in assessed sources | P78: Not observed in assessed sources | Q78: Reported | R78: Reported | S78: Reported | T78: Not reported in assessed sources | U78: Not reported in assessed sources | V78: Not reported in assessed sources | W78: Reported | X78: Not reported in assessed sources | Y78: Not ascertainable | Z78: Reported | AA78: Not recorded | AB78: 0 | AC78: 0 | AD78: =IF(AND(G78=1,AB78=0),1,0) -> 1 | AE78: =IF(AND(AD78=1,AC78=0),1,0) -> 1 | AF78: =IF(AND(G78=1,H78<>"Not specified"),1,0) -> 1 | AG78: =IF(AND(AE78=1,AF78=1),1,0) -> 1 | AH78: Supplied abstract/coding notes; no new full-text verification | AI78: https://doi.org/10.1038/s41598-020-65384-4 | AJ78: EVIDENCIA; original abstract/coding notes and lot source trace; Historical signals: title/abstract/notes; full-text completion not independently established | AK78: Motion tracking and eye tracking are explicitly combined and an independent sample is tested; multisource integration can occur within the behavioral domain. | AL78: Not applicable | AM78: Not separately specified | AO78: No additional status determination | AP78: Not documented for this recharting | AQ78: ChatGPT-assisted evidence recharting, 2026-09-08 | AR78: RA | AS78: Not recorded; historical inclusion retained
A79: 80 | B79: Historical | C79: Artificial intelligence analysis of newborn leucocyte epigenomic markers for the prediction of autism | D79: 10.1016/j.brainres.2019.146457 | E79: 2019 | F79: Include | G79: =IF(F79="Include",1,0) -> 1 | H79: Prognosis | I79: Deep Learning | J79: Biological/omics | K79: Deep neural network; architecture unresolved | L79: Other specified method | M79: Research only | N79: Risk/trajectory estimation | O79: Not observed in assessed sources | P79: Not observed in assessed sources | Q79: Not reported in assessed sources | R79: Not reported in assessed sources | S79: Not reported in assessed sources | T79: Not reported in assessed sources | U79: Not reported in assessed sources | V79: Not reported in assessed sources | W79: Not reported in assessed sources | X79: Not reported in assessed sources | Y79: Not ascertainable | Z79: Not reported in assessed sources | AA79: Not recorded | AB79: 0 | AC79: 0 | AD79: =IF(AND(G79=1,AB79=0),1,0) -> 1 | AE79: =IF(AND(AD79=1,AC79=0),1,0) -> 1 | AF79: =IF(AND(G79=1,H79<>"Not specified"),1,0) -> 1 | AG79: =IF(AND(AE79=1,AF79=1),1,0) -> 1 | AH79: Supplied abstract/coding notes; no new full-text verification | AI79: https://doi.org/10.1016/j.brainres.2019.146457 | AJ79: EVIDENCIA; original abstract/coding notes and lot source trace; Historical signals: title/abstract/notes; full-text completion not independently established | AK79: Newborn leukocyte methylation predicts subsequent ASD; biological input, not electrophysiological signal. Main neural architecture is not supplied in abstract. | AL79: Not applicable | AM79: Not separately specified | AO79: No additional status determination | AP79: Not documented for this recharting | AQ79: ChatGPT-assisted evidence recharting, 2026-09-08 | AR79: RA | AS79: Not recorded; historical inclusion retained
A80: 81 | B80: Historical | C80: Autism Detection in Children using Common Spatial Patterns of MEG Signals | D80: 10.1109/embc40787.2023.10340449 | E80: 2023 | F80: Include | G80: =IF(F80="Include",1,0) -> 1 | H80: Diagnosis | I80: Machine Learning | J80: Physiological signals | K80: Common spatial patterns with supervised classifier | L80: Other specified method | M80: Research only | N80: Automated measurement/classification | O80: Not observed in assessed sources | P80: Not observed in assessed sources | Q80: Not reported in assessed sources | R80: Not reported in assessed sources | S80: Not reported in assessed sources | T80: Not reported in assessed sources | U80: Not reported in assessed sources | V80: Not reported in assessed sources | W80: Not reported in assessed sources | X80: Not reported in assessed sources | Y80: Not ascertainable | Z80: Not reported in assessed sources | AA80: Not recorded | AB80: 0 | AC80: 0 | AD80: =IF(AND(G80=1,AB80=0),1,0) -> 1 | AE80: =IF(AND(AD80=1,AC80=0),1,0) -> 1 | AF80: =IF(AND(G80=1,H80<>"Not specified"),1,0) -> 1 | AG80: =IF(AND(AE80=1,AF80=1),1,0) -> 1 | AH80: Supplied abstract/coding notes; no new full-text verification | AI80: https://doi.org/10.1109/embc40787.2023.10340449 | AJ80: EVIDENCIA; original abstract/coding notes and lot source trace; Historical signals: title/abstract/notes; full-text completion not independently established | AK80: MEG band-power classification; spatial patterns are described as putative biomarkers, with no clinician-facing deployment. | AL80: Not applicable | AM80: Not separately specified | AO80: No additional status determination | AP80: Not documented for this recharting | AQ80: ChatGPT-assisted evidence recharting, 2026-09-08 | AR80: RA | AS80: Not recorded; historical inclusion retained
A81: 82 | B81: Historical | C81: Autism Spectrum Disorder detection framework for children based on federated learning integrated CNN-LSTM | D81: 10.1016/j.compbiomed.2023.107539 | E81: 2023 | F81: Include | G81: =IF(F81="Include",1,0) -> 1 | H81: Screening | I81: Deep Learning | J81: Structured clinical/questionnaire data | K81: Federated CNN-LSTM with decision aggregation | L81: Composite/ensemble pipeline | M81: Proposed only | N81: Triage/questionnaire assessment | O81: Pre-decision | P81: Not observed in assessed sources | Q81: Not reported in assessed sources | R81: Not ascertainable | S81: Not reported in assessed sources | T81: Not reported in assessed sources | U81: Not reported in assessed sources | V81: Not reported in assessed sources | W81: Reported | X81: Not reported in assessed sources | Y81: Not ascertainable | Z81: Not reported in assessed sources | AA81: Not recorded | AB81: 0 | AC81: 1 | AD81: =IF(AND(G81=1,AB81=0),1,0) -> 1 | AE81: =IF(AND(AD81=1,AC81=0),1,0) -> 0 | AF81: =IF(AND(G81=1,H81<>"Not specified"),1,0) -> 1 | AG81: =IF(AND(AE81=1,AF81=1),1,0) -> 0 | AH81: Supplied abstract/coding notes; no new full-text verification | AI81: https://doi.org/10.1016/j.compbiomed.2023.107539 | AJ81: EVIDENCIA; original abstract/coding notes and lot source trace; Historical signals: title/abstract/notes; full-text completion not independently established | AK81: Named inputs are structured developmental screening instruments. Federated simulation does not demonstrate deployment, independent clinical sites, or held-out-site generalization; actual cross-instrument patient pairing remains unverified. Federated simulation claims across named instruments; participant linkage and provenance are not established in accessible evidence. | AL81: Not applicable | AM81: Not separately specified | AN81: Federated simulation claims across named instruments; participant linkage and provenance are not established in accessible evidence. | AO81: No additional status determination | AP81: Not documented for this recharting | AQ81: ChatGPT-assisted evidence recharting, 2026-09-08 | AR81: RA | AS81: Not recorded; historical inclusion retained
A82: 83 | B82: Historical | C82: Converging Representations of Attention-Deficit/Hyperactivity Disorder and Autism on Social Media: Linguistic and Topic Analysis of Trends in Reddit Data | D82: 10.2196/70914 | E82: 2025 | F82: Exclude | G82: =IF(F82="Include",1,0) -> 0 | H82: Excluded | I82: Excluded | J82: Excluded | K82: Not specified | L82: Multiple/not uniquely specified | M82: Excluded | N82: Excluded | O82: Not applicable - excluded | P82: Not applicable - excluded | Q82: Not reported in assessed sources | R82: Not reported in assessed sources | S82: Not reported in assessed sources | T82: Not reported in assessed sources | U82: Not reported in assessed sources | V82: Not reported in assessed sources | W82: Not reported in assessed sources | X82: Not reported in assessed sources | Y82: Not ascertainable | Z82: Not reported in assessed sources | AA82: Not recorded | AB82: 0 | AC82: 0 | AD82: =IF(AND(G82=1,AB82=0),1,0) -> 0 | AE82: =IF(AND(AD82=1,AC82=0),1,0) -> 0 | AF82: =IF(AND(G82=1,H82<>"Not specified"),1,0) -> 0 | AG82: =IF(AND(AE82=1,AF82=1),1,0) -> 0 | AH82: Supplied abstract/coding notes; no new full-text verification | AI82: https://doi.org/10.2196/70914 | AJ82: EVIDENCIA; original abstract/coding notes and lot source trace; Historical signals: title/abstract/notes; full-text completion not independently established | AK82: Public discourse convergence on Reddit is the primary endpoint; topic modeling does not classify, assess, monitor, predict care outcomes or provide an ASD intervention. | AL82: EC4 No clinical or care-process model | AM82: Not separately specified | AO82: No additional status determination | AP82: Not documented for this recharting | AQ82: ChatGPT-assisted evidence recharting, 2026-09-08 | AS82: Not recorded; historical inclusion retained
A83: 84 | B83: Historical | C83: Creating a diagnostic assessment model for autism spectrum disorder by differentiating lexicogrammatical choices through machine learning | D83: 10.1371/journal.pone.0311209 | E83: 2024 | F83: Include | G83: =IF(F83="Include",1,0) -> 1 | H83: Diagnosis | I83: Deep Learning | J83: Text/language | K83: DNN for lexicogrammatical and text features | L83: Other specified method | M83: Proposed only | N83: Diagnostic decision support | O83: In-decision | P83: Not observed in assessed sources | Q83: Not reported in assessed sources | R83: Not reported in assessed sources | S83: Reported | T83: Not reported in assessed sources | U83: Not reported in assessed sources | V83: Not reported in assessed sources | W83: Not reported in assessed sources | X83: Not reported in assessed sources | Y83: Not ascertainable | Z83: Reported | AA83: Not recorded | AB83: 0 | AC83: 0 | AD83: =IF(AND(G83=1,AB83=0),1,0) -> 1 | AE83: =IF(AND(AD83=1,AC83=0),1,0) -> 1 | AF83: =IF(AND(G83=1,H83<>"Not specified"),1,0) -> 1 | AG83: =IF(AND(AE83=1,AF83=1),1,0) -> 1 | AH83: Supplied abstract/coding notes; no new full-text verification | AI83: https://doi.org/10.1371/journal.pone.0311209 | AJ83: EVIDENCIA; original abstract/coding notes and lot source trace; Historical signals: title/abstract/notes; full-text completion not independently established | AK83: Spoken language is transcribed and modeled as text; comparison with an interpretable logistic baseline does not establish an RNN architecture. | AL83: Not applicable | AM83: Not separately specified | AO83: No additional status determination | AP83: Not documented for this recharting | AQ83: ChatGPT-assisted evidence recharting, 2026-09-08 | AS83: Not recorded; historical inclusion retained
A84: 85 | B84: Historical | C84: Diagnosing autism spectrum disorder in children using conventional MRI and apparent diffusion coefficient based deep learning algorithms | D84: 10.1007/s00330-021-08239-4 | E84: 2022 | F84: Include | G84: =IF(F84="Include",1,0) -> 1 | H84: Diagnosis | I84: Deep Learning | J84: Neuroimaging | K84: Dual-stream CNN with attention | L84: CNN | M84: Research only | N84: Automated measurement/classification | O84: Not observed in assessed sources | P84: Not observed in assessed sources | Q84: Reported | R84: Reported | S84: Not reported in assessed sources | T84: Not reported in assessed sources | U84: Not reported in assessed sources | V84: Not reported in assessed sources | W84: Reported | X84: Not reported in assessed sources | Y84: Not ascertainable | Z84: Not reported in assessed sources | AA84: Not recorded | AB84: 0 | AC84: 0 | AD84: =IF(AND(G84=1,AB84=0),1,0) -> 1 | AE84: =IF(AND(AD84=1,AC84=0),1,0) -> 1 | AF84: =IF(AND(G84=1,H84<>"Not specified"),1,0) -> 1 | AG84: =IF(AND(AE84=1,AF84=1),1,0) -> 1 | AH84: Supplied abstract/coding notes; no new full-text verification | AI84: https://doi.org/10.1007/s00330-021-08239-4 | AJ84: EVIDENCIA; original abstract/coding notes and lot source trace; Historical signals: title/abstract/notes; full-text completion not independently established | AK84: Additional independently acquired subjects form a test cohort. FLAIR and ADC are explicitly combined; attention as architecture is not sufficient for strict explainability. | AL84: Not applicable | AM84: Not separately specified | AO84: No additional status determination | AP84: Not documented for this recharting | AQ84: ChatGPT-assisted evidence recharting, 2026-09-08 | AR84: RA | AS84: Not recorded; historical inclusion retained
A85: 86 | B85: Historical | C85: Dissecting the heterogeneity of autism spectrum disorder with sensory behavior, brain, and epigenetic factors | D85: 10.1038/s41398-025-03566-2 | E85: 2025 | F85: Include | G85: =IF(F85="Include",1,0) -> 1 | H85: Diagnosis | I85: Machine Learning | J85: Multiple source categories | K85: XGBoost | L85: Gradient boosting | M85: Research only | N85: Automated measurement/classification | O85: Not observed in assessed sources | P85: Not observed in assessed sources | Q85: Not reported in assessed sources | R85: Reported | S85: Not reported in assessed sources | T85: Not reported in assessed sources | U85: Not reported in assessed sources | V85: Not reported in assessed sources | W85: Reported | X85: Not reported in assessed sources | Y85: Not ascertainable | Z85: Not reported in assessed sources | AA85: Not recorded | AB85: 0 | AC85: 0 | AD85: =IF(AND(G85=1,AB85=0),1,0) -> 1 | AE85: =IF(AND(AD85=1,AC85=0),1,0) -> 1 | AF85: =IF(AND(G85=1,H85<>"Not specified"),1,0) -> 1 | AG85: =IF(AND(AE85=1,AF85=1),1,0) -> 1 | AH85: Supplied abstract/coding notes; no new full-text verification | AI85: https://doi.org/10.1038/s41398-025-03566-2 | AJ85: EVIDENCIA; original abstract/coding notes and lot source trace; Historical signals: title/abstract/notes; full-text completion not independently established | AK85: Integrated sensory behavior, neuroimaging and saliva methylation; XGBoost is conventional machine learning, not deep learning. | AL85: Not applicable | AM85: Not separately specified | AO85: No additional status determination | AP85: Not documented for this recharting | AQ85: ChatGPT-assisted evidence recharting, 2026-09-08 | AS85: Not recorded; historical inclusion retained
A86: 88 | B86: Historical | C86: Facial Emotions Are Accurately Encoded in the Neural Signal of Those With Autism Spectrum Disorder: A Deep Learning Approach | D86: 10.1016/j.bpsc.2021.03.015 | E86: 2022 | F86: Include | G86: =IF(F86="Include",1,0) -> 1 | H86: Not specified | I86: Deep Learning | J86: Physiological signals | K86: CNN emotion decoder | L86: CNN | M86: Research only | N86: Research characterization | O86: Not observed in assessed sources | P86: Not observed in assessed sources | Q86: Not ascertainable | R86: Not reported in assessed sources | S86: Reported | T86: Not reported in assessed sources | U86: Not reported in assessed sources | V86: Not reported in assessed sources | W86: Not reported in assessed sources | X86: Not reported in assessed sources | Y86: Not ascertainable | Z86: Reported | AA86: Not recorded | AB86: 0 | AC86: 0 | AD86: =IF(AND(G86=1,AB86=0),1,0) -> 1 | AE86: =IF(AND(AD86=1,AC86=0),1,0) -> 1 | AF86: =IF(AND(G86=1,H86<>"Not specified"),1,0) -> 0 | AG86: =IF(AND(AE86=1,AF86=1),1,0) -> 0 | AH86: Supplied abstract/coding notes; no new full-text verification | AI86: https://doi.org/10.1016/j.bpsc.2021.03.015 | AJ86: EVIDENCIA; original abstract/coding notes and lot source trace; Historical signals: title/abstract/notes; full-text completion not independently established | AK86: EEG emotion decoding across ASD and non-ASD samples is mechanistic characterization, not an evaluated intervention. Replication across samples does not alone establish transfer of a frozen classifier. Independent sample replication reported; a trained-model transfer test is not established in accessible abstract. | AL86: Not applicable | AM86: Not separately specified | AO86: No additional status determination | AP86: Not documented for this recharting | AQ86: ChatGPT-assisted evidence recharting, 2026-09-08 | AR86: RA | AS86: Not recorded; historical inclusion retained
A87: 89 | B87: Historical | C87: Feasibility Testing of a Wearable Behavioral Aid for Social Learning in Children with Autism | D87: 10.1055/s-0038-1626727 | E87: 2018 | F87: Include | G87: =IF(F87="Include",1,0) -> 1 | H87: Monitoring/intervention | I87: Machine Learning | J87: Behavioral images/video/gaze/movement | K87: Logistic regression ancillary classifier; wearable labeling system | L87: Logistic regression | M87: Evaluated AI-supported intervention | N87: Assistive support | O87: Post-decision | P87: Post-decision | Q87: Not reported in assessed sources | R87: Not reported in assessed sources | S87: Not reported in assessed sources | T87: Not reported in assessed sources | U87: Not reported in assessed sources | V87: Not reported in assessed sources | W87: Not reported in assessed sources | X87: Reported | Y87: Reported | Z87: Not reported in assessed sources | AA87: Not recorded | AB87: 0 | AC87: 0 | AD87: =IF(AND(G87=1,AB87=0),1,0) -> 1 | AE87: =IF(AND(AD87=1,AC87=0),1,0) -> 1 | AF87: =IF(AND(G87=1,H87<>"Not specified"),1,0) -> 1 | AG87: =IF(AND(AE87=1,AF87=1),1,0) -> 1 | AH87: Supplied abstract/coding notes; no new full-text verification | AI87: https://doi.org/10.1055/s-0038-1626727 | AJ87: EVIDENCIA; original abstract/coding notes and lot source trace; Historical signals: title/abstract/notes; full-text completion not independently established | AK87: Controlled feasibility experiment supplied emotion labels via wearable glasses to participants. The separate ASD classifier is an ancillary analysis, not proof of clinical ASD diagnosis using glasses. Wearable feedback was evaluated in a laboratory; not routine care and not an external validation of ASD diagnosis. | AL87: Not applicable | AM87: Not separately specified | AO87: No additional status determination | AP87: Not documented for this recharting | AQ87: ChatGPT-assisted evidence recharting, 2026-09-08 | AS87: Not recorded; historical inclusion retained
A88: 90 | B88: Historical | C88: Handwriting-Based ADHD Detection for Children Having ASD Using Machine Learning Approaches | D88: 10.1109/access.2023.3302903 | E88: 2023 | F88: Include | G88: =IF(F88="Include",1,0) -> 1 | H88: Diagnosis | I88: Machine Learning | J88: Behavioral images/video/gaze/movement | K88: Random forest | L88: Random forest | M88: Research only | N88: Automated measurement/classification | O88: Not observed in assessed sources | P88: Not observed in assessed sources | Q88: Not reported in assessed sources | R88: Not reported in assessed sources | S88: Reported | T88: Not reported in assessed sources | U88: Not reported in assessed sources | V88: Not reported in assessed sources | W88: Not reported in assessed sources | X88: Not reported in assessed sources | Y88: Not ascertainable | Z88: Reported | AA88: Not recorded | AB88: 0 | AC88: 0 | AD88: =IF(AND(G88=1,AB88=0),1,0) -> 1 | AE88: =IF(AND(AD88=1,AC88=0),1,0) -> 1 | AF88: =IF(AND(G88=1,H88<>"Not specified"),1,0) -> 1 | AG88: =IF(AND(AE88=1,AF88=1),1,0) -> 1 | AH88: Supplied abstract/coding notes; no new full-text verification | AI88: https://doi.org/10.1109/access.2023.3302903 | AJ88: EVIDENCIA; original abstract/coding notes and lot source trace; Historical signals: title/abstract/notes; full-text completion not independently established | AK88: Tablet handwriting features classify ADHD with co-occurring ASD versus healthy controls. Included as ASD-related differential assessment; specificity for ASD alone cannot be inferred. | AL88: Not applicable | AM88: Not separately specified | AO88: No additional status determination | AP88: Not documented for this recharting | AQ88: ChatGPT-assisted evidence recharting, 2026-09-08 | AS88: Not recorded; historical inclusion retained
A89: 91 | B89: Historical | C89: Integrating Graph Convolutional Networks (GCNNs) and Long Short-Term Memory (LSTM) for Efficient Diagnosis of Autism | D89: 10.1007/978-3-031-09342-5_11 | E89: 2022 | F89: Include | G89: =IF(F89="Include",1,0) -> 1 | H89: Diagnosis | I89: Deep Learning | J89: Neuroimaging | K89: GCN-LSTM | L89: Composite/ensemble pipeline | M89: Research only | N89: Automated measurement/classification | O89: Not observed in assessed sources | P89: Not observed in assessed sources | Q89: Not reported in assessed sources | R89: Not reported in assessed sources | S89: Not reported in assessed sources | T89: Not reported in assessed sources | U89: Not reported in assessed sources | V89: Reported | W89: Not reported in assessed sources | X89: Not reported in assessed sources | Y89: Not ascertainable | Z89: Not reported in assessed sources | AA89: Not recorded | AB89: 0 | AC89: 0 | AD89: =IF(AND(G89=1,AB89=0),1,0) -> 1 | AE89: =IF(AND(AD89=1,AC89=0),1,0) -> 1 | AF89: =IF(AND(G89=1,H89<>"Not specified"),1,0) -> 1 | AG89: =IF(AND(AE89=1,AF89=1),1,0) -> 1 | AH89: Supplied abstract/coding notes; no new full-text verification | AI89: https://doi.org/10.1007/978-3-031-09342-5_11 | AJ89: EVIDENCIA; original abstract/coding notes and lot source trace; Historical signals: title/abstract/notes; full-text completion not independently established | AK89: ABIDE fMRI; combining graph and recurrent neural networks remains deep learning, not a conventional-ML/DL hybrid. | AL89: Not applicable | AM89: Not separately specified | AO89: No additional status determination | AP89: Not documented for this recharting | AQ89: ChatGPT-assisted evidence recharting, 2026-09-08 | AS89: Not recorded; historical inclusion retained
A90: 92 | B90: Historical | C90: Learning discriminative functional connectivity networks for identifying Autism spectrum disorder | D90: 10.1016/j.bspc.2024.107466 | E90: 2025 | F90: Include | G90: =IF(F90="Include",1,0) -> 1 | H90: Diagnosis | I90: Machine Learning | J90: Neuroimaging | K90: Supervised functional-connectivity network learning | L90: Other specified method | M90: Research only | N90: Automated measurement/classification | O90: Not observed in assessed sources | P90: Not observed in assessed sources | Q90: Not reported in assessed sources | R90: Not reported in assessed sources | S90: Not reported in assessed sources | T90: Not reported in assessed sources | U90: Not reported in assessed sources | V90: Reported | W90: Not reported in assessed sources | X90: Not reported in assessed sources | Y90: Not ascertainable | Z90: Not reported in assessed sources | AA90: Not recorded | AB90: 0 | AC90: 0 | AD90: =IF(AND(G90=1,AB90=0),1,0) -> 1 | AE90: =IF(AND(AD90=1,AC90=0),1,0) -> 1 | AF90: =IF(AND(G90=1,H90<>"Not specified"),1,0) -> 1 | AG90: =IF(AND(AE90=1,AF90=1),1,0) -> 1 | AH90: Supplied abstract/coding notes; no new full-text verification | AI90: https://doi.org/10.1016/j.bspc.2024.107466 | AJ90: EVIDENCIA; original abstract/coding notes and lot source trace; Historical signals: title/abstract/notes; full-text completion not independently established | AK90: Projection-matrix and connectivity learning, with no deep architecture specified in accessible source. A mathematical brain network is not automatically a neural network. | AL90: Not applicable | AM90: Not separately specified | AO90: No additional status determination | AP90: Not documented for this recharting | AQ90: ChatGPT-assisted evidence recharting, 2026-09-08 | AR90: RA | AS90: Not recorded; historical inclusion retained
A91: 94 | B91: Historical | C91: Optimizing a de novo artificial intelligence-based medical device under a predetermined change control plan: Improved ability to detect or rule out pediatric autism | D91: 10.1016/j.ibmed.2023.100102 | E91: 2023 | F91: Include | G91: =IF(F91="Include",1,0) -> 1 | H91: Diagnosis | I91: Not specified | J91: Not specified | K91: Device threshold-optimization framework; model family unresolved | L91: Other specified method | M91: Proposed only | N91: Diagnostic decision support | O91: In-decision | P91: Not observed in assessed sources | Q91: Not reported in assessed sources | R91: Not reported in assessed sources | S91: Not reported in assessed sources | T91: Not reported in assessed sources | U91: Not reported in assessed sources | V91: Not reported in assessed sources | W91: Not reported in assessed sources | X91: Not reported in assessed sources | Y91: Not ascertainable | Z91: Not reported in assessed sources | AA91: Not recorded | AB91: 0 | AC91: 0 | AD91: =IF(AND(G91=1,AB91=0),1,0) -> 1 | AE91: =IF(AND(AD91=1,AC91=0),1,0) -> 1 | AF91: =IF(AND(G91=1,H91<>"Not specified"),1,0) -> 1 | AG91: =IF(AND(AE91=1,AF91=1),1,0) -> 1 | AH91: Supplied abstract/coding notes; no new full-text verification | AI91: https://doi.org/10.1016/j.ibmed.2023.100102 | AJ91: EVIDENCIA; original abstract/coding notes and lot source trace; Historical signals: title/abstract/notes; full-text completion not independently established | AK91: Authorized device algorithm update is not itself evidence of prospective physician use of the new version. Source describes diagnostic threshold optimization, not general screening or an explicit deep architecture. | AL91: Not applicable | AM91: Not separately specified | AO91: No additional status determination | AP91: Not documented for this recharting | AQ91: ChatGPT-assisted evidence recharting, 2026-09-08 | AR91: RA | AS91: Not recorded; historical inclusion retained
A92: 95 | B92: Historical | C92: Physician Versus Large Language Model Chatbot Responses to Web-Based Questions From Autistic Patients in Chinese: Cross-Sectional Comparative Analysis | D92: 10.2196/54706 | E92: 2024 | F92: Include | G92: =IF(F92="Include",1,0) -> 1 | H92: Monitoring/intervention | I92: Deep Learning | J92: Text/language | K92: GPT-4 and ERNIE Bot language models | L92: Transformer | M92: Research only | N92: Assistive support | O92: Not observed in assessed sources | P92: Not observed in assessed sources | Q92: Not reported in assessed sources | R92: Not reported in assessed sources | S92: Not reported in assessed sources | T92: Not reported in assessed sources | U92: Not reported in assessed sources | V92: Not reported in assessed sources | W92: Not reported in assessed sources | X92: Not reported in assessed sources | Y92: Not ascertainable | Z92: Not reported in assessed sources | AA92: Not recorded | AB92: 0 | AC92: 0 | AD92: =IF(AND(G92=1,AB92=0),1,0) -> 1 | AE92: =IF(AND(AD92=1,AC92=0),1,0) -> 1 | AF92: =IF(AND(G92=1,H92<>"Not specified"),1,0) -> 1 | AG92: =IF(AND(AE92=1,AF92=1),1,0) -> 1 | AH92: Supplied abstract/coding notes; no new full-text verification | AI92: https://doi.org/10.2196/54706 | AJ92: EVIDENCIA; original abstract/coding notes and lot source trace; Historical signals: title/abstract/notes; full-text completion not independently established | AK92: Comparison of generated versus physician answers to archived patient questions; no real-time clinical advice delivery or intervention is evaluated. | AL92: Not applicable | AM92: Not separately specified | AO92: No additional status determination | AP92: Not documented for this recharting | AQ92: ChatGPT-assisted evidence recharting, 2026-09-08 | AR92: RA | AS92: Not recorded; historical inclusion retained
A93: 96 | B93: Historical | C93: Polychlorinated biphenyls influence on autism spectrum disorder risk in the MARBLES cohort | D93: 10.1016/j.envres.2018.12.061 | E93: 2019 | F93: Exclude | G93: =IF(F93="Include",1,0) -> 0 | H93: Excluded | I93: Excluded | J93: Excluded | K93: Logistic Regression | L93: Logistic regression | M93: Excluded | N93: Excluded | O93: Not applicable - excluded | P93: Not applicable - excluded | Q93: Not reported in assessed sources | R93: Not ascertainable | S93: Not reported in assessed sources | T93: Not reported in assessed sources | U93: Not reported in assessed sources | V93: Not reported in assessed sources | W93: Reported | X93: Not reported in assessed sources | Y93: Not ascertainable | Z93: Not reported in assessed sources | AA93: Not recorded | AB93: 0 | AC93: 0 | AD93: =IF(AND(G93=1,AB93=0),1,0) -> 0 | AE93: =IF(AND(AD93=1,AC93=0),1,0) -> 0 | AF93: =IF(AND(G93=1,H93<>"Not specified"),1,0) -> 0 | AG93: =IF(AND(AE93=1,AF93=1),1,0) -> 0 | AH93: Supplied abstract/coding notes; no new full-text verification | AI93: https://doi.org/10.1016/j.envres.2018.12.061 | AJ93: EVIDENCIA; original abstract/coding notes and lot source trace; Historical signals: title/abstract/notes; full-text completion not independently established | AK93: Exposure-association epidemiology with multinomial odds ratios. DL denotes dioxin-like PCB, not deep learning; source notes explicitly identify non-ML analysis. | AL93: EC3 No qualifying AI evaluation | AM93: Not separately specified | AO93: No additional status determination | AP93: Not documented for this recharting | AQ93: ChatGPT-assisted evidence recharting, 2026-09-08 | AS93: Not recorded; historical inclusion retained
A94: 97 | B94: Historical | C94: Predicting Core Characteristics of ASD Through Facial Emotion Recognition and Eye Tracking in Youth. | D94: 10.1109/embc44109.2020.9176843 | E94: 2020 | F94: Include | G94: =IF(F94="Include",1,0) -> 1 | H94: Diagnosis | I94: Machine Learning | J94: Behavioral images/video/gaze/movement | K94: Random forest regressor | L94: Random forest | M94: Research only | N94: Automated measurement/classification | O94: Not observed in assessed sources | P94: Not observed in assessed sources | Q94: Not reported in assessed sources | R94: Reported | S94: Not reported in assessed sources | T94: Not reported in assessed sources | U94: Not reported in assessed sources | V94: Not reported in assessed sources | W94: Reported | X94: Not reported in assessed sources | Y94: Not ascertainable | Z94: Not reported in assessed sources | AA94: Not recorded | AB94: 0 | AC94: 0 | AD94: =IF(AND(G94=1,AB94=0),1,0) -> 1 | AE94: =IF(AND(AD94=1,AC94=0),1,0) -> 1 | AF94: =IF(AND(G94=1,H94<>"Not specified"),1,0) -> 1 | AG94: =IF(AND(AE94=1,AF94=1),1,0) -> 1 | AH94: Supplied abstract/coding notes; no new full-text verification | AI94: https://doi.org/10.1109/embc44109.2020.9176843 | AJ94: EVIDENCIA; original abstract/coding notes and lot source trace; Historical signals: title/abstract/notes; full-text completion not independently established | AK94: Predicts contemporaneous SRS-2/RBS-R scores from emotion-task performance and eye tracking; diagnostic characterization, not a longitudinal prognostic endpoint. | AL94: Not applicable | AM94: Not separately specified | AO94: No additional status determination | AP94: Not documented for this recharting | AQ94: ChatGPT-assisted evidence recharting, 2026-09-08 | AS94: Not recorded; historical inclusion retained
A95: 98 | B95: Historical | C95: Self-supervised machine learning approach for autism detection in young children using MEG signals | D95: 10.1016/j.bspc.2024.106671 | E95: 2024 | F95: Include | G95: =IF(F95="Include",1,0) -> 1 | H95: Diagnosis | I95: Deep Learning | J95: Physiological signals | K95: wav2vec 2.0 transformer embeddings with ANN | L95: Composite/ensemble pipeline | M95: Research only | N95: Automated measurement/classification | O95: Not observed in assessed sources | P95: Not observed in assessed sources | Q95: Not reported in assessed sources | R95: Not reported in assessed sources | S95: Not reported in assessed sources | T95: Not reported in assessed sources | U95: Not reported in assessed sources | V95: Not reported in assessed sources | W95: Not reported in assessed sources | X95: Not reported in assessed sources | Y95: Not ascertainable | Z95: Not reported in assessed sources | AA95: Not recorded | AB95: 0 | AC95: 0 | AD95: =IF(AND(G95=1,AB95=0),1,0) -> 1 | AE95: =IF(AND(AD95=1,AC95=0),1,0) -> 1 | AF95: =IF(AND(G95=1,H95<>"Not specified"),1,0) -> 1 | AG95: =IF(AND(AE95=1,AF95=1),1,0) -> 1 | AH95: Supplied abstract/coding notes; no new full-text verification | AI95: https://doi.org/10.1016/j.bspc.2024.106671 | AJ95: EVIDENCIA; original abstract/coding notes and lot source trace; Historical signals: title/abstract/notes; full-text completion not independently established | AK95: MEG remains the input despite speech pretraining; best reported classifier is neural. An alternative SVM branch is documented but not substituted for the principal pipeline. | AL95: Not applicable | AM95: Not separately specified | AO95: No additional status determination | AP95: Not documented for this recharting | AQ95: ChatGPT-assisted evidence recharting, 2026-09-08 | AR95: RA | AS95: Not recorded; historical inclusion retained
A96: 99 | B96: Historical | C96: Serum Brain-derived neurotrophic factor levels in Chinese children with autism spectrum disorders: A pilot study | D96: 10.1016/j.ijdevneu.2014.06.013 | E96: 2014 | F96: Exclude | G96: =IF(F96="Include",1,0) -> 0 | H96: Excluded | I96: Excluded | J96: Excluded | K96: Other / Not clear | L96: Other specified method | M96: Excluded | N96: Excluded | O96: Not applicable - excluded | P96: Not applicable - excluded | Q96: Not reported in assessed sources | R96: Not reported in assessed sources | S96: Not reported in assessed sources | T96: Not reported in assessed sources | U96: Not reported in assessed sources | V96: Not reported in assessed sources | W96: Not reported in assessed sources | X96: Not reported in assessed sources | Y96: Not ascertainable | Z96: Not reported in assessed sources | AA96: Not recorded | AB96: 0 | AC96: 0 | AD96: =IF(AND(G96=1,AB96=0),1,0) -> 0 | AE96: =IF(AND(AD96=1,AC96=0),1,0) -> 0 | AF96: =IF(AND(G96=1,H96<>"Not specified"),1,0) -> 0 | AG96: =IF(AND(AE96=1,AF96=1),1,0) -> 0 | AH96: Supplied abstract/coding notes; no new full-text verification | AI96: https://doi.org/10.1016/j.ijdevneu.2014.06.013 | AJ96: EVIDENCIA; original abstract/coding notes and lot source trace; Historical signals: title/abstract/notes; full-text completion not independently established | AK96: Serum BDNF association and ROC threshold analysis; no AI model is described and the prior RQ2 adjudication explicitly found no AI/ML system. | AL96: EC3 No qualifying AI evaluation | AM96: Not separately specified | AO96: No additional status determination | AP96: Not documented for this recharting | AQ96: ChatGPT-assisted evidence recharting, 2026-09-08 | AR96: RA | AS96: Not recorded; historical inclusion retained
A97: 100 | B97: Historical | C97: Sex Differences in Functional Gradients and Dynamic Functional Connectivity in Preschool-Aged Children With ASD | D97: 10.1111/cns.70562 | E97: 2025 | F97: Include | G97: =IF(F97="Include",1,0) -> 1 | H97: Diagnosis | I97: Machine Learning | J97: Neuroimaging | K97: Multiple classifiers; principal family unresolved | L97: Multiple/not uniquely specified | M97: Research only | N97: Automated measurement/classification | O97: Not observed in assessed sources | P97: Not observed in assessed sources | Q97: Not reported in assessed sources | R97: Not reported in assessed sources | S97: Not reported in assessed sources | T97: Not reported in assessed sources | U97: Not reported in assessed sources | V97: Not reported in assessed sources | W97: Not reported in assessed sources | X97: Not reported in assessed sources | Y97: Not ascertainable | Z97: Not reported in assessed sources | AA97: Not recorded | AB97: 0 | AC97: 0 | AD97: =IF(AND(G97=1,AB97=0),1,0) -> 1 | AE97: =IF(AND(AD97=1,AC97=0),1,0) -> 1 | AF97: =IF(AND(G97=1,H97<>"Not specified"),1,0) -> 1 | AG97: =IF(AND(AE97=1,AF97=1),1,0) -> 1 | AH97: Supplied abstract/coding notes; no new full-text verification | AI97: https://doi.org/10.1111/cns.70562 | AJ97: EVIDENCIA; original abstract/coding notes and lot source trace; Historical signals: title/abstract/notes; full-text completion not independently established | AK97: Functional-gradient and dynamic-connectivity MRI features classify ASD versus TD; no deep classifier is specified in the accessible abstract. | AL97: Not applicable | AM97: Not separately specified | AO97: No additional status determination | AP97: Not documented for this recharting | AQ97: ChatGPT-assisted evidence recharting, 2026-09-08 | AR97: RA | AS97: Not recorded; historical inclusion retained
A98: 102 | B98: Historical | C98: Toward continuous social phenotyping: Analyzing gaze patterns in an emotion recognition task for children with autism through wearable smart glasses | D98: 10.2196/13810 | E98: 2020 | F98: Include | G98: =IF(F98="Include",1,0) -> 1 | H98: Screening | I98: Machine Learning | J98: Behavioral images/video/gaze/movement | K98: Gaze and emotion-response classifier; family unresolved | L98: Other specified method | M98: Research only | N98: Automated measurement/classification | O98: Not observed in assessed sources | P98: Not observed in assessed sources | Q98: Not reported in assessed sources | R98: Reported | S98: Not reported in assessed sources | T98: Not reported in assessed sources | U98: Not reported in assessed sources | V98: Not reported in assessed sources | W98: Reported | X98: Not reported in assessed sources | Y98: Not ascertainable | Z98: Not reported in assessed sources | AA98: Not recorded | AB98: 0 | AC98: 0 | AD98: =IF(AND(G98=1,AB98=0),1,0) -> 1 | AE98: =IF(AND(AD98=1,AC98=0),1,0) -> 1 | AF98: =IF(AND(G98=1,H98<>"Not specified"),1,0) -> 1 | AG98: =IF(AND(AE98=1,AF98=1),1,0) -> 1 | AH98: Supplied abstract/coding notes; no new full-text verification | AI98: https://doi.org/10.2196/13810 | AJ98: EVIDENCIA; original abstract/coding notes and lot source trace; Historical signals: title/abstract/notes; full-text completion not independently established | AK98: Wearable gaze collection is tested, but diagnostic model performance is investigated offline; a wearable form factor alone does not establish clinical integration. | AL98: Not applicable | AM98: Not separately specified | AO98: No additional status determination | AP98: Not documented for this recharting | AQ98: ChatGPT-assisted evidence recharting, 2026-09-08 | AR98: RA | AS98: Not recorded; historical inclusion retained
A99: 103 | B99: Historical | C99: Using machine learning to identify patterns of lifetime health problems in decedents with autism spectrum disorder | D99: 10.1002/aur.1960 | E99: 2018 | F99: Include | G99: =IF(F99="Include",1,0) -> 1 | H99: Not specified | I99: Machine Learning | J99: Structured clinical/questionnaire data | K99: Random forest | L99: Random forest | M99: Research only | N99: Research characterization | O99: Not observed in assessed sources | P99: Not observed in assessed sources | Q99: Not reported in assessed sources | R99: Not reported in assessed sources | S99: Not reported in assessed sources | T99: Not reported in assessed sources | U99: Not reported in assessed sources | V99: Not reported in assessed sources | W99: Not reported in assessed sources | X99: Not reported in assessed sources | Y99: Not ascertainable | Z99: Not reported in assessed sources | AA99: Not recorded | AB99: 0 | AC99: 0 | AD99: =IF(AND(G99=1,AB99=0),1,0) -> 1 | AE99: =IF(AND(AD99=1,AC99=0),1,0) -> 1 | AF99: =IF(AND(G99=1,H99<>"Not specified"),1,0) -> 0 | AG99: =IF(AND(AE99=1,AF99=1),1,0) -> 0 | AH99: Supplied abstract/coding notes; no new full-text verification | AI99: https://doi.org/10.1002/aur.1960 | AJ99: EVIDENCIA; original abstract/coding notes and lot source trace; Historical signals: title/abstract/notes; full-text completion not independently established | AK99: Lifetime diagnostic-code patterns in decedents are retrospective care characterization, not prospective monitoring or multisource sensor integration. | AL99: Not applicable | AM99: Not separately specified | AO99: No additional status determination | AP99: Not documented for this recharting | AQ99: ChatGPT-assisted evidence recharting, 2026-09-08 | AS99: Not recorded; historical inclusion retained
A100: 104 | B100: Historical | C100: A Framework for Comparison and Interpretation of Machine Learning Classifiers to Predict Autism on the ABIDE Dataset | D100: 10.1002/hbm.70190 | E100: 2025 | F100: Include | G100: =IF(F100="Include",1,0) -> 1 | H100: Diagnosis | I100: Not specified | J100: Multiple source categories | K100: Ensemble and multiple neural/SVM benchmarks | L100: SVM | M100: Research only | N100: Automated measurement/classification | O100: Not observed in assessed sources | P100: Not observed in assessed sources | Q100: Not reported in assessed sources | R100: Reported | S100: Reported | T100: Reported | U100: Not reported in assessed sources | V100: Reported | W100: Reported | X100: Not reported in assessed sources | Y100: Not ascertainable | Z100: Not reported in assessed sources | AA100: Not recorded | AB100: 0 | AC100: 0 | AD100: =IF(AND(G100=1,AB100=0),1,0) -> 1 | AE100: =IF(AND(AD100=1,AC100=0),1,0) -> 1 | AF100: =IF(AND(G100=1,H100<>"Not specified"),1,0) -> 1 | AG100: =IF(AND(AE100=1,AF100=1),1,0) -> 1 | AH100: Supplied abstract/coding notes; no new full-text verification | AI100: https://doi.org/10.1002/hbm.70190 | AJ100: EVIDENCIA; original abstract/coding notes and lot source trace; Historical signals: title/abstract/notes; full-text completion not independently established | AK100: Explicit benchmark compares heterogeneous models under equal testing conditions. Do not call comparison itself a hybrid pipeline; retain ensemble/multiple-model status and explicit SmoothGrad explanations. | AL100: Not applicable | AM100: Not separately specified | AO100: No additional status determination | AP100: Not documented for this recharting | AQ100: ChatGPT-assisted evidence recharting, 2026-09-08 | AS100: Not recorded; historical inclusion retained
A101: 105 | B101: Historical | C101: A Novel Deep Learning Approach for Recognizing Stereotypical Motor Movements within and across Subjects on the Autism Spectrum Disorder | D101: 10.1155/2018/7186762 | E101: 2018 | F101: Include | G101: =IF(F101="Include",1,0) -> 1 | H101: Monitoring/intervention | I101: Hybrid | J101: Behavioral images/video/gaze/movement | K101: CNN transfer features with SVM | L101: Composite/ensemble pipeline | M101: Research only | N101: Monitoring/longitudinal analysis | O101: Not observed in assessed sources | P101: Not observed in assessed sources | Q101: Not reported in assessed sources | R101: Not reported in assessed sources | S101: Not reported in assessed sources | T101: Not reported in assessed sources | U101: Not reported in assessed sources | V101: Not reported in assessed sources | W101: Not reported in assessed sources | X101: Not reported in assessed sources | Y101: Not ascertainable | Z101: Not reported in assessed sources | AA101: Not recorded | AB101: 0 | AC101: 0 | AD101: =IF(AND(G101=1,AB101=0),1,0) -> 1 | AE101: =IF(AND(AD101=1,AC101=0),1,0) -> 1 | AF101: =IF(AND(G101=1,H101<>"Not specified"),1,0) -> 1 | AG101: =IF(AND(AE101=1,AF101=1),1,0) -> 1 | AH101: Supplied abstract/coding notes; no new full-text verification | AI101: https://doi.org/10.1155/2018/7186762 | AJ101: EVIDENCIA; original abstract/coding notes and lot source trace; Historical signals: title/abstract/notes; full-text completion not independently established | AK101: Stereotyped-movement recognition from wearable kinematics, including cross-subject transfer. Cross-subject testing is not cross-site robustness. | AL101: Not applicable | AM101: Not separately specified | AO101: No additional status determination | AP101: Not documented for this recharting | AQ101: ChatGPT-assisted evidence recharting, 2026-09-08 | AS101: Not recorded; historical inclusion retained
...

Sheet RESUMEN_CIERRE
A1: Resultados descriptivos | Corpus principal
A2: Todos los porcentajes de esta hoja usan N = incluidos; las cinco etapas resueltas usan otro denominador en RESULTADOS_EN.
A4: dimension | B4: category | C4: n | D4: denominator | E4: proportion
A5: cohort | B5: Historical | C5: =COUNTIFS('BASE_CIERRE'!$G$5:$G$458,1,'BASE_CIERRE'!$B$5:$B$458,"Historical") -> 253 | D5: =COUNTIFS('BASE_CIERRE'!$G$5:$G$458,1) -> 428 | E5: =IFERROR(C5/D5,0) -> 0.5911215
A6: cohort | B6: Update | C6: =COUNTIFS('BASE_CIERRE'!$G$5:$G$458,1,'BASE_CIERRE'!$B$5:$B$458,"Update") -> 175 | D6: =COUNTIFS('BASE_CIERRE'!$G$5:$G$458,1) -> 428 | E6: =IFERROR(C6/D6,0) -> 0.4088785
A7: stage_primary | B7: Diagnosis | C7: =COUNTIFS('BASE_CIERRE'!$G$5:$G$458,1,'BASE_CIERRE'!$H$5:$H$458,"Diagnosis") -> 216 | D7: =COUNTIFS('BASE_CIERRE'!$G$5:$G$458,1) -> 428 | E7: =IFERROR(C7/D7,0) -> 0.5046729
A8: stage_primary | B8: Screening | C8: =COUNTIFS('BASE_CIERRE'!$G$5:$G$458,1,'BASE_CIERRE'!$H$5:$H$458,"Screening") -> 113 | D8: =COUNTIFS('BASE_CIERRE'!$G$5:$G$458,1) -> 428 | E8: =IFERROR(C8/D8,0) -> 0.26401869
A9: stage_primary | B9: Monitoring/intervention | C9: =COUNTIFS('BASE_CIERRE'!$G$5:$G$458,1,'BASE_CIERRE'!$H$5:$H$458,"Monitoring/intervention") -> 38 | D9: =COUNTIFS('BASE_CIERRE'!$G$5:$G$458,1) -> 428 | E9: =IFERROR(C9/D9,0) -> 0.088785047
A10: stage_primary | B10: Not specified | C10: =COUNTIFS('BASE_CIERRE'!$G$5:$G$458,1,'BASE_CIERRE'!$H$5:$H$458,"Not specified") -> 31 | D10: =COUNTIFS('BASE_CIERRE'!$G$5:$G$458,1) -> 428 | E10: =IFERROR(C10/D10,0) -> 0.072429907
A11: stage_primary | B11: Prognosis | C11: =COUNTIFS('BASE_CIERRE'!$G$5:$G$458,1,'BASE_CIERRE'!$H$5:$H$458,"Prognosis") -> 22 | D11: =COUNTIFS('BASE_CIERRE'!$G$5:$G$458,1) -> 428 | E11: =IFERROR(C11/D11,0) -> 0.051401869
A12: stage_primary | B12: Prescreening | C12: =COUNTIFS('BASE_CIERRE'!$G$5:$G$458,1,'BASE_CIERRE'!$H$5:$H$458,"Prescreening") -> 8 | D12: =COUNTIFS('BASE_CIERRE'!$G$5:$G$458,1) -> 428 | E12: =IFERROR(C12/D12,0) -> 0.018691589
A13: ai_type | B13: Machine Learning | C13: =COUNTIFS('BASE_CIERRE'!$G$5:$G$458,1,'BASE_CIERRE'!$I$5:$I$458,"Machine Learning") -> 218 | D13: =COUNTIFS('BASE_CIERRE'!$G$5:$G$458,1) -> 428 | E13: =IFERROR(C13/D13,0) -> 0.50934579
A14: ai_type | B14: Deep Learning | C14: =COUNTIFS('BASE_CIERRE'!$G$5:$G$458,1,'BASE_CIERRE'!$I$5:$I$458,"Deep Learning") -> 161 | D14: =COUNTIFS('BASE_CIERRE'!$G$5:$G$458,1) -> 428 | E14: =IFERROR(C14/D14,0) -> 0.37616822
A15: ai_type | B15: Hybrid | C15: =COUNTIFS('BASE_CIERRE'!$G$5:$G$458,1,'BASE_CIERRE'!$I$5:$I$458,"Hybrid") -> 29 | D15: =COUNTIFS('BASE_CIERRE'!$G$5:$G$458,1) -> 428 | E15: =IFERROR(C15/D15,0) -> 0.067757009
A16: ai_type | B16: Not specified | C16: =COUNTIFS('BASE_CIERRE'!$G$5:$G$458,1,'BASE_CIERRE'!$I$5:$I$458,"Not specified") -> 20 | D16: =COUNTIFS('BASE_CIERRE'!$G$5:$G$458,1) -> 428 | E16: =IFERROR(C16/D16,0) -> 0.046728972
A17: data_source_primary | B17: Neuroimaging | C17: =COUNTIFS('BASE_CIERRE'!$G$5:$G$458,1,'BASE_CIERRE'!$J$5:$J$458,"Neuroimaging") -> 101 | D17: =COUNTIFS('BASE_CIERRE'!$G$5:$G$458,1) -> 428 | E17: =IFERROR(C17/D17,0) -> 0.23598131
A18: data_source_primary | B18: Structured clinical/questionnaire data | C18: =COUNTIFS('BASE_CIERRE'!$G$5:$G$458,1,'BASE_CIERRE'!$J$5:$J$458,"Structured clinical/questionnaire data") -> 85 | D18: =COUNTIFS('BASE_CIERRE'!$G$5:$G$458,1) -> 428 | E18: =IFERROR(C18/D18,0) -> 0.19859813
A19: data_source_primary | B19: Behavioral images/video/gaze/movement | C19: =COUNTIFS('BASE_CIERRE'!$G$5:$G$458,1,'BASE_CIERRE'!$J$5:$J$458,"Behavioral images/video/gaze/movement") -> 68 | D19: =COUNTIFS('BASE_CIERRE'!$G$5:$G$458,1) -> 428 | E19: =IFERROR(C19/D19,0) -> 0.1588785
A20: data_source_primary | B20: Multiple source categories | C20: =COUNTIFS('BASE_CIERRE'!$G$5:$G$458,1,'BASE_CIERRE'!$J$5:$J$458,"Multiple source categories") -> 47 | D20: =COUNTIFS('BASE_CIERRE'!$G$5:$G$458,1) -> 428 | E20: =IFERROR(C20/D20,0) -> 0.10981308
A21: data_source_primary | B21: Physiological signals | C21: =COUNTIFS('BASE_CIERRE'!$G$5:$G$458,1,'BASE_CIERRE'!$J$5:$J$458,"Physiological signals") -> 47 | D21: =COUNTIFS('BASE_CIERRE'!$G$5:$G$458,1) -> 428 | E21: =IFERROR(C21/D21,0) -> 0.10981308
A22: data_source_primary | B22: Biological/omics | C22: =COUNTIFS('BASE_CIERRE'!$G$5:$G$458,1,'BASE_CIERRE'!$J$5:$J$458,"Biological/omics") -> 34 | D22: =COUNTIFS('BASE_CIERRE'!$G$5:$G$458,1) -> 428 | E22: =IFERROR(C22/D22,0) -> 0.079439252
A23: data_source_primary | B23: Text/language | C23: =COUNTIFS('BASE_CIERRE'!$G$5:$G$458,1,'BASE_CIERRE'!$J$5:$J$458,"Text/language") -> 15 | D23: =COUNTIFS('BASE_CIERRE'!$G$5:$G$458,1) -> 428 | E23: =IFERROR(C23/D23,0) -> 0.035046729
A24: data_source_primary | B24: Not specified | C24: =COUNTIFS('BASE_CIERRE'!$G$5:$G$458,1,'BASE_CIERRE'!$J$5:$J$458,"Not specified") -> 15 | D24: =COUNTIFS('BASE_CIERRE'!$G$5:$G$458,1) -> 428 | E24: =IFERROR(C24/D24,0) -> 0.035046729
A25: data_source_primary | B25: Audio/voice | C25: =COUNTIFS('BASE_CIERRE'!$G$5:$G$458,1,'BASE_CIERRE'!$J$5:$J$458,"Audio/voice") -> 9 | D25: =COUNTIFS('BASE_CIERRE'!$G$5:$G$458,1) -> 428 | E25: =IFERROR(C25/D25,0) -> 0.021028037
A26: data_source_primary | B26: Other biomedical/digital data | C26: =COUNTIFS('BASE_CIERRE'!$G$5:$G$458,1,'BASE_CIERRE'!$J$5:$J$458,"Other biomedical/digital data") -> 7 | D26: =COUNTIFS('BASE_CIERRE'!$G$5:$G$458,1) -> 428 | E26: =IFERROR(C26/D26,0) -> 0.01635514
A27: algorithm_family | B27: Other specified method | C27: =COUNTIFS('BASE_CIERRE'!$G$5:$G$458,1,'BASE_CIERRE'!$L$5:$L$458,"Other specified method") -> 94 | D27: =COUNTIFS('BASE_CIERRE'!$G$5:$G$458,1) -> 428 | E27: =IFERROR(C27/D27,0) -> 0.21962617
A28: algorithm_family | B28: Multiple/not uniquely specified | C28: =COUNTIFS('BASE_CIERRE'!$G$5:$G$458,1,'BASE_CIERRE'!$L$5:$L$458,"Multiple/not uniquely specified") -> 63 | D28: =COUNTIFS('BASE_CIERRE'!$G$5:$G$458,1) -> 428 | E28: =IFERROR(C28/D28,0) -> 0.14719626
A29: algorithm_family | B29: Composite/ensemble pipeline | C29: =COUNTIFS('BASE_CIERRE'!$G$5:$G$458,1,'BASE_CIERRE'!$L$5:$L$458,"Composite/ensemble pipeline") -> 57 | D29: =COUNTIFS('BASE_CIERRE'!$G$5:$G$458,1) -> 428 | E29: =IFERROR(C29/D29,0) -> 0.13317757
A30: algorithm_family | B30: CNN | C30: =COUNTIFS('BASE_CIERRE'!$G$5:$G$458,1,'BASE_CIERRE'!$L$5:$L$458,"CNN") -> 54 | D30: =COUNTIFS('BASE_CIERRE'!$G$5:$G$458,1) -> 428 | E30: =IFERROR(C30/D30,0) -> 0.12616822
A31: algorithm_family | B31: SVM | C31: =COUNTIFS('BASE_CIERRE'!$G$5:$G$458,1,'BASE_CIERRE'!$L$5:$L$458,"SVM") -> 27 | D31: =COUNTIFS('BASE_CIERRE'!$G$5:$G$458,1) -> 428 | E31: =IFERROR(C31/D31,0) -> 0.063084112
A32: algorithm_family | B32: Random forest | C32: =COUNTIFS('BASE_CIERRE'!$G$5:$G$458,1,'BASE_CIERRE'!$L$5:$L$458,"Random forest") -> 25 | D32: =COUNTIFS('BASE_CIERRE'!$G$5:$G$458,1) -> 428 | E32: =IFERROR(C32/D32,0) -> 0.058411215
A33: algorithm_family | B33: Transformer | C33: =COUNTIFS('BASE_CIERRE'!$G$5:$G$458,1,'BASE_CIERRE'!$L$5:$L$458,"Transformer") -> 24 | D33: =COUNTIFS('BASE_CIERRE'!$G$5:$G$458,1) -> 428 | E33: =IFERROR(C33/D33,0) -> 0.056074766
A34: algorithm_family | B34: Decision tree/rules | C34: =COUNTIFS('BASE_CIERRE'!$G$5:$G$458,1,'BASE_CIERRE'!$L$5:$L$458,"Decision tree/rules") -> 15 | D34: =COUNTIFS('BASE_CIERRE'!$G$5:$G$458,1) -> 428 | E34: =IFERROR(C34/D34,0) -> 0.035046729
A35: algorithm_family | B35: GNN | C35: =COUNTIFS('BASE_CIERRE'!$G$5:$G$458,1,'BASE_CIERRE'!$L$5:$L$458,"GNN") -> 14 | D35: =COUNTIFS('BASE_CIERRE'!$G$5:$G$458,1) -> 428 | E35: =IFERROR(C35/D35,0) -> 0.03271028
A36: algorithm_family | B36: Gradient boosting | C36: =COUNTIFS('BASE_CIERRE'!$G$5:$G$458,1,'BASE_CIERRE'!$L$5:$L$458,"Gradient boosting") -> 14 | D36: =COUNTIFS('BASE_CIERRE'!$G$5:$G$458,1) -> 428 | E36: =IFERROR(C36/D36,0) -> 0.03271028
A37: algorithm_family | B37: Logistic regression | C37: =COUNTIFS('BASE_CIERRE'!$G$5:$G$458,1,'BASE_CIERRE'!$L$5:$L$458,"Logistic regression") -> 14 | D37: =COUNTIFS('BASE_CIERRE'!$G$5:$G$458,1) -> 428 | E37: =IFERROR(C37/D37,0) -> 0.03271028
A38: algorithm_family | B38: Clustering | C38: =COUNTIFS('BASE_CIERRE'!$G$5:$G$458,1,'BASE_CIERRE'!$L$5:$L$458,"Clustering") -> 10 | D38: =COUNTIFS('BASE_CIERRE'!$G$5:$G$458,1) -> 428 | E38: =IFERROR(C38/D38,0) -> 0.023364486
A39: algorithm_family | B39: MLP/ANN | C39: =COUNTIFS('BASE_CIERRE'!$G$5:$G$458,1,'BASE_CIERRE'!$L$5:$L$458,"MLP/ANN") -> 7 | D39: =COUNTIFS('BASE_CIERRE'!$G$5:$G$458,1) -> 428 | E39: =IFERROR(C39/D39,0) -> 0.01635514
A40: algorithm_family | B40: Recurrent network | C40: =COUNTIFS('BASE_CIERRE'!$G$5:$G$458,1,'BASE_CIERRE'!$L$5:$L$458,"Recurrent network") -> 5 | D40: =COUNTIFS('BASE_CIERRE'!$G$5:$G$458,1) -> 428 | E40: =IFERROR(C40/D40,0) -> 0.011682243
A41: algorithm_family | B41: Autoencoder | C41: =COUNTIFS('BASE_CIERRE'!$G$5:$G$458,1,'BASE_CIERRE'!$L$5:$L$458,"Autoencoder") -> 4 | D41: =COUNTIFS('BASE_CIERRE'!$G$5:$G$458,1) -> 428 | E41: =IFERROR(C41/D41,0) -> 0.0093457944
A42: algorithm_family | B42: k-nearest neighbors | C42: =COUNTIFS('BASE_CIERRE'!$G$5:$G$458,1,'BASE_CIERRE'!$L$5:$L$458,"k-nearest neighbors") -> 1 | D42: =COUNTIFS('BASE_CIERRE'!$G$5:$G$458,1) -> 428 | E42: =IFERROR(C42/D42,0) -> 0.0023364486
A43: rq2_status | B43: Research only | C43: =COUNTIFS('BASE_CIERRE'!$G$5:$G$458,1,'BASE_CIERRE'!$M$5:$M$458,"Research only") -> 311 | D43: =COUNTIFS('BASE_CIERRE'!$G$5:$G$458,1) -> 428 | E43: =IFERROR(C43/D43,0) -> 0.72663551
A44: rq2_status | B44: Proposed only | C44: =COUNTIFS('BASE_CIERRE'!$G$5:$G$458,1,'BASE_CIERRE'!$M$5:$M$458,"Proposed only") -> 98 | D44: =COUNTIFS('BASE_CIERRE'!$G$5:$G$458,1) -> 428 | E44: =IFERROR(C44/D44,0) -> 0.22897196
A45: rq2_status | B45: Evaluated AI-supported intervention | C45: =COUNTIFS('BASE_CIERRE'!$G$5:$G$458,1,'BASE_CIERRE'!$M$5:$M$458,"Evaluated AI-supported intervention") -> 10 | D45: =COUNTIFS('BASE_CIERRE'!$G$5:$G$458,1) -> 428 | E45: =IFERROR(C45/D45,0) -> 0.023364486
A46: rq2_status | B46: Evaluated at point of use | C46: =COUNTIFS('BASE_CIERRE'!$G$5:$G$458,1,'BASE_CIERRE'!$M$5:$M$458,"Evaluated at point of use") -> 8 | D46: =COUNTIFS('BASE_CIERRE'!$G$5:$G$458,1) -> 428 | E46: =IFERROR(C46/D46,0) -> 0.018691589
A47: rq2_status | B47: Evaluated care-delivery platform | C47: =COUNTIFS('BASE_CIERRE'!$G$5:$G$458,1,'BASE_CIERRE'!$M$5:$M$458,"Evaluated care-delivery platform") -> 1 | D47: =COUNTIFS('BASE_CIERRE'!$G$5:$G$458,1) -> 428 | E47: =IFERROR(C47/D47,0) -> 0.0023364486
A48: rq2_role | B48: Automated measurement/classification | C48: =COUNTIFS('BASE_CIERRE'!$G$5:$G$458,1,'BASE_CIERRE'!$N$5:$N$458,"Automated measurement/classification") -> 236 | D48: =COUNTIFS('BASE_CIERRE'!$G$5:$G$458,1) -> 428 | E48: =IFERROR(C48/D48,0) -> 0.55140187
A49: rq2_role | B49: Triage/questionnaire assessment | C49: =COUNTIFS('BASE_CIERRE'!$G$5:$G$458,1,'BASE_CIERRE'!$N$5:$N$458,"Triage/questionnaire assessment") -> 73 | D49: =COUNTIFS('BASE_CIERRE'!$G$5:$G$458,1) -> 428 | E49: =IFERROR(C49/D49,0) -> 0.17056075
A50: rq2_role | B50: Risk/trajectory estimation | C50: =COUNTIFS('BASE_CIERRE'!$G$5:$G$458,1,'BASE_CIERRE'!$N$5:$N$458,"Risk/trajectory estimation") -> 31 | D50: =COUNTIFS('BASE_CIERRE'!$G$5:$G$458,1) -> 428 | E50: =IFERROR(C50/D50,0) -> 0.072429907
A51: rq2_role | B51: Diagnostic decision support | C51: =COUNTIFS('BASE_CIERRE'!$G$5:$G$458,1,'BASE_CIERRE'!$N$5:$N$458,"Diagnostic decision support") -> 26 | D51: =COUNTIFS('BASE_CIERRE'!$G$5:$G$458,1) -> 428 | E51: =IFERROR(C51/D51,0) -> 0.060747664
A52: rq2_role | B52: Research characterization | C52: =COUNTIFS('BASE_CIERRE'!$G$5:$G$458,1,'BASE_CIERRE'!$N$5:$N$458,"Research characterization") -> 25 | D52: =COUNTIFS('BASE_CIERRE'!$G$5:$G$458,1) -> 428 | E52: =IFERROR(C52/D52,0) -> 0.058411215
A53: rq2_role | B53: Monitoring/longitudinal analysis | C53: =COUNTIFS('BASE_CIERRE'!$G$5:$G$458,1,'BASE_CIERRE'!$N$5:$N$458,"Monitoring/longitudinal analysis") -> 13 | D53: =COUNTIFS('BASE_CIERRE'!$G$5:$G$458,1) -> 428 | E53: =IFERROR(C53/D53,0) -> 0.030373832
A54: rq2_role | B54: Adaptive intervention | C54: =COUNTIFS('BASE_CIERRE'!$G$5:$G$458,1,'BASE_CIERRE'!$N$5:$N$458,"Adaptive intervention") -> 12 | D54: =COUNTIFS('BASE_CIERRE'!$G$5:$G$458,1) -> 428 | E54: =IFERROR(C54/D54,0) -> 0.028037383
A55: rq2_role | B55: Assistive support | C55: =COUNTIFS('BASE_CIERRE'!$G$5:$G$458,1,'BASE_CIERRE'!$N$5:$N$458,"Assistive support") -> 7 | D55: =COUNTIFS('BASE_CIERRE'!$G$5:$G$458,1) -> 428 | E55: =IFERROR(C55/D55,0) -> 0.01635514
A56: rq2_role | B56: Mobile assessment | C56: =COUNTIFS('BASE_CIERRE'!$G$5:$G$458,1,'BASE_CIERRE'!$N$5:$N$458,"Mobile assessment") -> 5 | D56: =COUNTIFS('BASE_CIERRE'!$G$5:$G$458,1) -> 428 | E56: =IFERROR(C56/D56,0) -> 0.011682243
A57: observed_decision_timing | B57: Not observed in assessed sources | C57: =COUNTIFS('BASE_CIERRE'!$G$5:$G$458,1,'BASE_CIERRE'!$P$5:$P$458,"Not observed in assessed sources") -> 409 | D57: =COUNTIFS('BASE_CIERRE'!$G$5:$G$458,1) -> 428 | E57: =IFERROR(C57/D57,0) -> 0.95560748
A58: observed_decision_timing | B58: Post-decision | C58: =COUNTIFS('BASE_CIERRE'!$G$5:$G$458,1,'BASE_CIERRE'!$P$5:$P$458,"Post-decision") -> 14 | D58: =COUNTIFS('BASE_CIERRE'!$G$5:$G$458,1) -> 428 | E58: =IFERROR(C58/D58,0) -> 0.03271028
A59: observed_decision_timing | B59: Pre-decision | C59: =COUNTIFS('BASE_CIERRE'!$G$5:$G$458,1,'BASE_CIERRE'!$P$5:$P$458,"Pre-decision") -> 4 | D59: =COUNTIFS('BASE_CIERRE'!$G$5:$G$458,1) -> 428 | E59: =IFERROR(C59/D59,0) -> 0.0093457944
A60: observed_decision_timing | B60: In-decision | C60: =COUNTIFS('BASE_CIERRE'!$G$5:$G$458,1,'BASE_CIERRE'!$P$5:$P$458,"In-decision") -> 1 | D60: =COUNTIFS('BASE_CIERRE'!$G$5:$G$458,1) -> 428 | E60: =IFERROR(C60/D60,0) -> 0.0023364486
A61: source_level | B61: Supplied abstract/coding notes; no new full-text verification | C61: =COUNTIFS('BASE_CIERRE'!$G$5:$G$458,1,'BASE_CIERRE'!$AH$5:$AH$458,"Supplied abstract/coding notes; no new full-text verification") -> 300 | D61: =COUNTIFS('BASE_CIERRE'!$G$5:$G$458,1) -> 428 | E61: =IFERROR(C61/D61,0) -> 0.70093458
A62: source_level | B62: Prior source-specific extraction retained; no new full-text retrieval | C62: =COUNTIFS('BASE_CIERRE'!$G$5:$G$458,1,'BASE_CIERRE'!$AH$5:$AH$458,"Prior source-specific extraction retained; no new full-text retrieval") -> 119 | D62: =COUNTIFS('BASE_CIERRE'!$G$5:$G$458,1) -> 428 | E62: =IFERROR(C62/D62,0) -> 0.27803738
A63: source_level | B63: Primary-source full text (targeted sections) | C63: =COUNTIFS('BASE_CIERRE'!$G$5:$G$458,1,'BASE_CIERRE'!$AH$5:$AH$458,"Primary-source full text (targeted sections)") -> 4 | D63: =COUNTIFS('BASE_CIERRE'!$G$5:$G$458,1) -> 428 | E63: =IFERROR(C63/D63,0) -> 0.0093457944
A64: source_level | B64: Publisher abstract and bibliographic metadata | C64: =COUNTIFS('BASE_CIERRE'!$G$5:$G$458,1,'BASE_CIERRE'!$AH$5:$AH$458,"Publisher abstract and bibliographic metadata") -> 1 | D64: =COUNTIFS('BASE_CIERRE'!$G$5:$G$458,1) -> 428 | E64: =IFERROR(C64/D64,0) -> 0.0023364486
A65: source_level | B65: Author-institution bibliographic record | C65: =COUNTIFS('BASE_CIERRE'!$G$5:$G$458,1,'BASE_CIERRE'!$AH$5:$AH$458,"Author-institution bibliographic record") -> 1 | D65: =COUNTIFS('BASE_CIERRE'!$G$5:$G$458,1) -> 428 | E65: =IFERROR(C65/D65,0) -> 0.0023364486
A66: source_level | B66: Primary-source final article abstract and publication metadata | C66: =COUNTIFS('BASE_CIERRE'!$G$5:$G$458,1,'BASE_CIERRE'!$AH$5:$AH$458,"Primary-source final article abstract and publication metadata") -> 1 | D66: =COUNTIFS('BASE_CIERRE'!$G$5:$G$458,1) -> 428 | E66: =IFERROR(C66/D66,0) -> 0.0023364486
A67: source_level | B67: Primary-source final publication metadata | C67: =COUNTIFS('BASE_CIERRE'!$G$5:$G$458,1,'BASE_CIERRE'!$AH$5:$AH$458,"Primary-source final publication metadata") -> 1 | D67: =COUNTIFS('BASE_CIERRE'!$G$5:$G$458,1) -> 428 | E67: =IFERROR(C67/D67,0) -> 0.0023364486
A68: source_level | B68: Primary-source abstract and final-publication metadata | C68: =COUNTIFS('BASE_CIERRE'!$G$5:$G$458,1,'BASE_CIERRE'!$AH$5:$AH$458,"Primary-source abstract and final-publication metadata") -> 1 | D68: =COUNTIFS('BASE_CIERRE'!$G$5:$G$458,1) -> 428 | E68: =IFERROR(C68/D68,0) -> 0.0023364486

Sheet RQ1_PERFILES
A1: RQ1 | Tecnica, fuente y etapa
A2: Conteos mutuamente exclusivos por informe. Research only no demuestra ausencia de utilidad; Proposed only no demuestra uso clinico.
A4: stage_primary | B4: data_source_primary | C4: ai_type | D4: n | E4: denominator_stage | F4: within_stage_fraction
A5: Diagnosis | B5: Audio/voice | C5: Hybrid | D5: =COUNTIFS('BASE_CIERRE'!$G$5:$G$458,1,'BASE_CIERRE'!$H$5:$H$458,"Diagnosis",'BASE_CIERRE'!$J$5:$J$458,"Audio/voice",'BASE_CIERRE'!$I$5:$I$458,"Hybrid") -> 1 | E5: =COUNTIFS('BASE_CIERRE'!$G$5:$G$458,1,'BASE_CIERRE'!$H$5:$H$458,"Diagnosis") -> 216 | F5: =IFERROR(D5/E5,0) -> 0.0046296296
A6: Diagnosis | B6: Audio/voice | C6: Machine Learning | D6: =COUNTIFS('BASE_CIERRE'!$G$5:$G$458,1,'BASE_CIERRE'!$H$5:$H$458,"Diagnosis",'BASE_CIERRE'!$J$5:$J$458,"Audio/voice",'BASE_CIERRE'!$I$5:$I$458,"Machine Learning") -> 1 | E6: =COUNTIFS('BASE_CIERRE'!$G$5:$G$458,1,'BASE_CIERRE'!$H$5:$H$458,"Diagnosis") -> 216 | F6: =IFERROR(D6/E6,0) -> 0.0046296296
A7: Diagnosis | B7: Audio/voice | C7: Not specified | D7: =COUNTIFS('BASE_CIERRE'!$G$5:$G$458,1,'BASE_CIERRE'!$H$5:$H$458,"Diagnosis",'BASE_CIERRE'!$J$5:$J$458,"Audio/voice",'BASE_CIERRE'!$I$5:$I$458,"Not specified") -> 1 | E7: =COUNTIFS('BASE_CIERRE'!$G$5:$G$458,1,'BASE_CIERRE'!$H$5:$H$458,"Diagnosis") -> 216 | F7: =IFERROR(D7/E7,0) -> 0.0046296296
A8: Diagnosis | B8: Behavioral images/video/gaze/movement | C8: Deep Learning | D8: =COUNTIFS('BASE_CIERRE'!$G$5:$G$458,1,'BASE_CIERRE'!$H$5:$H$458,"Diagnosis",'BASE_CIERRE'!$J$5:$J$458,"Behavioral images/video/gaze/movement",'BASE_CIERRE'!$I$5:$I$458,"Deep Learning") -> 9 | E8: =COUNTIFS('BASE_CIERRE'!$G$5:$G$458,1,'BASE_CIERRE'!$H$5:$H$458,"Diagnosis") -> 216 | F8: =IFERROR(D8/E8,0) -> 0.041666667
A9: Diagnosis | B9: Behavioral images/video/gaze/movement | C9: Hybrid | D9: =COUNTIFS('BASE_CIERRE'!$G$5:$G$458,1,'BASE_CIERRE'!$H$5:$H$458,"Diagnosis",'BASE_CIERRE'!$J$5:$J$458,"Behavioral images/video/gaze/movement",'BASE_CIERRE'!$I$5:$I$458,"Hybrid") -> 2 | E9: =COUNTIFS('BASE_CIERRE'!$G$5:$G$458,1,'BASE_CIERRE'!$H$5:$H$458,"Diagnosis") -> 216 | F9: =IFERROR(D9/E9,0) -> 0.0092592593
A10: Diagnosis | B10: Behavioral images/video/gaze/movement | C10: Machine Learning | D10: =COUNTIFS('BASE_CIERRE'!$G$5:$G$458,1,'BASE_CIERRE'!$H$5:$H$458,"Diagnosis",'BASE_CIERRE'!$J$5:$J$458,"Behavioral images/video/gaze/movement",'BASE_CIERRE'!$I$5:$I$458,"Machine Learning") -> 8 | E10: =COUNTIFS('BASE_CIERRE'!$G$5:$G$458,1,'BASE_CIERRE'!$H$5:$H$458,"Diagnosis") -> 216 | F10: =IFERROR(D10/E10,0) -> 0.037037037
A11: Diagnosis | B11: Behavioral images/video/gaze/movement | C11: Not specified | D11: =COUNTIFS('BASE_CIERRE'!$G$5:$G$458,1,'BASE_CIERRE'!$H$5:$H$458,"Diagnosis",'BASE_CIERRE'!$J$5:$J$458,"Behavioral images/video/gaze/movement",'BASE_CIERRE'!$I$5:$I$458,"Not specified") -> 1 | E11: =COUNTIFS('BASE_CIERRE'!$G$5:$G$458,1,'BASE_CIERRE'!$H$5:$H$458,"Diagnosis") -> 216 | F11: =IFERROR(D11/E11,0) -> 0.0046296296
A12: Diagnosis | B12: Biological/omics | C12: Machine Learning | D12: =COUNTIFS('BASE_CIERRE'!$G$5:$G$458,1,'BASE_CIERRE'!$H$5:$H$458,"Diagnosis",'BASE_CIERRE'!$J$5:$J$458,"Biological/omics",'BASE_CIERRE'!$I$5:$I$458,"Machine Learning") -> 19 | E12: =COUNTIFS('BASE_CIERRE'!$G$5:$G$458,1,'BASE_CIERRE'!$H$5:$H$458,"Diagnosis") -> 216 | F12: =IFERROR(D12/E12,0) -> 0.087962963
